src/dmem_iverilog.v
module DMEM(
    input           clk, write_enable,
    input [31:0]    dataaddr, writedata,
    output [31:0]   readdata
);

reg [31:0] RAM[63:0];

assign readdata = RAM[dataaddr[31:2]];

always @ (posedge clk)
    if (write_enable)
        RAM[dataaddr[31:2]] <= writedata;

/* データメモリの初期化(シミュレーション用) */
integer i;
initial begin
    for (i = 0; i < 32; i = i + 1) begin
        RAM[i] = 64'b0;
    end
end

endmodule

src/imem_iverilog.v
`define MEMDATA "memory.data"

module IMEM(
    input   [31:0]  addr,
    output  [31:0]  instr
);

reg [31:0]  ROM[63:0];

initial begin
    $readmemh(`MEMDATA, ROM, 0, 63);
end

assign  instr = ROM[addr[31:2]];    // pc <= pc + 32'h4;に対応

endmodule

src/alu.v
module ALU(
    input [3:0] alu_op,
    input [31:0] src1,
    input [31:0] src2,
    output reg [31:0] aluout
);

always @* begin
    case (alu_op)
        4'b0000: aluout <= src1 + src2;  // add
        4'b0001: aluout <= src1 - src2;  // sub
        4'b0010: aluout <= src1 & src2;  // and
        4'b0011: aluout <= src1 | src2;  // or
        4'b0100: aluout <= src1 ^ src2;  // xor
    endcase
end

endmodule

src/regfile.v
module REGFILE(
    input clk,
    input write_enable,
    input   [4:0] write_address,
    input   [4:0] read_address1,
    input   [4:0] read_address2,
    output  [31:0] write_data,
    output  [31:0] read_data1,
    output  [31:0] read_data2
);

reg [31:0] register_file [31:0];

// always @ (posedge clk) begin
//     if (write_enable) register_file[write_address] <= write_data;
// end

/* レジスタの初期化(シミュレーション用) */
integer i;
initial begin
    for (i = 0; i < 32; i = i + 1) begin
        register_file[i] = 32'b0;
    end
end

assign read_data1 = (read_address1 != 0) ? register_file[read_address1] : 0;
assign read_data2 = (read_address2 != 0) ? register_file[read_address2] : 0;

endmodule

src/decoder.v

/*
    少なくともaddはよさそう
*/

module DECODER(
    input       [31:0]  instr,
    output reg  [3:0]   alu_op,
    output reg  [31:0]  immext,
    output reg  [4:0]   rd, rs1, rs2
);

wire [6:0] opcode = instr[6:0];
reg [6:0] funct7;
reg [2:0] funct3;

always @* begin
    case (opcode)
        /* R-type */
        7'b0110011:
        begin
            funct7  = instr[31:25];
            funct3  = instr[14:12];
            immext  = 32'bx;
            rd      = instr[11:7];
            rs1     = instr[19:15];
            rs2     = instr[24:20];
        end

        /* I-type */
        7'b0010011,
        7'b0000011,
        7'b1100011:
        begin
            funct7  = 7'bx;
            funct3  = 3'bx;
            immext  = 32'bx;
            rd      = 4'bx;
            rs1     = 4'bx;
            rs2     = 4'bx;
        end

        /* S-type */
        7'b0100011:
        begin
            funct7  = 7'bx;
            funct3  = 3'bx;
            immext  = 32'bx;
            rd      = 4'bx;
            rs1     = 4'bx;
            rs2     = 4'bx;
        end

        /* B-type */
        7'b1100011:
        begin
            funct7  = 7'bx;
            funct3  = 3'bx;
            immext  = 32'bx;
            rd      = 4'bx;
            rs1     = 4'bx;
            rs2     = 4'bx;
        end

        /* U-type */
        7'b011011,
        7'b0010111:
        begin
            funct7  = 7'bx;
            funct3  = 3'bx;
            immext  = 32'bx;
            rd      = 4'bx;
            rs1     = 4'bx;
            rs2     = 4'bx;
        end

        /* J-type */
        7'b1101111:
        begin
            funct7  = 7'bx;
            funct3  = 3'bx;
            immext  = 32'bx;
            rd      = 4'bx;
            rs1     = 4'bx;
            rs2     = 4'bx;
        end

        default:
        begin
            funct7  = 7'bx;
            funct3  = 3'bx;
            immext  = 32'bx;
            rd      = 4'bx;
            rs1     = 4'bx;
            rs2     = 4'bx;
        end
    endcase
end

always @* begin
    case (funct3)
        3'b000: begin
            case (funct7)
                7'b0000000: alu_op = 4'b0000;  // add
                7'b0100000: alu_op = 4'b0001;  // sub
                default:    alu_op = 4'bx;
            endcase
        end
        3'b001: alu_op = 4'b0010;  // sll
        3'b010: alu_op = 4'b0011;  // slt
        3'b011: alu_op = 4'b0100;  // sltu
        3'b100: alu_op = 4'b0101;  // xor
        3'b101: begin
            case (funct7)
                7'b0000000: alu_op = 4'b0110;  // srl
                7'b0100000: alu_op = 4'b0111;  // sra
                default:    alu_op = 4'bx;
            endcase
        end
        3'b110: alu_op = 4'b1000;  // or
        3'b111: alu_op = 4'b1001;  // and
        default:
            alu_op = 4'bx;
    endcase
end

endmodule

// module SIM_DEC();
//     reg clk;
//     reg[31:0] instr;
//     wire[31:0] immext;
//     wire[3:0] alu_op;
//     wire[4:0] rd, rs1, rs2;

//     DECODER dec(
//         .instr(instr),
//         .alu_op(alu_op),
//         .immext(immext),
//         .rd(rd),
//         .rs1(rs1),
//         .rs2(rs2)
//     );

//     initial begin
//         clk = 0;
//         forever #10 clk = ~clk;
//     end

//     initial begin
//         $dumpfile("sim_dec.vcd");
//         $dumpvars(0, dec);
        
//         #10
//         instr = 32'b00000001000010000000100000110011;
        
//         #10 $finish;
//     end

// endmodule

src/haconiwa_core.v
module HACONIWA_CORE(
    input   clk,
    input   reset,
    output reg [31:0]   pc,
    input  [31:0]   instr,
    output  write_enable,
    output [31:0]   dataaddr,
    output [31:0]   writedata,
    input  [31:0]   readdata
);

/* IF */
// pc counter
always @ (posedge clk) begin
    if (reset) begin
        pc <= 32'h0;
    end else begin
        pc <= pc + 32'h4;
    end
    // $display("PC: %h", pc);
end


/* DECODE */
wire [3:0]   alu_op;
wire [31:0]  immext;
wire [4:0]   rd, rs1, rs2;
wire [31:0]  read_data1, read_data2, aluout;

// decoder
DECODER dec(
    .instr(instr),
    .alu_op(alu_op),
    .immext(immext),
    .rd(rd),
    .rs1(rs1),
    .rs2(rs2)
);

// reg
REGFILE regfile(
    .clk(clk),
    // .write_enable(),
    .write_address(rd),
    .read_address1(rs1),
    .read_address2(rs2),
    // .write_data(),
    .read_data1(read_data1),
    .read_data2(read_data2)
);

/* EXE */
// alu
ALU alu(
    .alu_op(alu_op),
    .src1(read_data1),
    .src2(read_data2),
    .aluout(aluout)
);

/* MEM */
// mem


endmodule

src/haconiwa_top.v
module HACONIWA_TOP(
    input   CLOCK_50_B5B, CPU_RESET_n
);

wire [31:0] pc, instr, readdata;

HACONIWA_CORE hcore(
    .clk(CLOCK_50_B5B),
    .reset(!CPU_RESET_n),
    .pc(pc),
    .instr(instr),
    .write_enable(write_enable),
    .dataaddr(dataaddr),
    .writedata(writedata),
    .readdata(readdata)    
);

IMEM imem(
    .addr(pc),
    .instr(instr)
);

DMEM dmem(
    .clk(CLOCK_50_B5B),
    .write_enable(write_enable),
    .dataaddr(dataaddr),
    .writedata(writedata),
    .readdata(readdata)
);

endmodule

module SIMTOP();
    reg clk, reset;

    HACONIWA_TOP htop(
        .CLOCK_50_B5B(clk),
        .CPU_RESET_n(!reset)
    );

    initial begin
        clk = 0;
        forever #5 clk = ~clk;
    end

    initial begin
        #10 reset = 1;
        #20 reset = 0;
        $dumpfile("sim_top_haconiwa.vcd");
        $dumpvars(0, htop);

        #1000 $finish;
    end
endmodule

test/sim_top_haconiwa.vcd
$date
	Wed Apr 30 17:13:08 2025
$end
$version
	Icarus Verilog
$end
$timescale
	1s
$end
$scope module SIMTOP $end
$scope module htop $end
$var wire 1 ! CLOCK_50_B5B $end
$var wire 1 " CPU_RESET_n $end
$var wire 1 # write_enable $end
$var wire 1 $ writedata $end
$var wire 32 % readdata [31:0] $end
$var wire 32 & pc [31:0] $end
$var wire 32 ' instr [31:0] $end
$var wire 1 ( dataaddr $end
$scope module dmem $end
$var wire 1 ! clk $end
$var wire 32 ) dataaddr [31:0] $end
$var wire 32 * readdata [31:0] $end
$var wire 1 # write_enable $end
$var wire 32 + writedata [31:0] $end
$var integer 32 , i [31:0] $end
$upscope $end
$scope module hcore $end
$var wire 1 ! clk $end
$var wire 32 - dataaddr [31:0] $end
$var wire 32 . readdata [31:0] $end
$var wire 1 / reset $end
$var wire 1 # write_enable $end
$var wire 32 0 writedata [31:0] $end
$var wire 5 1 rs2 [4:0] $end
$var wire 5 2 rs1 [4:0] $end
$var wire 32 3 read_data2 [31:0] $end
$var wire 32 4 read_data1 [31:0] $end
$var wire 5 5 rd [4:0] $end
$var wire 32 6 instr [31:0] $end
$var wire 32 7 immext [31:0] $end
$var wire 32 8 aluout [31:0] $end
$var wire 4 9 alu_op [3:0] $end
$var reg 32 : pc [31:0] $end
$scope module alu $end
$var wire 32 ; src2 [31:0] $end
$var wire 32 < src1 [31:0] $end
$var wire 4 = alu_op [3:0] $end
$var reg 32 > aluout [31:0] $end
$upscope $end
$scope module dec $end
$var wire 7 ? opcode [6:0] $end
$var wire 32 @ instr [31:0] $end
$var reg 4 A alu_op [3:0] $end
$var reg 3 B funct3 [2:0] $end
$var reg 7 C funct7 [6:0] $end
$var reg 32 D immext [31:0] $end
$var reg 5 E rd [4:0] $end
$var reg 5 F rs1 [4:0] $end
$var reg 5 G rs2 [4:0] $end
$upscope $end
$scope module regfile $end
$var wire 1 ! clk $end
$var wire 5 H read_address1 [4:0] $end
$var wire 5 I read_address2 [4:0] $end
$var wire 5 J write_address [4:0] $end
$var wire 32 K write_data [31:0] $end
$var wire 1 L write_enable $end
$var wire 32 M read_data2 [31:0] $end
$var wire 32 N read_data1 [31:0] $end
$var integer 32 O i [31:0] $end
$upscope $end
$upscope $end
$scope module imem $end
$var wire 32 P addr [31:0] $end
$var wire 32 Q instr [31:0] $end
$upscope $end
$upscope $end
$upscope $end
$enddefinitions $end
$comment Show the parameter values. $end
$dumpall
$end
#30
$dumpvars
b10100000000000100010011 Q
b0 P
b100000 O
bx N
bx M
zL
bz K
b0xxxx J
b0xxxx I
b0xxxx H
b0xxxx G
b0xxxx F
b0xxxx E
bx D
bx C
bx B
bx A
b10100000000000100010011 @
b10011 ?
bx >
bx =
bx <
bx ;
b0 :
bx 9
bx 8
bx 7
b10100000000000100010011 6
b0xxxx 5
bx 4
bx 3
b0xxxx 2
b0xxxx 1
bz 0
0/
b0 .
bz -
b100000 ,
b0z +
b0 *
b0z )
z(
b10100000000000100010011 '
b0 &
b0 %
z$
z#
1"
0!
$end
#35
b110000000000000110010011 '
b110000000000000110010011 6
b110000000000000110010011 @
b110000000000000110010011 Q
b100 &
b100 :
b100 P
1!
#40
0!
#45
b11111111011100011000001110010011 '
b11111111011100011000001110010011 6
b11111111011100011000001110010011 @
b11111111011100011000001110010011 Q
b1000 &
b1000 :
b1000 P
1!
#50
0!
#55
b0 3
b0 ;
b0 M
b0 4
b0 <
b0 N
b1000 9
b1000 =
b1000 A
b10 1
b10 G
b10 I
b111 2
b111 F
b111 H
b100 5
b100 E
b100 J
b110 B
b0 C
b110011 ?
b1000111110001000110011 '
b1000111110001000110011 6
b1000111110001000110011 @
b1000111110001000110011 Q
b1100 &
b1100 :
b1100 P
1!
#60
0!
#65
b1001 9
b1001 =
b1001 A
b100 1
b100 G
b100 I
b11 2
b11 F
b11 H
b101 5
b101 E
b101 J
b111 B
b10000011111001010110011 '
b10000011111001010110011 6
b10000011111001010110011 @
b10000011111001010110011 Q
b10000 &
b10000 :
b10000 P
1!
#70
0!
#75
b0 8
b0 >
b0 9
b0 =
b0 A
b101 2
b101 F
b101 H
b0 B
b10000101000001010110011 '
b10000101000001010110011 6
b10000101000001010110011 @
b10000101000001010110011 Q
b10100 &
b10100 :
b10100 P
1!
#80
0!
#85
bx 3
bx ;
bx M
bx 4
bx <
bx N
b0xxxx 2
b0xxxx F
b0xxxx H
bx B
bx 9
bx =
bx A
b1100011 ?
b0xxxx 1
b0xxxx G
b0xxxx I
b0xxxx 5
b0xxxx E
b0xxxx J
bx C
b10011100101000011001100011 '
b10011100101000011001100011 6
b10011100101000011001100011 @
b10011100101000011001100011 Q
b11000 &
b11000 :
b11000 P
1!
#90
0!
#95
b0 8
b0 >
b0 3
b0 ;
b0 M
b0 4
b0 <
b0 N
b11 9
b11 =
b11 A
b100 1
b100 G
b100 I
b11 2
b11 F
b11 H
b100 5
b100 E
b100 J
b10 B
b0 C
b110011 ?
b10000011010001000110011 '
b10000011010001000110011 6
b10000011010001000110011 @
b10000011010001000110011 Q
b11100 &
b11100 :
b11100 P
1!
#100
0!
#105
bx 3
bx ;
bx M
bx 4
bx <
bx N
bx C
bx 9
bx =
bx A
b1100011 ?
b0xxxx 1
b0xxxx G
b0xxxx I
b0xxxx 2
b0xxxx F
b0xxxx H
b0xxxx 5
b0xxxx E
b0xxxx J
bx B
b100000010001100011 '
b100000010001100011 6
b100000010001100011 @
b100000010001100011 Q
b100000 &
b100000 :
b100000 P
1!
#110
0!
#115
b10011 ?
b1010010011 '
b1010010011 6
b1010010011 @
b1010010011 Q
b100100 &
b100100 :
b100100 P
1!
#120
0!
#125
b0 8
b0 >
b0 3
b0 ;
b0 M
b0 4
b0 <
b0 N
b11 9
b11 =
b11 A
b10 1
b10 G
b10 I
b111 2
b111 F
b111 H
b100 5
b100 E
b100 J
b10 B
b0 C
b110011 ?
b1000111010001000110011 '
b1000111010001000110011 6
b1000111010001000110011 @
b1000111010001000110011 Q
b101000 &
b101000 :
b101000 P
1!
#130
0!
#135
b0 9
b0 =
b0 A
b101 1
b101 G
b101 I
b100 2
b100 F
b100 H
b111 5
b111 E
b111 J
b0 B
b10100100000001110110011 '
b10100100000001110110011 6
b10100100000001110110011 @
b10100100000001110110011 Q
b101100 &
b101100 :
b101100 P
1!
#140
0!
#145
b1 9
b1 =
b1 A
b10 1
b10 G
b10 I
b111 2
b111 F
b111 H
b100000 C
b1000000001000111000001110110011 '
b1000000001000111000001110110011 6
b1000000001000111000001110110011 @
b1000000001000111000001110110011 Q
b110000 &
b110000 :
b110000 P
1!
#150
0!
#155
bx 3
bx ;
bx M
bx 4
bx <
bx N
bx 9
bx =
bx A
b100011 ?
b0xxxx 1
b0xxxx G
b0xxxx I
b0xxxx 2
b0xxxx F
b0xxxx H
b0xxxx 5
b0xxxx E
b0xxxx J
bx B
bx C
b100011100011010001000100011 '
b100011100011010001000100011 6
b100011100011010001000100011 @
b100011100011010001000100011 Q
b110100 &
b110100 :
b110100 P
1!
#160
0!
#165
b11 ?
b101000000000010000100000011 '
b101000000000010000100000011 6
b101000000000010000100000011 @
b101000000000010000100000011 Q
b111000 &
b111000 :
b111000 P
1!
#170
0!
#175
b1101111 ?
b100000000000000001101111 '
b100000000000000001101111 6
b100000000000000001101111 @
b100000000000000001101111 Q
b111100 &
b111100 :
b111100 P
1!
#180
0!
#185
b10011 ?
b100000000000100010011 '
b100000000000100010011 6
b100000000000100010011 @
b100000000000100010011 Q
b1000000 &
b1000000 :
b1000000 P
1!
#190
0!
#195
b100011 ?
b100001000000010101000100011 '
b100001000000010101000100011 6
b100001000000010101000100011 @
b100001000000010101000100011 Q
b1000100 &
b1000100 :
b1000100 P
1!
#200
0!
#205
bx ?
bx '
bx 6
bx @
bx Q
b1001000 &
b1001000 :
b1001000 P
1!
#210
0!
#215
b1001100 &
b1001100 :
b1001100 P
1!
#220
0!
#225
b1010000 &
b1010000 :
b1010000 P
1!
#230
0!
#235
b1010100 &
b1010100 :
b1010100 P
1!
#240
0!
#245
b1011000 &
b1011000 :
b1011000 P
1!
#250
0!
#255
b1011100 &
b1011100 :
b1011100 P
1!
#260
0!
#265
b1100000 &
b1100000 :
b1100000 P
1!
#270
0!
#275
b1100100 &
b1100100 :
b1100100 P
1!
#280
0!
#285
b1101000 &
b1101000 :
b1101000 P
1!
#290
0!
#295
b1101100 &
b1101100 :
b1101100 P
1!
#300
0!
#305
b1110000 &
b1110000 :
b1110000 P
1!
#310
0!
#315
b1110100 &
b1110100 :
b1110100 P
1!
#320
0!
#325
b1111000 &
b1111000 :
b1111000 P
1!
#330
0!
#335
b1111100 &
b1111100 :
b1111100 P
1!
#340
0!
#345
b10000000 &
b10000000 :
b10000000 P
1!
#350
0!
#355
b10000100 &
b10000100 :
b10000100 P
1!
#360
0!
#365
b10001000 &
b10001000 :
b10001000 P
1!
#370
0!
#375
b10001100 &
b10001100 :
b10001100 P
1!
#380
0!
#385
b10010000 &
b10010000 :
b10010000 P
1!
#390
0!
#395
b10010100 &
b10010100 :
b10010100 P
1!
#400
0!
#405
b10011000 &
b10011000 :
b10011000 P
1!
#410
0!
#415
b10011100 &
b10011100 :
b10011100 P
1!
#420
0!
#425
b10100000 &
b10100000 :
b10100000 P
1!
#430
0!
#435
b10100100 &
b10100100 :
b10100100 P
1!
#440
0!
#445
b10101000 &
b10101000 :
b10101000 P
1!
#450
0!
#455
b10101100 &
b10101100 :
b10101100 P
1!
#460
0!
#465
b10110000 &
b10110000 :
b10110000 P
1!
#470
0!
#475
b10110100 &
b10110100 :
b10110100 P
1!
#480
0!
#485
b10111000 &
b10111000 :
b10111000 P
1!
#490
0!
#495
b10111100 &
b10111100 :
b10111100 P
1!
#500
0!
#505
b11000000 &
b11000000 :
b11000000 P
1!
#510
0!
#515
b11000100 &
b11000100 :
b11000100 P
1!
#520
0!
#525
b11001000 &
b11001000 :
b11001000 P
1!
#530
0!
#535
b11001100 &
b11001100 :
b11001100 P
1!
#540
0!
#545
b11010000 &
b11010000 :
b11010000 P
1!
#550
0!
#555
b11010100 &
b11010100 :
b11010100 P
1!
#560
0!
#565
b11011000 &
b11011000 :
b11011000 P
1!
#570
0!
#575
b11011100 &
b11011100 :
b11011100 P
1!
#580
0!
#585
b11100000 &
b11100000 :
b11100000 P
1!
#590
0!
#595
b11100100 &
b11100100 :
b11100100 P
1!
#600
0!
#605
b11101000 &
b11101000 :
b11101000 P
1!
#610
0!
#615
b11101100 &
b11101100 :
b11101100 P
1!
#620
0!
#625
b11110000 &
b11110000 :
b11110000 P
1!
#630
0!
#635
b11110100 &
b11110100 :
b11110100 P
1!
#640
0!
#645
b11111000 &
b11111000 :
b11111000 P
1!
#650
0!
#655
b11111100 &
b11111100 :
b11111100 P
1!
#660
0!
#665
b100000000 &
b100000000 :
b100000000 P
1!
#670
0!
#675
b100000100 &
b100000100 :
b100000100 P
1!
#680
0!
#685
b100001000 &
b100001000 :
b100001000 P
1!
#690
0!
#695
b100001100 &
b100001100 :
b100001100 P
1!
#700
0!
#705
b100010000 &
b100010000 :
b100010000 P
1!
#710
0!
#715
b100010100 &
b100010100 :
b100010100 P
1!
#720
0!
#725
b100011000 &
b100011000 :
b100011000 P
1!
#730
0!
#735
b100011100 &
b100011100 :
b100011100 P
1!
#740
0!
#745
b100100000 &
b100100000 :
b100100000 P
1!
#750
0!
#755
b100100100 &
b100100100 :
b100100100 P
1!
#760
0!
#765
b100101000 &
b100101000 :
b100101000 P
1!
#770
0!
#775
b100101100 &
b100101100 :
b100101100 P
1!
#780
0!
#785
b100110000 &
b100110000 :
b100110000 P
1!
#790
0!
#795
b100110100 &
b100110100 :
b100110100 P
1!
#800
0!
#805
b100111000 &
b100111000 :
b100111000 P
1!
#810
0!
#815
b100111100 &
b100111100 :
b100111100 P
1!
#820
0!
#825
b101000000 &
b101000000 :
b101000000 P
1!
#830
0!
#835
b101000100 &
b101000100 :
b101000100 P
1!
#840
0!
#845
b101001000 &
b101001000 :
b101001000 P
1!
#850
0!
#855
b101001100 &
b101001100 :
b101001100 P
1!
#860
0!
#865
b101010000 &
b101010000 :
b101010000 P
1!
#870
0!
#875
b101010100 &
b101010100 :
b101010100 P
1!
#880
0!
#885
b101011000 &
b101011000 :
b101011000 P
1!
#890
0!
#895
b101011100 &
b101011100 :
b101011100 P
1!
#900
0!
#905
b101100000 &
b101100000 :
b101100000 P
1!
#910
0!
#915
b101100100 &
b101100100 :
b101100100 P
1!
#920
0!
#925
b101101000 &
b101101000 :
b101101000 P
1!
#930
0!
#935
b101101100 &
b101101100 :
b101101100 P
1!
#940
0!
#945
b101110000 &
b101110000 :
b101110000 P
1!
#950
0!
#955
b101110100 &
b101110100 :
b101110100 P
1!
#960
0!
#965
b101111000 &
b101111000 :
b101111000 P
1!
#970
0!
#975
b101111100 &
b101111100 :
b101111100 P
1!
#980
0!
#985
b110000000 &
b110000000 :
b110000000 P
1!
#990
0!
#995
b110000100 &
b110000100 :
b110000100 P
1!
#1000
0!
#1005
b110001000 &
b110001000 :
b110001000 P
1!
#1010
0!
#1015
b110001100 &
b110001100 :
b110001100 P
1!
#1020
0!
#1025
b110010000 &
b110010000 :
b110010000 P
1!
