src/dmem_iverilog.v
module DMEM(
    input           clk, write_request,
    input   [31:0]  access_address, write_data,
    output  [31:0]  read_data
);

reg [31:0] RAM[63:0];

assign read_data = RAM[access_address[31:2]];

always @ (posedge clk) begin
    if (write_request) begin
        RAM[access_address[31:2]] <= write_data;
    end
end

/* データメモリの初期化(シミュレーション用) */
integer i;
initial begin
    for (i = 0; i < 32; i = i + 1) begin
        RAM[i] = 64'b0;
    end
end

endmodule

src/imem_iverilog.v
`define MEMDATA "memory.data"

module IMEM(
    input   [31:0]  addr,
    output  [31:0]  instr
);

reg [31:0]  ROM[63:0];

initial begin
    $readmemh(`MEMDATA, ROM, 0, 63);
end

assign  instr = ROM[addr[31:2]];    // pc <= pc + 32'h4;に対応

endmodule

src/alu.v
module ALU(
    input       [3:0]   alu_op,
    input       [31:0]  src1,
    input       [31:0]  src2,
    output reg  [31:0]  aluout
);

always @* begin
    case (alu_op)
        4'b0000,
        4'b1010:
        begin
            aluout <= src1 + src2;  // add, addi
        end
        4'b0001: aluout = src1 - src2;  // sub
        4'b0010: aluout = src1 & src2;  // and
        4'b0011: aluout = src1 | src2;  // or
        4'b0100: aluout = src1 ^ src2;  // xor
        4'b1100: aluout = (src1 == src2) ? 32'b1 : 32'b0; // beq
        4'b1101: aluout = (src1 != src2) ? 32'b1 : 32'b0; // bne
        4'b1110: aluout = ($signed(src1) < $signed(src2)) ? 32'b1 : 32'b0; // blt, slt
        4'b1111: aluout = ($signed(src1) >= $signed(src2)) ? 32'b1 : 32'b0; // bge
    endcase
end

endmodule

src/regfile.v
module REGFILE(
    input clk,
    input write_request,
    input   [4:0] write_address,
    input   [4:0] read_address1,
    input   [4:0] read_address2,
    input  [31:0] write_data,
    output  [31:0] read_data1,
    output  [31:0] read_data2
);

reg [31:0] register_file [31:0];

always @ (posedge clk) begin
    if (write_request) register_file[write_address] <= write_data;
end

/* レジスタの初期化(シミュレーション用) */
integer i;
initial begin
    for (i = 0; i < 32; i = i + 1) begin
        register_file[i] = 32'b0;
    end
end

assign read_data1 = (read_address1 != 0) ? register_file[read_address1] : 0;
assign read_data2 = (read_address2 != 0) ? register_file[read_address2] : 0;

endmodule

src/decoder.v
module DECODER(
    input       [31:0]  instr,
    output reg  [3:0]   alu_op,
    output reg  [31:0]  immext,
    output reg  [4:0]   rd, rs1, rs2,
    output reg          reg_write_request,
    output reg          mem_write_request,
    output reg          mem_read_request,
    output reg          imm_enable
);

    reg debug_isload;
    reg debug_isstore;
    wire [6:0] opcode = instr[6:0];
    reg [6:0] funct7;
    reg [2:0] funct3;

    // 初期化（デフォルト値設定）
    always @* begin
        reg_write_request = 1'b0;
        mem_write_request = 1'b0;
        mem_read_request  = 1'b0;
        imm_enable        = 1'b0;
        funct7            = 7'bx;
        funct3            = 3'bx;
        rd                = 5'bx;
        rs1               = 5'bx;
        rs2               = 5'bx;
        immext            = 32'bx;
        debug_isload = 0;
        debug_isstore = 0;

        case (opcode)
            /* R-type */
            7'b0110011: begin
                funct7          = instr[31:25];
                funct3          = instr[14:12];
                immext          = 32'bx;
                rd              = instr[11:7];
                rs1             = instr[19:15];
                rs2             = instr[24:20];
                reg_write_request = 1'b1;
                imm_enable      = 1'b0;
            end

            /* I-type */
            7'b0010011, // addi
            7'b0000011: // lw
            begin
                funct7          = 7'bx;
                funct3          = instr[14:12];
                immext          = {{20{instr[31]}}, instr[31:20]};
                rd              = instr[11:7];
                rs1             = instr[19:15];
                rs2             = 5'bx;
                reg_write_request = 1'b1;
                imm_enable      = 1'b1;
            end

            /* S-type */
            7'b0100011: // sw
            begin
                funct7          = instr[31:25];
                funct3          = instr[14:12];
                immext          = {{20{instr[31]}}, instr[31:25], instr[11:7]};
                rd              = 5'bx;
                rs1             = instr[19:15];
                rs2             = instr[24:20];
                reg_write_request = 1'b0;
                imm_enable          = 1'b1;
                debug_isstore = 1'b1;
            end

            /* B-type */
            7'b1100011: begin // branch instructions
                funct7          = 7'bx;
                funct3          = 3'bx;
                immext          = 32'bx;
                rd              = 5'bx;
                rs1             = 5'bx;
                rs2             = 5'bx;
            end

            /* U-type */
            7'b0110111,  // LUI
            7'b0010111: begin  // AUIPC
                funct7          = 7'bx;
                funct3          = 3'bx;
                immext          = 32'bx;
                rd              = instr[11:7];
                rs1             = 5'bx;
                rs2             = 5'bx;
            end

            /* J-type */
            7'b1101111: begin // jal
                funct7          = 7'bx;
                funct3          = 3'bx;
                immext          = 32'bx;
                rd              = instr[11:7];
                rs1             = 5'bx;
                rs2             = 5'bx;
            end

            default: begin
                funct7          = 7'bx;
                funct3          = 3'bx;
                immext          = 32'bx;
                rd              = 5'bx;
                rs1             = 5'bx;
                rs2             = 5'bx;
            end
        endcase
    end

    // ALU operation decoding
    always @* begin
        case (funct3)
            3'b000: begin
                if (opcode == 7'b0110011) // R-type
                begin
                    case (funct7)
                        7'b0000000: alu_op = 4'b0000;  // add
                        7'b0100000: alu_op = 4'b0001;  // sub
                        default:    alu_op = 4'bx;
                    endcase
                end
                else if (opcode == 7'b0010011) // I-type (addi)
                begin
                    alu_op = 4'b0000;   // addi
                end
                else begin
                    alu_op = 4'bx;
                end
            end

            3'b001: alu_op = 4'b0010;  // sll
            3'b010: begin
                case (opcode)
                    7'b0000011: begin // lw
                        alu_op = 4'b0000; // addでアドレス計算
                        reg_write_request = 1;
                        mem_read_request  = 1;
                        debug_isload = 1;
                    end

                    7'b0100011: begin // sw
                        alu_op = 4'b0000;
                        mem_write_request = 1;
                    end
                    default: alu_op = 4'bx;
                endcase
            end

            3'b011: alu_op = 4'b0100;  // sltu
            3'b100: alu_op = 4'b0101;  // xor
            3'b101: begin
                case (funct7)
                    7'b0000000: alu_op = 4'b0110;  // srl
                    7'b0100000: alu_op = 4'b0111;  // sra
                    default:    alu_op = 4'bx;
                endcase
            end
            3'b110: alu_op = 4'b1000;  // or
            3'b111: alu_op = 4'b1001;  // and
            default: alu_op = 4'bx;
        endcase
    end

endmodule


// module DECODER(
//     input       [31:0]  instr,
//     output reg  [3:0]   alu_op,
//     output reg  [31:0]  immext,
//     output reg  [4:0]   rd, rs1, rs2,
//     output reg          reg_write_request,
//     output reg          mem_write_request,
//     output reg          mem_read_request,
//     output reg          imm_enable
// );

//     wire [6:0] opcode = instr[6:0];
//     wire [2:0] funct3 = instr[14:12];
//     wire [6:0] funct7 = instr[31:25];

//     always @* begin
//         // デフォルト値の設定
//         alu_op             = 4'bxxxx;
//         immext             = 32'b0;
//         rd                 = 5'b0;
//         rs1                = 5'b0;
//         rs2                = 5'b0;
//         reg_write_request  = 1'b0;
//         mem_write_request  = 1'b0;
//         mem_read_request   = 1'b0;
//         imm_enable         = 1'b0;

//         case (opcode)
//             7'b0110011: begin // R-type
//                 rd    = instr[11:7];
//                 rs1   = instr[19:15];
//                 rs2   = instr[24:20];
//                 reg_write_request = 1;
//                 imm_enable = 0;
//                 case (funct3)
//                     3'b000: alu_op = (funct7 == 7'b0100000) ? 4'b0001 : 4'b0000; // sub : add
//                     3'b001: alu_op = 4'b0010; // sll
//                     3'b010: alu_op = 4'b0011; // slt
//                     3'b011: alu_op = 4'b0100; // sltu
//                     3'b100: alu_op = 4'b0101; // xor
//                     3'b101: alu_op = (funct7 == 7'b0100000) ? 4'b0111 : 4'b0110; // sra : srl
//                     3'b110: alu_op = 4'b1000; // or
//                     3'b111: alu_op = 4'b1001; // and
//                     default: alu_op = 4'bxxxx;
//                 endcase
//             end

//             7'b0010011: begin // I-type (addi, etc.)
//                 rd    = instr[11:7];
//                 rs1   = instr[19:15];
//                 immext = {{20{instr[31]}}, instr[31:20]};
//                 reg_write_request = 1;
//                 imm_enable = 1;
//                 case (funct3)
//                     3'b000: alu_op = 4'b0000; // addi
//                     default: alu_op = 4'bxxxx;
//                 endcase
//                 $display("immext1: %h (opcode: %b)", immext, opcode);
//             end

//             7'b0000011: begin // I-type (lw)
//                 rd    = instr[11:7];
//                 rs1   = instr[19:15];
//                 immext = {{20{instr[31]}}, instr[31:20]};
//                 reg_write_request = 1;
//                 mem_read_request  = 1;
//                 imm_enable = 1;
//                 alu_op = 4'b0000; // address = rs1 + imm
//                 $display("immext1: %h (opcode: %b)", immext, opcode);
//             end

//             7'b0100011: begin // S-type (sw)
//                 rs1   = instr[19:15];
//                 rs2   = instr[24:20];
//                 immext = {{27{instr[11]}}, instr[11:7]};
//                 mem_write_request = 1;
//                 imm_enable = 1;
//                 alu_op = 4'b0000; // address = rs1 + imm
//                 $display("immext2: %h (opcode: %b)", immext, opcode);
//             end

//             7'b1100011: begin // B-type (e.g., beq)
//                 rs1   = instr[19:15];
//                 rs2   = instr[24:20];
//                 immext = {{20{instr[31]}}, instr[7], instr[30:25], instr[11:8], 1'b0};
//                 alu_op = 4'b1010; // 仮: 比較命令
//                 imm_enable = 1;
//             end

//             7'b0110111: begin // LUI
//                 rd = instr[11:7];
//                 immext = {instr[31:12], 12'b0};
//                 reg_write_request = 1;
//                 imm_enable = 1;
//                 alu_op = 4'b0000;
//             end

//             7'b0010111: begin // AUIPC
//                 rd = instr[11:7];
//                 immext = {instr[31:12], 12'b0};
//                 reg_write_request = 1;
//                 imm_enable = 1;
//                 alu_op = 4'b0000;
//             end

//             7'b1101111: begin // JAL
//                 rd = instr[11:7];
//                 immext = {{12{instr[31]}}, instr[19:12], instr[20], instr[30:21], 1'b0};
//                 reg_write_request = 1;
//                 imm_enable = 1;
//                 alu_op = 4'b0000;
//             end

//             default: begin
//                 alu_op = 4'bxxxx;
//             end
//         endcase
//     end
// endmodule

src/haconiwa_core.v
module HACONIWA_CORE(
    input               clk,
    input               reset,
    output reg  [31:0]  pc,
    input       [31:0]  instr,
    output      [31:0]  core2mem_access_address,
    input       [31:0]  mem2core_read_data,
    output      [31:0]  core2mem_write_data,
    output              core2mem_write_request
);

/* === Pipeline Registers === */
reg [31:0]  IF_ID_instr;
reg [3:0]   ID_EXE_alu_op;
reg [31:0]  ID_EXE_immext, ID_EXE_read_reg_data1, ID_EXE_read_reg_data2;
reg [4:0]   ID_EXE_rd, ID_EXE_rs1, ID_EXE_rs2;
reg         ID_EXE_reg_write_request, ID_EXE_mem_write_request, ID_EXE_mem_read_request, ID_EXE_imm_enable;
reg [4:0]   EXE_MEM_rd;
reg [31:0]  EXE_MEM_aluout, EXE_MEM_write_data;
reg         EXE_MEM_reg_write_request, EXE_MEM_mem_write_request, EXE_MEM_mem_read_request;
reg         MEM_WB_reg_write_request;
reg [4:0]   MEM_WB_rd;
reg [31:0]  MEM_WB_reg_write_data;

/* === IF Stage === */
always @ (posedge clk) begin
    if (reset) begin
        pc <= 32'h0;
    end else begin
        pc <= pc + 32'h4;
        IF_ID_instr <= instr;
    end
end

/* === ID Stage === */
wire [3:0] alu_op;
wire [31:0] immext, read_reg_data1, read_reg_data2;
wire [4:0] rd, rs1, rs2;
wire dec_reg_write_request, dec_mem_write_request, dec_mem_read_request, dec_imm_enable;

DECODER dec(
    .instr(IF_ID_instr),
    .alu_op(alu_op),
    .rd(rd),
    .rs1(rs1),
    .rs2(rs2),
    .immext(immext),
    .imm_enable(dec_imm_enable),
    .reg_write_request(dec_reg_write_request),
    .mem_write_request(dec_mem_write_request),
    .mem_read_request(dec_mem_read_request)
);

REGFILE regfile(
    .clk(clk),
    .read_address1(rs1),
    .read_address2(rs2),
    .read_data1(read_reg_data1),
    .read_data2(read_reg_data2),
    .write_request(MEM_WB_reg_write_request),
    .write_address(MEM_WB_rd),
    .write_data(MEM_WB_reg_write_data)
);

always @ (posedge clk) begin
    ID_EXE_alu_op <= alu_op;
    ID_EXE_immext <= immext;
    ID_EXE_read_reg_data1 <= read_reg_data1;
    ID_EXE_read_reg_data2 <= read_reg_data2;
    ID_EXE_rd <= rd;
    ID_EXE_rs1 <= rs1;
    ID_EXE_rs2 <= rs2;
    ID_EXE_reg_write_request <= dec_reg_write_request;
    ID_EXE_mem_write_request <= dec_mem_write_request;
    ID_EXE_mem_read_request <= dec_mem_read_request;
    ID_EXE_imm_enable <= dec_imm_enable;
end

/* === EXE Stage === */
wire [31:0] alu_src1, alu_src2, exe_aluout;
assign alu_src1 = ID_EXE_read_reg_data1;
assign alu_src2 = ID_EXE_imm_enable ? ID_EXE_immext : ID_EXE_read_reg_data2;

ALU alu(
    .alu_op(ID_EXE_alu_op),
    .src1(alu_src1),
    .src2(alu_src2),
    .aluout(exe_aluout)
);

always @ (posedge clk) begin
    EXE_MEM_aluout <= exe_aluout;
    EXE_MEM_rd <= ID_EXE_rd;
    EXE_MEM_write_data <= ID_EXE_read_reg_data2;
    EXE_MEM_reg_write_request <= ID_EXE_reg_write_request;
    EXE_MEM_mem_write_request <= ID_EXE_mem_write_request;
    EXE_MEM_mem_read_request <= ID_EXE_mem_read_request;
end

/* === MEM Stage === */
assign core2mem_write_request = EXE_MEM_mem_write_request;
assign core2mem_access_address = EXE_MEM_aluout;    // read/writeリクエスト時のみアドレスを有効化する仕様を排除，カーネル領域へのアクセスなどはMMUなどで制限
assign core2mem_write_data = EXE_MEM_write_data;

always @ (posedge clk) begin
    MEM_WB_reg_write_request <= EXE_MEM_reg_write_request;
    MEM_WB_rd <= EXE_MEM_rd;
    MEM_WB_reg_write_data <= (EXE_MEM_mem_read_request) ? mem2core_read_data : EXE_MEM_aluout;
end

endmodule

src/haconiwa_top.v
module HACONIWA_TOP(
    input   CLOCK_50_B5B, CPU_RESET_n
);

wire [31:0] pc, instr, core2mem_access_address, mem2core_read_data, core2mem_write_data;
wire core2mem_write_request;

HACONIWA_CORE hcore(
    .clk(CLOCK_50_B5B),
    .reset(!CPU_RESET_n),
    .pc(pc),
    .instr(instr),
    .core2mem_access_address(core2mem_access_address),
    .mem2core_read_data(mem2core_read_data),
    .core2mem_write_data(core2mem_write_data),
    .core2mem_write_request(core2mem_write_request)
);

IMEM imem(
    .addr(pc),
    .instr(instr)
);

DMEM dmem(
    .clk(CLOCK_50_B5B),
    .access_address(core2mem_access_address),
    .read_data(mem2core_read_data),
    .write_data(core2mem_write_data),
    .write_request(core2mem_write_request)
);

endmodule

module SIMTOP();
    reg clk, reset;

    HACONIWA_TOP htop(
        .CLOCK_50_B5B(clk),
        .CPU_RESET_n(!reset)
    );

    initial begin
        clk = 0;
        forever #5 clk = ~clk;
    end

    initial begin
        #10 reset = 1;
        #20 reset = 0;
        $dumpfile("sim_top_haconiwa.vcd");
        $dumpvars(0, htop);

        #500 $finish;
    end
endmodule

test/sim_top_haconiwa.vcd
$date
	Fri May  2 12:40:49 2025
$end
$version
	Icarus Verilog
$end
$timescale
	1s
$end
$scope module SIMTOP $end
$scope module htop $end
$var wire 1 ! CLOCK_50_B5B $end
$var wire 1 " CPU_RESET_n $end
$var wire 32 # pc [31:0] $end
$var wire 32 $ mem2core_read_data [31:0] $end
$var wire 32 % instr [31:0] $end
$var wire 1 & core2mem_write_request $end
$var wire 32 ' core2mem_write_data [31:0] $end
$var wire 32 ( core2mem_access_address [31:0] $end
$scope module dmem $end
$var wire 1 ! clk $end
$var wire 32 ) read_data [31:0] $end
$var wire 1 & write_request $end
$var wire 32 * write_data [31:0] $end
$var wire 32 + access_address [31:0] $end
$var integer 32 , i [31:0] $end
$upscope $end
$scope module hcore $end
$var wire 32 - alu_src1 [31:0] $end
$var wire 1 ! clk $end
$var wire 32 . core2mem_access_address [31:0] $end
$var wire 32 / core2mem_write_data [31:0] $end
$var wire 1 & core2mem_write_request $end
$var wire 32 0 mem2core_read_data [31:0] $end
$var wire 1 1 reset $end
$var wire 5 2 rs2 [4:0] $end
$var wire 5 3 rs1 [4:0] $end
$var wire 32 4 read_reg_data2 [31:0] $end
$var wire 32 5 read_reg_data1 [31:0] $end
$var wire 5 6 rd [4:0] $end
$var wire 32 7 instr [31:0] $end
$var wire 32 8 immext [31:0] $end
$var wire 32 9 exe_aluout [31:0] $end
$var wire 1 : dec_reg_write_request $end
$var wire 1 ; dec_mem_write_request $end
$var wire 1 < dec_mem_read_request $end
$var wire 1 = dec_imm_enable $end
$var wire 32 > alu_src2 [31:0] $end
$var wire 4 ? alu_op [3:0] $end
$var reg 32 @ EXE_MEM_aluout [31:0] $end
$var reg 1 A EXE_MEM_mem_read_request $end
$var reg 1 B EXE_MEM_mem_write_request $end
$var reg 5 C EXE_MEM_rd [4:0] $end
$var reg 1 D EXE_MEM_reg_write_request $end
$var reg 32 E EXE_MEM_write_data [31:0] $end
$var reg 4 F ID_EXE_alu_op [3:0] $end
$var reg 1 G ID_EXE_imm_enable $end
$var reg 32 H ID_EXE_immext [31:0] $end
$var reg 1 I ID_EXE_mem_read_request $end
$var reg 1 J ID_EXE_mem_write_request $end
$var reg 5 K ID_EXE_rd [4:0] $end
$var reg 32 L ID_EXE_read_reg_data1 [31:0] $end
$var reg 32 M ID_EXE_read_reg_data2 [31:0] $end
$var reg 1 N ID_EXE_reg_write_request $end
$var reg 5 O ID_EXE_rs1 [4:0] $end
$var reg 5 P ID_EXE_rs2 [4:0] $end
$var reg 32 Q IF_ID_instr [31:0] $end
$var reg 5 R MEM_WB_rd [4:0] $end
$var reg 32 S MEM_WB_reg_write_data [31:0] $end
$var reg 1 T MEM_WB_reg_write_request $end
$var reg 32 U pc [31:0] $end
$scope module alu $end
$var wire 4 V alu_op [3:0] $end
$var wire 32 W src1 [31:0] $end
$var wire 32 X src2 [31:0] $end
$var reg 32 Y aluout [31:0] $end
$upscope $end
$scope module dec $end
$var wire 32 Z instr [31:0] $end
$var wire 7 [ opcode [6:0] $end
$var reg 4 \ alu_op [3:0] $end
$var reg 1 ] debug_isload $end
$var reg 1 ^ debug_isstore $end
$var reg 3 _ funct3 [2:0] $end
$var reg 7 ` funct7 [6:0] $end
$var reg 1 = imm_enable $end
$var reg 32 a immext [31:0] $end
$var reg 1 < mem_read_request $end
$var reg 1 ; mem_write_request $end
$var reg 5 b rd [4:0] $end
$var reg 1 : reg_write_request $end
$var reg 5 c rs1 [4:0] $end
$var reg 5 d rs2 [4:0] $end
$upscope $end
$scope module regfile $end
$var wire 1 ! clk $end
$var wire 5 e read_address1 [4:0] $end
$var wire 5 f read_address2 [4:0] $end
$var wire 5 g write_address [4:0] $end
$var wire 32 h write_data [31:0] $end
$var wire 1 T write_request $end
$var wire 32 i read_data2 [31:0] $end
$var wire 32 j read_data1 [31:0] $end
$var integer 32 k i [31:0] $end
$upscope $end
$upscope $end
$scope module imem $end
$var wire 32 l addr [31:0] $end
$var wire 32 m instr [31:0] $end
$upscope $end
$upscope $end
$upscope $end
$enddefinitions $end
$comment Show the parameter values. $end
$dumpall
$end
#30
$dumpvars
b10011 m
b0 l
b100000 k
bx j
bx i
bx h
bx g
bx f
bx e
bx d
bx c
bx b
bx a
bx `
bx _
x^
x]
bx \
bx [
bx Z
bx Y
bx X
bx W
bx V
b0 U
xT
bx S
bx R
bx Q
bx P
bx O
xN
bx M
bx L
bx K
xJ
xI
bx H
xG
bx F
bx E
xD
bx C
xB
xA
bx @
bx ?
bx >
x=
x<
x;
x:
bx 9
bx 8
b10011 7
bx 6
bx 5
bx 4
bx 3
bx 2
01
bx 0
bx /
bx .
bx -
b100000 ,
bx +
bx *
bx )
bx (
bx '
x&
b10011 %
bx $
b0 #
1"
0!
$end
#35
b0 5
b0 j
b0 ?
b0 \
b0 3
b0 c
b0 e
b0 6
b0 b
b0 8
b0 a
b0 _
0^
0]
1=
0<
0;
1:
b10011 [
b10100000000000010010011 %
b10100000000000010010011 7
b10100000000000010010011 m
b10011 Q
b10011 Z
b100 #
b100 U
b100 l
1!
#40
0!
#45
b0 9
b0 Y
b101 8
b101 a
b0 3
b0 c
b0 e
b1 6
b1 b
b0 _
1=
1:
b10011 %
b10011 7
b10011 m
b0 >
b0 X
b10100000000000010010011 Q
b10100000000000010010011 Z
b1000 #
b1000 U
b1000 l
1G
0I
0J
1N
b0 O
b0 K
b0 -
b0 W
b0 L
b0 H
b0 F
b0 V
1!
#50
0!
#55
b101 9
b101 Y
b0 $
b0 )
b0 0
b101 >
b101 X
b0 8
b0 a
b0 3
b0 c
b0 e
b0 6
b0 b
b0 _
1=
1:
0A
0&
0B
1D
b0 C
b0 (
b0 +
b0 .
b0 @
b1 K
b101 H
b10011 Q
b10011 Z
b1100 #
b1100 U
b1100 l
1!
#60
0!
#65
b0 9
b0 Y
b0 >
b0 X
b10000 #
b10000 U
b10000 l
b0 K
b0 H
b1 C
b101 (
b101 +
b101 .
b101 @
b0 S
b0 h
b0 R
b0 g
1T
1!
#70
0!
#75
b101000000000000100010011 %
b101000000000000100010011 7
b101000000000000100010011 m
b101 S
b101 h
b1 R
b1 g
b0 C
b0 (
b0 +
b0 .
b0 @
b10100 #
b10100 U
b10100 l
1!
#80
0!
#85
b1010 8
b1010 a
b0 3
b0 c
b0 e
b10 6
b10 b
b0 _
1=
1:
b10011 %
b10011 7
b10011 m
b101000000000000100010011 Q
b101000000000000100010011 Z
b11000 #
b11000 U
b11000 l
b0 S
b0 h
b0 R
b0 g
1!
#90
0!
#95
b1010 9
b1010 Y
b1010 >
b1010 X
b0 8
b0 a
b0 3
b0 c
b0 e
b0 6
b0 b
b0 _
1=
1:
b10 K
b1010 H
b10011 Q
b10011 Z
b11100 #
b11100 U
b11100 l
1!
#100
0!
#105
b0 9
b0 Y
b0 >
b0 X
b100000 #
b100000 U
b100000 l
b0 K
b0 H
b10 C
b1010 (
b1010 +
b1010 .
b1010 @
1!
#110
0!
#115
b1000001000000110110011 %
b1000001000000110110011 7
b1000001000000110110011 m
b1010 S
b1010 h
b10 R
b10 g
b0 C
b0 (
b0 +
b0 .
b0 @
b100100 #
b100100 U
b100100 l
1!
#120
0!
#125
b1010 4
b1010 i
b101 5
b101 j
b10 2
b10 d
b10 f
b0 `
bx 8
bx a
b1 3
b1 c
b1 e
b11 6
b11 b
b0 _
0=
1:
b110011 [
b10011 %
b10011 7
b10011 m
b1000001000000110110011 Q
b1000001000000110110011 Z
b101000 #
b101000 U
b101000 l
b0 S
b0 h
b0 R
b0 g
1!
#130
0!
#135
b1111 9
b1111 Y
bx 4
bx i
b0 5
b0 j
b1010 >
b1010 X
1=
b0 8
b0 a
bx 2
bx d
bx f
b0 3
b0 c
b0 e
b0 6
b0 b
b0 _
bx `
1:
b10011 [
0G
b10 P
b1 O
b11 K
b1010 M
b101 -
b101 W
b101 L
bx H
b10011 Q
b10011 Z
b101100 #
b101100 U
b101100 l
1!
#140
0!
#145
b0 9
b0 Y
b0 >
b0 X
b110000 #
b110000 U
b110000 l
1G
bx P
b0 O
b0 K
bx M
b0 -
b0 W
b0 L
b0 H
b1010 '
b1010 *
b1010 /
b1010 E
b11 C
b1111 (
b1111 +
b1111 .
b1111 @
1!
#150
0!
#155
b1100000010001000100011 %
b1100000010001000100011 7
b1100000010001000100011 m
b1111 S
b1111 h
b11 R
b11 g
bx '
bx *
bx /
bx E
b0 C
b0 (
b0 +
b0 .
b0 @
b110100 #
b110100 U
b110100 l
1!
#160
0!
#165
b1111 4
b1111 i
1;
1^
b11 2
b11 d
b11 f
b0 `
b100 8
b100 a
b0 3
b0 c
b0 e
bx 6
bx b
b10 _
1=
0:
b100011 [
b10011 %
b10011 7
b10011 m
b1100000010001000100011 Q
b1100000010001000100011 Z
b111000 #
b111000 U
b111000 l
b0 S
b0 h
b0 R
b0 g
1!
#170
0!
#175
b100 9
b100 Y
bx 4
bx i
b100 >
b100 X
1:
b0 6
b0 b
0^
b0 8
b0 a
bx 2
bx d
bx f
b0 3
b0 c
b0 e
b0 _
bx `
1=
0;
b10011 [
1J
0N
b11 P
bx K
b1111 M
b100 H
b10011 Q
b10011 Z
b111100 #
b111100 U
b111100 l
1!
#180
0!
#185
b0 9
b0 Y
b0 >
b0 X
b1000000 #
b1000000 U
b1000000 l
0J
1N
bx P
b0 K
bx M
b0 H
1&
1B
0D
b1111 '
b1111 *
b1111 /
b1111 E
bx C
b100 (
b100 +
b100 .
b100 @
1!
#190
0!
#195
b10000000000001000010011 %
b10000000000001000010011 7
b10000000000001000010011 m
b0 $
b0 )
b0 0
b100 S
b100 h
bx R
bx g
0T
0&
0B
1D
bx '
bx *
bx /
bx E
b0 C
b0 (
b0 +
b0 .
b0 @
b1000100 #
b1000100 U
b1000100 l
1!
#200
0!
#205
b100 8
b100 a
b0 3
b0 c
b0 e
b100 6
b100 b
b0 _
1=
1:
b10011 %
b10011 7
b10011 m
b10000000000001000010011 Q
b10000000000001000010011 Z
b1001000 #
b1001000 U
b1001000 l
b0 S
b0 h
b0 R
b0 g
1T
1!
#210
0!
#215
b100 9
b100 Y
b100 >
b100 X
b0 8
b0 a
b0 3
b0 c
b0 e
b0 6
b0 b
b0 _
1=
1:
b100 K
b100 H
b10011 Q
b10011 Z
b1001100 #
b1001100 U
b1001100 l
1!
#220
0!
#225
b0 9
b0 Y
b0 >
b0 X
b1111 $
b1111 )
b1111 0
b1010000 #
b1010000 U
b1010000 l
b0 K
b0 H
b100 C
b100 (
b100 +
b100 .
b100 @
1!
#230
0!
#235
b0 $
b0 )
b0 0
b100010001010000011 %
b100010001010000011 7
b100010001010000011 m
b100 S
b100 h
b100 R
b100 g
b0 C
b0 (
b0 +
b0 .
b0 @
b1010100 #
b1010100 U
b1010100 l
1!
#240
0!
#245
b100 5
b100 j
1]
1<
b0 8
b0 a
b100 3
b100 c
b100 e
b101 6
b101 b
b10 _
1=
1:
b11 [
b10011 %
b10011 7
b10011 m
b100010001010000011 Q
b100010001010000011 Z
b1011000 #
b1011000 U
b1011000 l
b0 S
b0 h
b0 R
b0 g
1!
#250
0!
#255
b100 9
b100 Y
b0 5
b0 j
0]
b0 8
b0 a
b0 3
b0 c
b0 e
b0 6
b0 b
b0 _
1=
0<
1:
b10011 [
1I
b100 O
b101 K
b100 -
b100 W
b100 L
b10011 Q
b10011 Z
b1011100 #
b1011100 U
b1011100 l
1!
#260
0!
#265
b0 9
b0 Y
b1111 $
b1111 )
b1111 0
b1100000 #
b1100000 U
b1100000 l
0I
b0 O
b0 K
b0 -
b0 W
b0 L
1A
b101 C
b100 (
b100 +
b100 .
b100 @
1!
#270
0!
#275
b0 $
b0 )
b0 0
b1111 S
b1111 h
b101 R
b101 g
0A
b0 C
b0 (
b0 +
b0 .
b0 @
b1100100 #
b1100100 U
b1100100 l
1!
#280
0!
#285
b1101000 #
b1101000 U
b1101000 l
b0 S
b0 h
b0 R
b0 g
1!
#290
0!
#295
b1101100 #
b1101100 U
b1101100 l
1!
#300
0!
#305
b10100001000001100110011 %
b10100001000001100110011 7
b10100001000001100110011 m
b1110000 #
b1110000 U
b1110000 l
1!
#310
0!
#315
b1111 4
b1111 i
b101 5
b101 j
b101 2
b101 d
b101 f
b0 `
bx 8
bx a
b1 3
b1 c
b1 e
b110 6
b110 b
b0 _
0=
1:
b110011 [
bx %
bx 7
bx m
b10100001000001100110011 Q
b10100001000001100110011 Z
b1110100 #
b1110100 U
b1110100 l
1!
#320
0!
#325
b10100 9
b10100 Y
bx 4
bx i
bx 5
bx j
bx ?
bx \
bx 2
bx d
bx f
bx 3
bx c
bx e
bx 6
bx b
bx _
bx `
0:
bx [
b1111 >
b1111 X
bx Q
bx Z
b1111000 #
b1111000 U
b1111000 l
0G
b101 P
b1 O
b110 K
b1111 M
b101 -
b101 W
b101 L
bx H
1!
#330
0!
#335
bx >
bx X
b1111 '
b1111 *
b1111 /
b1111 E
b110 C
b10100 (
b10100 +
b10100 .
b10100 @
0N
bx P
bx O
bx K
bx M
bx -
bx W
bx L
bx F
bx V
b1111100 #
b1111100 U
b1111100 l
1!
#340
0!
#345
b10000000 #
b10000000 U
b10000000 l
0D
bx '
bx *
bx /
bx E
bx C
b10100 S
b10100 h
b110 R
b110 g
1!
#350
0!
#355
bx R
bx g
0T
b10000100 #
b10000100 U
b10000100 l
1!
#360
0!
#365
b10001000 #
b10001000 U
b10001000 l
1!
#370
0!
#375
b10001100 #
b10001100 U
b10001100 l
1!
#380
0!
#385
b10010000 #
b10010000 U
b10010000 l
1!
#390
0!
#395
b10010100 #
b10010100 U
b10010100 l
1!
#400
0!
#405
b10011000 #
b10011000 U
b10011000 l
1!
#410
0!
#415
b10011100 #
b10011100 U
b10011100 l
1!
#420
0!
#425
b10100000 #
b10100000 U
b10100000 l
1!
#430
0!
#435
b10100100 #
b10100100 U
b10100100 l
1!
#440
0!
#445
b10101000 #
b10101000 U
b10101000 l
1!
#450
0!
#455
b10101100 #
b10101100 U
b10101100 l
1!
#460
0!
#465
b10110000 #
b10110000 U
b10110000 l
1!
#470
0!
#475
b10110100 #
b10110100 U
b10110100 l
1!
#480
0!
#485
b10111000 #
b10111000 U
b10111000 l
1!
#490
0!
#495
b10111100 #
b10111100 U
b10111100 l
1!
#500
0!
#505
b11000000 #
b11000000 U
b11000000 l
1!
#510
0!
#515
b11000100 #
b11000100 U
b11000100 l
1!
#520
0!
#525
b11001000 #
b11001000 U
b11001000 l
1!
