src/dmem_iverilog.v
`define DRAM_depth 4096

module DMEM(
    input           clk, write_request,
    input   [31:0]  access_address, write_data,
    output  [31:0]  read_data
);

reg [31:0] RAM[0:`DRAM_depth-1];

assign read_data = RAM[access_address[31:2]];

always @ (posedge clk) begin
    if (write_request) begin
        RAM[access_address[31:2]] <= write_data;

        if (access_address == 32'h0000FFFC) begin
            $display("writedata: %d", write_data);
        end
    end
end

/* データメモリの初期化(シミュレーション用) */
integer i;
initial begin
    for (i = 0; i < `DRAM_depth; i = i + 1) begin
        RAM[i] = 32'b0;
    end
end

endmodule

src/imem_iverilog.v
`define MEMDATA "memory.data"

module IMEM(
    input   [31:0]  addr,
    output  [31:0]  instr
);

reg [31:0]  ROM[63:0];

initial begin
    $readmemh(`MEMDATA, ROM, 0, 63);
end

assign  instr = ROM[addr[31:2]];    // pc <= pc + 32'h4;に対応

endmodule

src/alu.v
module ALU(
    input       [3:0]   alu_op,
    input       [31:0]  src1,
    input       [31:0]  src2,
    output reg  [31:0]  aluout
);

always @* begin
    case (alu_op)
        4'b0000,
        4'b1010:
        begin
            aluout <= src1 + src2;  // add, addi
        end
        4'b0001: aluout <= src1 - src2;  // sub
        4'b0010: aluout <= src1 & src2;  // and
        4'b0011: aluout <= src1 | src2;  // or
        4'b0100: aluout <= src1 ^ src2;  // xor
        4'b1100: aluout <= (src1 == src2) ? 32'b1 : 32'b0; // beq
        4'b1101: aluout <= (src1 != src2) ? 32'b1 : 32'b0; // bne
        4'b1110: aluout <= ($signed(src1) < $signed(src2)) ? 32'b1 : 32'b0; // blt
        4'b1111: aluout <= ($signed(src1) >= $signed(src2)) ? 32'b1 : 32'b0; // bge
    endcase
end

endmodule

src/regfile.v
module REGFILE(
    input   clk,
    input   write_request,
    input   [4:0] write_address,
    input   [4:0] read_address1,
    input   [4:0] read_address2,
    input   [31:0] write_data,
    output  [31:0] read_data1,
    output  [31:0] read_data2
);

reg [31:0] register_file [31:0];

always @ (posedge clk) begin
    if (write_request) register_file[write_address] <= write_data;
end

/* レジスタの初期化(シミュレーション用) */
integer i;
initial begin
    for (i = 0; i < 32; i = i + 1) begin
        register_file[i] = 32'b0;
    end
end

assign read_data1 = (read_address1 != 0) ? register_file[read_address1] : 0;
assign read_data2 = (read_address2 != 0) ? register_file[read_address2] : 0;

endmodule

src/decoder.v
module DECODER(
    input       [31:0]  instr,
    output reg  [3:0]   alu_op,
    output reg  [31:0]  immext,
    output reg  [4:0]   rd, rs1, rs2,
    output reg          reg_write_request,
    output reg          mem_write_request,
    output reg          mem_read_request,
    output reg          imm_enable,
    output reg          is_branch,
    output reg  [2:0]   branch_type
);

    wire [6:0] opcode = instr[6:0];
    reg [6:0] funct7;
    reg [2:0] funct3;

    // 初期化（デフォルト値設定）
    always @* begin
        reg_write_request = 1'b0;
        mem_write_request = 1'b0;
        mem_read_request  = 1'b0;
        imm_enable        = 1'b0;
        funct7            = 7'bx;
        funct3            = 3'bx;
        rd                = 5'bx;
        rs1               = 5'bx;
        rs2               = 5'bx;
        immext            = 32'bx;
        is_branch         = 1'b0;
        branch_type      = 3'b0;

        case (opcode)
            /* R-type */
            7'b0110011: begin
                funct7          = instr[31:25];
                funct3          = instr[14:12];
                immext          = 32'bx;
                rd              = instr[11:7];
                rs1             = instr[19:15];
                rs2             = instr[24:20];
                reg_write_request = 1'b1;
                imm_enable      = 1'b0;
                is_branch         = 1'b0;
                branch_type      = 3'bx;
            end

            /* I-type */
            7'b0010011, // addi
            7'b0000011: // lw
            begin
                funct7          = 7'bx;
                funct3          = instr[14:12];
                immext          = {{20{instr[31]}}, instr[31:20]};
                rd              = instr[11:7];
                rs1             = instr[19:15];
                rs2             = 5'bx;
                reg_write_request = 1'b1;
                imm_enable      = 1'b1;
                is_branch         = 1'b0;
                branch_type      = 3'bx;
            end

            /* S-type */
            7'b0100011: // sw
            begin
                funct7          = instr[31:25];
                funct3          = instr[14:12];
                immext          = {{20{instr[31]}}, instr[31:25], instr[11:7]};
                rd              = 5'bx;
                rs1             = instr[19:15];
                rs2             = instr[24:20];
                reg_write_request = 1'b0;
                imm_enable          = 1'b1;
                is_branch         = 1'b0;
                branch_type      = 3'bx;
            end

            /* B-type */
            7'b1100011: begin // branch instructions
                funct3          = instr[14:12];
                immext          = {{20{instr[31]}}, instr[7], instr[30:25], instr[11:8], 1'b0}; // B型即値
                rd              = 5'bx;
                rs1             = instr[19:15];
                rs2             = instr[24:20];
                reg_write_request = 1'b0;
                imm_enable      = 1'b0;
                is_branch         = 1'b1;
            end

            /* U-type */
            7'b0110111,  // LUI
            7'b0010111: begin  // AUIPC
                funct7          = 7'bx;
                funct3          = 3'bx;
                immext          = 32'bx;
                rd              = instr[11:7];
                rs1             = 5'bx;
                rs2             = 5'bx;
                is_branch         = 1'b0;
                branch_type      = 3'bx;
            end

            /* J-type */
            7'b1101111: begin // jal
                funct7          = 7'bx;
                funct3          = 3'bx;
                immext          = 32'bx;
                rd              = instr[11:7];
                rs1             = 5'bx;
                rs2             = 5'bx;
                is_branch         = 1'b0;
                branch_type      = 3'bx;
            end

            default: begin
                funct7          = 7'bx;
                funct3          = 3'bx;
                immext          = 32'bx;
                rd              = 5'bx;
                rs1             = 5'bx;
                rs2             = 5'bx;
                is_branch         = 1'b0;
                branch_type      = 3'bx;
            end
        endcase
    end

    // ALU operation decoding
    always @* begin
        case (funct3)
            3'b000: begin
                if (opcode == 7'b0110011) // R-type
                begin
                    case (funct7)
                        7'b0000000: alu_op = 4'b0000;  // add
                        7'b0100000: alu_op = 4'b0001;  // sub
                        default:    alu_op = 4'bx;
                    endcase
                end
                else if (opcode == 7'b0010011) // I-type (addi)
                begin
                    alu_op = 4'b0000;   // addi
                end
                else begin
                    alu_op = 4'bx;
                end
            end

            3'b001: alu_op = 4'b0010;  // sll
            3'b010: begin
                case (opcode)
                    7'b0000011: begin // lw
                        alu_op = 4'b0000; // addでアドレス計算
                        reg_write_request = 1;
                        mem_read_request  = 1;
                    end

                    7'b0100011: begin // sw
                        alu_op = 4'b0000;
                        mem_write_request = 1;
                    end
                    default: alu_op = 4'bx;
                endcase
            end

            3'b011: alu_op = 4'b0100;  // sltu
            3'b100: alu_op = 4'b0101;  // xor
            3'b101: begin
                case (funct7)
                    7'b0000000: alu_op = 4'b0110;  // srl
                    7'b0100000: alu_op = 4'b0111;  // sra
                    default:    alu_op = 4'bx;
                endcase
            end
            3'b110: alu_op = 4'b1000;  // or
            3'b111: alu_op = 4'b1001;  // and
            default: alu_op = 4'bx;
        endcase
        if (opcode == 7'b1100011) begin
            case (funct3)
                3'b000: begin
                    alu_op = 4'b1100; // beq
                    branch_type = 3'b000;
                end
                3'b001: begin
                    alu_op = 4'b1101; // bne
                    branch_type = 3'b001;
                end
                3'b100: begin
                    alu_op = 4'b1110; // blt
                    branch_type = 3'b100;
                end
                3'b101: begin
                    alu_op = 4'b1111; // bge
                    branch_type = 3'b101;
                end
            endcase
        end
    end

endmodule

src/haconiwa_core.v
module HACONIWA_CORE(
    input               clk,
    input               reset,
    output reg  [31:0]  pc,
    input       [31:0]  instr,
    output      [31:0]  core2mem_access_address,
    input       [31:0]  mem2core_read_data,
    output      [31:0]  core2mem_write_data,
    output              core2mem_write_request
);

/* === Pipeline Registers === */
reg [31:0]  IF_ID_pc, IF_ID_instr;
reg         stall, flush;
reg [3:0]   ID_EXE_alu_op;
reg [2:0]   ID_EXE_branch_type;
reg [31:0]  ID_EXE_pc, next_pc, ID_EXE_immext, ID_EXE_read_reg_data1, ID_EXE_read_reg_data2;
reg [4:0]   ID_EXE_rd, ID_EXE_rs1, ID_EXE_rs2;
reg         ID_EXE_reg_write_request, ID_EXE_mem_write_request, ID_EXE_mem_read_request, ID_EXE_imm_enable, ID_EXE_is_branch;
reg [4:0]   EXE_MEM_rd;
reg [31:0]  EXE_MEM_aluout, EXE_MEM_write_data;
reg         EXE_MEM_reg_write_request, EXE_MEM_mem_write_request, EXE_MEM_mem_read_request;
reg         MEM_WB_reg_write_request;
reg [4:0]   MEM_WB_rd;
reg [31:0]  MEM_WB_reg_write_data;

/* === IF Stage === */
always @* begin
    if (flush) begin
        next_pc = ID_EXE_pc + ID_EXE_immext;
    end else begin
        next_pc = pc + 4;
    end
end

always @ (posedge clk) begin
    if (reset) begin
        pc <= 32'h0;
    end else if (!stall) begin
        pc <= next_pc;
        IF_ID_pc <= pc;
        IF_ID_instr <= (flush) ? 32'h00000013 : instr;
    end
end

/* === ID Stage === */
wire [3:0] alu_op;
wire [31:0] immext, read_reg_data1, read_reg_data2;
wire [4:0] rd, rs1, rs2;
wire [2:0] branch_type;
wire dec_reg_write_request, dec_mem_write_request, dec_mem_read_request, dec_imm_enable, dec_is_branch;

DECODER dec(
    .instr(IF_ID_instr),
    .alu_op(alu_op),
    .rd(rd),
    .rs1(rs1),
    .rs2(rs2),
    .immext(immext),
    .imm_enable(dec_imm_enable),
    .reg_write_request(dec_reg_write_request),
    .mem_write_request(dec_mem_write_request),
    .mem_read_request(dec_mem_read_request),
    .is_branch(is_branch),
    .branch_type(branch_type)
);

REGFILE regfile(
    .clk(clk),
    .read_address1(rs1),
    .read_address2(rs2),
    .read_data1(read_reg_data1),
    .read_data2(read_reg_data2),
    .write_request(MEM_WB_reg_write_request),
    .write_address(MEM_WB_rd),
    .write_data(MEM_WB_reg_write_data)
);

always @ (posedge clk) begin
    if (!stall) begin
        ID_EXE_pc                   <= IF_ID_pc;
        ID_EXE_alu_op               <= alu_op;
        ID_EXE_immext               <= immext;
        ID_EXE_read_reg_data1       <= read_reg_data1;
        ID_EXE_read_reg_data2       <= read_reg_data2;
        ID_EXE_rd                   <= rd;
        ID_EXE_rs1                  <= rs1;
        ID_EXE_rs2                  <= rs2;
        ID_EXE_reg_write_request    <= dec_reg_write_request;
        ID_EXE_mem_write_request    <= dec_mem_write_request;
        ID_EXE_mem_read_request     <= dec_mem_read_request;
        ID_EXE_imm_enable           <= dec_imm_enable;
        ID_EXE_is_branch            <= is_branch;
        ID_EXE_branch_type          <= branch_type;
    end else begin
        ID_EXE_pc                   <= 32'b0;
        ID_EXE_alu_op               <= 4'b0;
        ID_EXE_immext               <= 32'b0;
        ID_EXE_read_reg_data1       <= 32'b0;
        ID_EXE_read_reg_data2       <= 32'b0;
        ID_EXE_rd                   <= 5'b0;
        ID_EXE_rs1                  <= 5'b0;
        ID_EXE_rs2                  <= 5'b0;
        ID_EXE_reg_write_request    <= 1'b0;
        ID_EXE_mem_write_request    <= 1'b0;
        ID_EXE_mem_read_request     <= 1'b0;
        ID_EXE_imm_enable           <= 1'b0; 
        ID_EXE_is_branch            <= 1'b0;
        ID_EXE_branch_type          <= 1'b0;
    end
end

// load-use hazard detection
wire load_use_hazard;
assign load_use_hazard = (ID_EXE_mem_read_request &&
                            ((ID_EXE_rd == rs1 && ID_EXE_rd != 0) ||
                            (ID_EXE_rd == rs2 && ID_EXE_rd != 0)));
always @* begin
    if (reset) begin
        stall = 1'b0;
    end else begin
        stall = load_use_hazard;
    end
end

/* === EXE Stage === */
wire [31:0] fwd_src1, fwd_src2;
assign fwd_src1 = (EXE_MEM_reg_write_request && EXE_MEM_rd != 0 && EXE_MEM_rd == ID_EXE_rs1)
                    ? EXE_MEM_aluout
                    : (MEM_WB_reg_write_request && MEM_WB_rd != 0 && MEM_WB_rd == ID_EXE_rs1)
                        ? MEM_WB_reg_write_data
                        : ID_EXE_read_reg_data1;

assign fwd_src2 = (EXE_MEM_reg_write_request && EXE_MEM_rd != 0 && EXE_MEM_rd == ID_EXE_rs2)
                    ? EXE_MEM_aluout
                    : (MEM_WB_reg_write_request && MEM_WB_rd != 0 && MEM_WB_rd == ID_EXE_rs2)
                        ? MEM_WB_reg_write_data
                        : ID_EXE_read_reg_data2;

wire [31:0] alu_src1, alu_src2, exe_aluout;
assign alu_src1 = fwd_src1;
assign alu_src2 = ID_EXE_imm_enable ? ID_EXE_immext : fwd_src2;

ALU alu(
    .alu_op(ID_EXE_alu_op),
    .src1(alu_src1),
    .src2(alu_src2),
    .aluout(exe_aluout)
);

wire branch_taken;
assign branch_taken = (ID_EXE_is_branch && (exe_aluout == 1'b1)) ? 1'b1 : 1'b0 ;
// assign branch_taken =   (ID_EXE_branch_type == 3'b000) ? (fwd_src1 == fwd_src2) :
//                         (ID_EXE_branch_type == 3'b001) ? (fwd_src1 != fwd_src2) :
//                         (ID_EXE_branch_type == 3'b100) ? (fwd_src1 < fwd_src2) :
//                         (ID_EXE_branch_type == 3'b101) ? (fwd_src1 >= fwd_src2) : 1'b0;

always @* begin
    flush = ID_EXE_is_branch && branch_taken;
end

always @ (posedge clk) begin
    EXE_MEM_aluout <= exe_aluout;
    EXE_MEM_rd <= ID_EXE_rd;
    EXE_MEM_write_data <= fwd_src2;
    EXE_MEM_reg_write_request <= ID_EXE_reg_write_request;
    EXE_MEM_mem_write_request <= ID_EXE_mem_write_request;
    EXE_MEM_mem_read_request <= ID_EXE_mem_read_request;
end

/* === MEM Stage === */
assign core2mem_write_request = EXE_MEM_mem_write_request;
assign core2mem_access_address = EXE_MEM_aluout;
assign core2mem_write_data = EXE_MEM_write_data;

always @ (posedge clk) begin
    MEM_WB_reg_write_request <= EXE_MEM_reg_write_request;
    MEM_WB_rd <= EXE_MEM_rd;
    MEM_WB_reg_write_data <= (EXE_MEM_mem_read_request) ? mem2core_read_data : EXE_MEM_aluout;
end

endmodule

src/haconiwa_top.v
module HACONIWA_TOP(
    input   CLOCK_50_B5B, CPU_RESET_n
);

wire [31:0] pc, instr, core2mem_access_address, mem2core_read_data, core2mem_write_data;
wire core2mem_write_request;

HACONIWA_CORE hcore(
    .clk(CLOCK_50_B5B),
    .reset(!CPU_RESET_n),
    .pc(pc),
    .instr(instr),
    .core2mem_access_address(core2mem_access_address),
    .mem2core_read_data(mem2core_read_data),
    .core2mem_write_data(core2mem_write_data),
    .core2mem_write_request(core2mem_write_request)
);

IMEM imem(
    .addr(pc),
    .instr(instr)
);

DMEM dmem(
    .clk(CLOCK_50_B5B),
    .access_address(core2mem_access_address),
    .read_data(mem2core_read_data),
    .write_data(core2mem_write_data),
    .write_request(core2mem_write_request)
);

endmodule

module SIMTOP();
    reg clk, reset;

    HACONIWA_TOP htop(
        .CLOCK_50_B5B(clk),
        .CPU_RESET_n(!reset)
    );

    initial begin
        clk = 0;
        forever #5 clk = ~clk;
    end

    initial begin
        #10 reset = 1;
        #20 reset = 0;
        $dumpfile("sim_top_haconiwa.vcd");
        $dumpvars(0, htop);

        #2000 $finish;
    end
endmodule

test/sim_top_haconiwa.vcd
$date
	Sat May  3 02:05:58 2025
$end
$version
	Icarus Verilog
$end
$timescale
	1s
$end
$scope module SIMTOP $end
$scope module htop $end
$var wire 1 ! CLOCK_50_B5B $end
$var wire 1 " CPU_RESET_n $end
$var wire 32 # pc [31:0] $end
$var wire 32 $ mem2core_read_data [31:0] $end
$var wire 32 % instr [31:0] $end
$var wire 1 & core2mem_write_request $end
$var wire 32 ' core2mem_write_data [31:0] $end
$var wire 32 ( core2mem_access_address [31:0] $end
$scope module dmem $end
$var wire 1 ! clk $end
$var wire 32 ) read_data [31:0] $end
$var wire 1 & write_request $end
$var wire 32 * write_data [31:0] $end
$var wire 32 + access_address [31:0] $end
$var integer 32 , i [31:0] $end
$upscope $end
$scope module hcore $end
$var wire 32 - alu_src1 [31:0] $end
$var wire 1 ! clk $end
$var wire 32 . core2mem_access_address [31:0] $end
$var wire 32 / core2mem_write_data [31:0] $end
$var wire 1 & core2mem_write_request $end
$var wire 1 0 load_use_hazard $end
$var wire 32 1 mem2core_read_data [31:0] $end
$var wire 1 2 reset $end
$var wire 5 3 rs2 [4:0] $end
$var wire 5 4 rs1 [4:0] $end
$var wire 32 5 read_reg_data2 [31:0] $end
$var wire 32 6 read_reg_data1 [31:0] $end
$var wire 5 7 rd [4:0] $end
$var wire 1 8 is_branch $end
$var wire 32 9 instr [31:0] $end
$var wire 32 : immext [31:0] $end
$var wire 32 ; fwd_src2 [31:0] $end
$var wire 32 < fwd_src1 [31:0] $end
$var wire 32 = exe_aluout [31:0] $end
$var wire 1 > dec_reg_write_request $end
$var wire 1 ? dec_mem_write_request $end
$var wire 1 @ dec_mem_read_request $end
$var wire 1 A dec_imm_enable $end
$var wire 3 B branch_type [2:0] $end
$var wire 1 C branch_taken $end
$var wire 32 D alu_src2 [31:0] $end
$var wire 4 E alu_op [3:0] $end
$var reg 32 F EXE_MEM_aluout [31:0] $end
$var reg 1 G EXE_MEM_mem_read_request $end
$var reg 1 H EXE_MEM_mem_write_request $end
$var reg 5 I EXE_MEM_rd [4:0] $end
$var reg 1 J EXE_MEM_reg_write_request $end
$var reg 32 K EXE_MEM_write_data [31:0] $end
$var reg 4 L ID_EXE_alu_op [3:0] $end
$var reg 3 M ID_EXE_branch_type [2:0] $end
$var reg 1 N ID_EXE_imm_enable $end
$var reg 32 O ID_EXE_immext [31:0] $end
$var reg 1 P ID_EXE_is_branch $end
$var reg 1 Q ID_EXE_mem_read_request $end
$var reg 1 R ID_EXE_mem_write_request $end
$var reg 32 S ID_EXE_pc [31:0] $end
$var reg 5 T ID_EXE_rd [4:0] $end
$var reg 32 U ID_EXE_read_reg_data1 [31:0] $end
$var reg 32 V ID_EXE_read_reg_data2 [31:0] $end
$var reg 1 W ID_EXE_reg_write_request $end
$var reg 5 X ID_EXE_rs1 [4:0] $end
$var reg 5 Y ID_EXE_rs2 [4:0] $end
$var reg 32 Z IF_ID_instr [31:0] $end
$var reg 32 [ IF_ID_pc [31:0] $end
$var reg 5 \ MEM_WB_rd [4:0] $end
$var reg 32 ] MEM_WB_reg_write_data [31:0] $end
$var reg 1 ^ MEM_WB_reg_write_request $end
$var reg 1 _ flush $end
$var reg 32 ` next_pc [31:0] $end
$var reg 32 a pc [31:0] $end
$var reg 1 b stall $end
$scope module alu $end
$var wire 4 c alu_op [3:0] $end
$var wire 32 d src1 [31:0] $end
$var wire 32 e src2 [31:0] $end
$var reg 32 f aluout [31:0] $end
$upscope $end
$scope module dec $end
$var wire 32 g instr [31:0] $end
$var wire 7 h opcode [6:0] $end
$var reg 4 i alu_op [3:0] $end
$var reg 3 j branch_type [2:0] $end
$var reg 3 k funct3 [2:0] $end
$var reg 7 l funct7 [6:0] $end
$var reg 1 A imm_enable $end
$var reg 32 m immext [31:0] $end
$var reg 1 8 is_branch $end
$var reg 1 @ mem_read_request $end
$var reg 1 ? mem_write_request $end
$var reg 5 n rd [4:0] $end
$var reg 1 > reg_write_request $end
$var reg 5 o rs1 [4:0] $end
$var reg 5 p rs2 [4:0] $end
$upscope $end
$scope module regfile $end
$var wire 1 ! clk $end
$var wire 5 q read_address1 [4:0] $end
$var wire 5 r read_address2 [4:0] $end
$var wire 5 s write_address [4:0] $end
$var wire 32 t write_data [31:0] $end
$var wire 1 ^ write_request $end
$var wire 32 u read_data2 [31:0] $end
$var wire 32 v read_data1 [31:0] $end
$var integer 32 w i [31:0] $end
$upscope $end
$upscope $end
$scope module imem $end
$var wire 32 x addr [31:0] $end
$var wire 32 y instr [31:0] $end
$upscope $end
$upscope $end
$upscope $end
$enddefinitions $end
$comment Show the parameter values. $end
$dumpall
$end
#30
$dumpvars
b10011 y
b0 x
b100000 w
bx v
bx u
bx t
b0 s
bx r
bx q
bx p
bx o
bx n
bx m
bx l
bx k
bx j
bx i
bx h
bx g
bx f
bx e
bx d
bx c
xb
b0 a
b100 `
x_
0^
bx ]
b0 \
bx [
bx Z
bx Y
bx X
xW
bx V
bx U
bx T
bx S
xR
xQ
xP
bx O
xN
bx M
bx L
bx K
xJ
bx I
xH
xG
bx F
bx E
bx D
xC
bx B
xA
x@
x?
x>
bx =
bx <
bx ;
bx :
b10011 9
x8
bx 7
bx 6
bx 5
bx 4
bx 3
02
bx 1
x0
bx /
bx .
bx -
b100000 ,
bx +
bx *
bx )
bx (
bx '
x&
b10011 %
bx $
b0 #
1"
0!
$end
#35
0C
0b
0_
00
bx \
bx s
x^
b0 M
0P
0N
0Q
0R
0W
b0 Y
b0 X
b0 T
b0 V
b0 U
b0 O
b0 L
b0 c
b0 S
1!
#40
0!
#45
xb
x0
b0 6
b0 v
x_
b0 E
b0 i
xC
b0 4
b0 o
b0 q
b0 7
b0 n
b0 :
b0 m
b0 k
bx B
bx j
08
1A
0@
0?
1>
b10011 h
b1000 `
b10011 Z
b10011 g
b0 [
b100 #
b100 a
b100 x
bx M
xP
xN
xQ
xR
xW
bx Y
bx X
bx T
bx V
bx U
bx O
bx L
bx c
bx S
0G
0&
0H
0J
b0 I
1!
#50
0!
#55
0C
0b
0_
00
b0 \
b0 s
0^
xG
x&
xH
xJ
bx I
b0 M
0P
0N
0Q
0R
0W
b0 Y
b0 X
b0 T
b0 V
b0 U
b0 O
b0 L
b0 c
b0 S
1!
#60
0!
#65
bx =
bx f
bx -
bx d
bx <
b1100 `
b0 D
b0 e
b100 [
b1000 #
b1000 a
b1000 x
bx M
1N
1W
bx Y
bx V
0G
0&
0H
0J
b0 I
bx \
bx s
x^
1!
#70
0!
#75
b0 =
b0 f
b0 -
b0 d
b0 <
b10000 `
b0 \
b0 s
0^
1J
b100 S
b1000 [
b1100 #
b1100 a
b1100 x
1!
#80
0!
#85
b10100 `
b0 $
b0 )
b0 1
b1100 [
b10000 #
b10000 a
b10000 x
b1000 S
b0 (
b0 +
b0 .
b0 F
1^
1!
#90
0!
#95
b11000 `
b0 ]
b0 t
b1100 S
b10000 [
b10100 #
b10100 a
b10100 x
1!
#100
0!
#105
b10100000000000010010011 %
b10100000000000010010011 9
b10100000000000010010011 y
b11100 `
b10100 [
b11000 #
b11000 a
b11000 x
b10000 S
1!
#110
0!
#115
bx B
bx j
b101 :
b101 m
b0 4
b0 o
b0 q
b1 7
b1 n
b0 k
1A
1>
b100000 `
b101000000000000100010011 %
b101000000000000100010011 9
b101000000000000100010011 y
b10100 S
b10100000000000010010011 Z
b10100000000000010010011 g
b11000 [
b11100 #
b11100 a
b11100 x
1!
#120
0!
#125
b101 =
b101 f
bx B
bx j
b1010 :
b1010 m
b0 4
b0 o
b0 q
b10 7
b10 n
b0 k
1A
1>
b1000001000000110110011 %
b1000001000000110110011 9
b1000001000000110110011 y
b101 D
b101 e
b100100 `
b101000000000000100010011 Z
b101000000000000100010011 g
b11100 [
b100000 #
b100000 a
b100000 x
b1 T
b101 O
b11000 S
1!
#130
0!
#135
b1010 =
b1010 f
b0 5
b0 u
b1010 D
b1010 e
b10 3
b10 p
b10 r
b0 l
bx B
bx j
bx :
bx m
b1 4
b1 o
b1 q
b11 7
b11 n
b0 k
0A
1>
b110011 h
b101000 `
b111100000000001000010011 %
b111100000000001000010011 9
b111100000000001000010011 y
b1 I
b101 (
b101 +
b101 .
b101 F
b10 T
b1010 O
b11100 S
b1000001000000110110011 Z
b1000001000000110110011 g
b100000 [
b100100 #
b100100 a
b100100 x
1!
#140
0!
#145
b1111 =
b1111 f
b101 -
b101 d
b101 <
bx 5
bx u
b1010 ;
1A
b1111 :
b1111 m
bx B
bx j
bx 3
bx p
bx r
b0 4
b0 o
b0 q
b100 7
b100 n
b0 k
bx l
1>
b10011 h
b11111110010000011000100011100011 %
b11111110010000011000100011100011 9
b11111110010000011000100011100011 y
b1010 D
b1010 e
b101100 `
b111100000000001000010011 Z
b111100000000001000010011 g
b100100 [
b101000 #
b101000 a
b101000 x
0N
b10 Y
b1 X
b11 T
b0 V
bx O
b100000 S
b10 I
b1010 (
b1010 +
b1010 .
b1010 F
b101 ]
b101 t
b1 \
b1 s
1!
#150
0!
#155
b1111 =
b1111 f
b0 5
b0 u
b0 -
b0 d
b0 <
b1100 E
b1100 i
bx ;
b1111 D
b1111 e
18
b100 3
b100 p
b100 r
b0 B
b0 j
b11111111111111111111111111110000 :
b11111111111111111111111111110000 m
b11 4
b11 o
b11 q
bx 7
bx n
b0 k
0A
0>
b1100011 h
b110000 `
b1100000010001000100011 %
b1100000010001000100011 9
b1100000010001000100011 y
b1010 ]
b1010 t
b10 \
b10 s
b1010 '
b1010 *
b1010 /
b1010 K
b11 I
b1111 (
b1111 +
b1111 .
b1111 F
1N
bx Y
b0 X
b100 T
bx V
b1111 O
b100100 S
b11111110010000011000100011100011 Z
b11111110010000011000100011100011 g
b101000 [
b101100 #
b101100 a
b101100 x
1!
#160
0!
#165
1_
1C
b1 =
b1 f
b1111 -
b1111 d
b1111 <
1?
b0 E
b0 i
b1111 ;
bx B
bx j
1A
b0 l
08
b100 :
b100 m
b11 3
b11 p
b11 r
b0 4
b0 o
b0 q
b10 k
b100011 h
bx %
bx 9
bx y
b1111 D
b1111 e
b11000 `
b1100000010001000100011 Z
b1100000010001000100011 g
b101100 [
b110000 #
b110000 a
b110000 x
b0 M
1P
0N
0W
b100 Y
b11 X
bx T
b0 V
b11111111111111111111111111110000 O
b1100 L
b1100 c
b101000 S
bx '
bx *
bx /
bx K
b100 I
b1111 ]
b1111 t
b11 \
b11 s
1!
#170
0!
#175
b100 =
b100 f
b0 -
b0 d
b0 <
0C
b0 ;
0_
b100 D
b100 e
1>
b0 7
b0 n
bx B
bx j
b0 :
b0 m
bx 3
bx p
bx r
b0 4
b0 o
b0 q
b0 k
bx l
1A
0?
b10011 h
b11100 `
b10100000000000010010011 %
b10100000000000010010011 9
b10100000000000010010011 y
bx 5
bx u
b100 \
b100 s
0J
b1111 '
b1111 *
b1111 /
b1111 K
bx I
b1 (
b1 +
b1 .
b1 F
bx M
0P
1N
1R
b11 Y
b0 X
b100 O
b0 L
b0 c
b101100 S
b10011 Z
b10011 g
b110000 [
b11000 #
b11000 a
b11000 x
1!
#180
0!
#185
b0 =
b0 f
bx ;
bx B
bx j
b101 :
b101 m
b0 4
b0 o
b0 q
b1 7
b1 n
b0 k
1A
1>
b101000000000000100010011 %
b101000000000000100010011 9
b101000000000000100010011 y
b0 D
b0 e
b100000 `
b10100000000000010010011 Z
b10100000000000010010011 g
b11000 [
b11100 #
b11100 a
b11100 x
0R
1W
bx Y
b0 T
bx V
b0 O
b110000 S
1&
1H
b0 '
b0 *
b0 /
b0 K
b100 (
b100 +
b100 .
b100 F
b1 ]
b1 t
bx \
bx s
0^
1!
#190
0!
#195
b101 =
b101 f
b101 D
b101 e
bx B
bx j
b1010 :
b1010 m
b0 4
b0 o
b0 q
b10 7
b10 n
b0 k
1A
1>
b100100 `
b1000001000000110110011 %
b1000001000000110110011 9
b1000001000000110110011 y
b100 ]
b100 t
0&
0H
1J
bx '
bx *
bx /
bx K
b0 I
b0 (
b0 +
b0 .
b0 F
b1 T
b101 O
b11000 S
b101000000000000100010011 Z
b101000000000000100010011 g
b11100 [
b100000 #
b100000 a
b100000 x
1!
#200
0!
#205
b1010 =
b1010 f
b1010 5
b1010 u
b101 6
b101 v
b10 3
b10 p
b10 r
b0 l
bx B
bx j
bx :
bx m
b1 4
b1 o
b1 q
b11 7
b11 n
b0 k
0A
1>
b110011 h
b111100000000001000010011 %
b111100000000001000010011 9
b111100000000001000010011 y
b1010 D
b1010 e
b101000 `
b1000001000000110110011 Z
b1000001000000110110011 g
b100000 [
b100100 #
b100100 a
b100100 x
b10 T
b1010 O
b11100 S
b1 I
b101 (
b101 +
b101 .
b101 F
b0 ]
b0 t
b0 \
b0 s
1^
1!
#210
0!
#215
b1111 =
b1111 f
bx 5
bx u
b0 6
b0 v
b101 -
b101 d
b101 <
b1010 ;
b1010 D
b1010 e
1A
b1111 :
b1111 m
bx B
bx j
bx 3
bx p
bx r
b0 4
b0 o
b0 q
b100 7
b100 n
b0 k
bx l
1>
b10011 h
b101100 `
b11111110010000011000100011100011 %
b11111110010000011000100011100011 9
b11111110010000011000100011100011 y
b101 ]
b101 t
b1 \
b1 s
b10 I
b1010 (
b1010 +
b1010 .
b1010 F
0N
b10 Y
b1 X
b11 T
b1010 V
b101 U
bx O
b100000 S
b111100000000001000010011 Z
b111100000000001000010011 g
b100100 [
b101000 #
b101000 a
b101000 x
1!
#220
0!
#225
b1111 5
b1111 u
b1111 6
b1111 v
b1100 E
b1100 i
b0 -
b0 d
b0 <
18
b100 3
b100 p
b100 r
b0 B
b0 j
b11111111111111111111111111110000 :
b11111111111111111111111111110000 m
b11 4
b11 o
b11 q
bx 7
bx n
b0 k
0A
0>
b1100011 h
b1100000010001000100011 %
b1100000010001000100011 9
b1100000010001000100011 y
b1111 D
b1111 e
b110000 `
bx ;
b11111110010000011000100011100011 Z
b11111110010000011000100011100011 g
b101000 [
b101100 #
b101100 a
b101100 x
1N
bx Y
b0 X
b100 T
bx V
b0 U
b1111 O
b100100 S
b1010 '
b1010 *
b1010 /
b1010 K
b11 I
b1111 (
b1111 +
b1111 .
b1111 F
b1010 ]
b1010 t
b10 \
b10 s
1!
#230
0!
#235
1_
1C
b1 =
b1 f
b0 6
b0 v
b1111 ;
b1111 -
b1111 d
b1111 <
1?
b0 E
b0 i
b1111 D
b1111 e
bx B
bx j
1A
b0 l
08
b100 :
b100 m
b11 3
b11 p
b11 r
b0 4
b0 o
b0 q
b10 k
b100011 h
b11000 `
bx %
bx 9
bx y
b1111 ]
b1111 t
b11 \
b11 s
bx '
bx *
bx /
bx K
b100 I
b0 M
1P
0N
0W
b100 Y
b11 X
bx T
b1111 V
b1111 U
b11111111111111111111111111110000 O
b1100 L
b1100 c
b101000 S
b1100000010001000100011 Z
b1100000010001000100011 g
b101100 [
b110000 #
b110000 a
b110000 x
1!
#240
0!
