src/dmem_iverilog.v
module DMEM(
    input           clk, write_request,
    input [31:0]    mem_access_address, writedata,
    output [31:0]   readdata
);

reg [31:0] RAM[63:0];

assign readdata = RAM[mem_access_address[31:2]];

always @ (posedge clk) begin
    $display("dmemaddr: %h -> readdata: %h", mem_access_address[31:2], readdata);
    if (write_request) begin
        RAM[mem_access_address[31:2]] <= writedata;
    end
end

/* データメモリの初期化(シミュレーション用) */
integer i;
initial begin
    for (i = 0; i < 32; i = i + 1) begin
        RAM[i] = 64'b0;
    end
end

endmodule

src/imem_iverilog.v
`define MEMDATA "memory.data"

module IMEM(
    input   [31:0]  addr,
    output  [31:0]  instr
);

reg [31:0]  ROM[63:0];

initial begin
    $readmemh(`MEMDATA, ROM, 0, 63);
end

assign  instr = ROM[addr[31:2]];    // pc <= pc + 32'h4;に対応

endmodule

src/alu.v
module ALU(
    input       [3:0]   alu_op,
    input       [31:0]  src1,
    input       [31:0]  src2,
    output reg  [31:0]  aluout
);

always @* begin
    case (alu_op)
        4'b0000,
        4'b1010:
        begin
            aluout <= src1 + src2;  // add, addi
        end
        4'b0001: aluout = src1 - src2;  // sub
        4'b0010: aluout = src1 & src2;  // and
        4'b0011: aluout = src1 | src2;  // or
        4'b0100: aluout = src1 ^ src2;  // xor
        4'b1100: aluout = (src1 == src2) ? 32'b1 : 32'b0; // beq
        4'b1101: aluout = (src1 != src2) ? 32'b1 : 32'b0; // bne
        4'b1110: aluout = ($signed(src1) < $signed(src2)) ? 32'b1 : 32'b0; // blt, slt
        4'b1111: aluout = ($signed(src1) >= $signed(src2)) ? 32'b1 : 32'b0; // bge
    endcase
end

endmodule

src/regfile.v
module REGFILE(
    input clk,
    input write_request,
    input   [4:0] write_address,
    input   [4:0] read_address1,
    input   [4:0] read_address2,
    input  [31:0] write_data,
    output  [31:0] read_data1,
    output  [31:0] read_data2
);

reg [31:0] register_file [31:0];

always @ (posedge clk) begin
    if (write_request) register_file[write_address] <= write_data;
end

/* レジスタの初期化(シミュレーション用) */
integer i;
initial begin
    for (i = 0; i < 32; i = i + 1) begin
        register_file[i] = 32'b0;
    end
end

assign read_data1 = (read_address1 != 0) ? register_file[read_address1] : 0;
assign read_data2 = (read_address2 != 0) ? register_file[read_address2] : 0;

endmodule

src/decoder.v
module DECODER(
    input       [31:0]  instr,
    output reg  [3:0]   alu_op,
    output reg  [31:0]  immext,
    output reg  [4:0]   rd, rs1, rs2,
    output reg          reg_write_request,
    output reg          mem_write_request,
    output reg          mem_read_request,
    output reg          imm_enable
);

    reg debug_isload;
    reg debug_isstore;
    wire [6:0] opcode = instr[6:0];
    reg [6:0] funct7;
    reg [2:0] funct3;

    // 初期化（デフォルト値設定）
    always @* begin
        reg_write_request = 1'b0;
        mem_write_request = 1'b0;
        mem_read_request  = 1'b0;
        imm_enable        = 1'b0;
        funct7            = 7'bx;
        funct3            = 3'bx;
        rd                = 5'bx;
        rs1               = 5'bx;
        rs2               = 5'bx;
        immext            = 32'bx;
        debug_isload = 0;
        debug_isstore = 0;

        case (opcode)
            /* R-type */
            7'b0110011: begin
                funct7          = instr[31:25];
                funct3          = instr[14:12];
                immext          = 32'bx;
                rd              = instr[11:7];
                rs1             = instr[19:15];
                rs2             = instr[24:20];
                reg_write_request = 1'b1;
                imm_enable      = 1'b0;
            end

            /* I-type */
            7'b0010011, // addi
            7'b0000011: // lw
            begin
                funct7          = 7'bx;
                funct3          = instr[14:12];
                immext          = {{20{instr[31]}}, instr[31:20]};
                rd              = instr[11:7];
                rs1             = instr[19:15];
                rs2             = 5'bx;
                reg_write_request = 1'b1;
                imm_enable      = 1'b1;
                // $display("immext1: %h (opcode: %b)", immext, opcode);
            end

            /* S-type */
            7'b0100011: // sw
            begin
                funct7          = instr[31:25];
                funct3          = instr[14:12];
                immext          = {{20{instr[31]}}, instr[31:25], instr[11:7]};
                rd              = 5'bx;
                rs1             = instr[19:15];
                rs2             = instr[24:20];
                reg_write_request = 1'b0;
                imm_enable          = 1'b1;
                debug_isstore = 1'b1;
                $display("immext2: %h (opcode: %b)", immext, opcode);
            end

            /* B-type */
            7'b1100011: begin // branch instructions
                funct7          = 7'bx;
                funct3          = 3'bx;
                immext          = 32'bx;
                rd              = 5'bx;
                rs1             = 5'bx;
                rs2             = 5'bx;
            end

            /* U-type */
            7'b0110111,  // LUI
            7'b0010111: begin  // AUIPC
                funct7          = 7'bx;
                funct3          = 3'bx;
                immext          = 32'bx;
                rd              = instr[11:7];
                rs1             = 5'bx;
                rs2             = 5'bx;
            end

            /* J-type */
            7'b1101111: begin // jal
                funct7          = 7'bx;
                funct3          = 3'bx;
                immext          = 32'bx;
                rd              = instr[11:7];
                rs1             = 5'bx;
                rs2             = 5'bx;
            end

            default: begin
                funct7          = 7'bx;
                funct3          = 3'bx;
                immext          = 32'bx;
                rd              = 5'bx;
                rs1             = 5'bx;
                rs2             = 5'bx;
            end
        endcase
    end

    // ALU operation decoding
    always @* begin
        case (funct3)
            3'b000: begin
                if (opcode == 7'b0110011) // R-type
                begin
                    case (funct7)
                        7'b0000000: alu_op = 4'b0000;  // add
                        7'b0100000: alu_op = 4'b0001;  // sub
                        default:    alu_op = 4'bx;
                    endcase
                end
                else if (opcode == 7'b0010011) // I-type (addi)
                begin
                    alu_op = 4'b0000;   // addi
                end
                else begin
                    alu_op = 4'bx;
                end
            end

            3'b001: alu_op = 4'b0010;  // sll
            3'b010: begin
                case (opcode)
                    7'b0000011: begin // lw
                        alu_op = 4'b0000; // addでアドレス計算
                        reg_write_request = 1;
                        mem_read_request  = 1;
                        debug_isload = 1;
                    end

                    7'b0100011: begin // sw
                        alu_op = 4'b0000;
                        mem_write_request = 1;
                    end
                    default: alu_op = 4'bx;
                endcase
            end

            3'b011: alu_op = 4'b0100;  // sltu
            3'b100: alu_op = 4'b0101;  // xor
            3'b101: begin
                case (funct7)
                    7'b0000000: alu_op = 4'b0110;  // srl
                    7'b0100000: alu_op = 4'b0111;  // sra
                    default:    alu_op = 4'bx;
                endcase
            end
            3'b110: alu_op = 4'b1000;  // or
            3'b111: alu_op = 4'b1001;  // and
            default: alu_op = 4'bx;
        endcase
    end

endmodule


// module DECODER(
//     input       [31:0]  instr,
//     output reg  [3:0]   alu_op,
//     output reg  [31:0]  immext,
//     output reg  [4:0]   rd, rs1, rs2,
//     output reg          reg_write_request,
//     output reg          mem_write_request,
//     output reg          mem_read_request,
//     output reg          imm_enable
// );

//     wire [6:0] opcode = instr[6:0];
//     wire [2:0] funct3 = instr[14:12];
//     wire [6:0] funct7 = instr[31:25];

//     always @* begin
//         // デフォルト値の設定
//         alu_op             = 4'bxxxx;
//         immext             = 32'b0;
//         rd                 = 5'b0;
//         rs1                = 5'b0;
//         rs2                = 5'b0;
//         reg_write_request  = 1'b0;
//         mem_write_request  = 1'b0;
//         mem_read_request   = 1'b0;
//         imm_enable         = 1'b0;

//         case (opcode)
//             7'b0110011: begin // R-type
//                 rd    = instr[11:7];
//                 rs1   = instr[19:15];
//                 rs2   = instr[24:20];
//                 reg_write_request = 1;
//                 imm_enable = 0;
//                 case (funct3)
//                     3'b000: alu_op = (funct7 == 7'b0100000) ? 4'b0001 : 4'b0000; // sub : add
//                     3'b001: alu_op = 4'b0010; // sll
//                     3'b010: alu_op = 4'b0011; // slt
//                     3'b011: alu_op = 4'b0100; // sltu
//                     3'b100: alu_op = 4'b0101; // xor
//                     3'b101: alu_op = (funct7 == 7'b0100000) ? 4'b0111 : 4'b0110; // sra : srl
//                     3'b110: alu_op = 4'b1000; // or
//                     3'b111: alu_op = 4'b1001; // and
//                     default: alu_op = 4'bxxxx;
//                 endcase
//             end

//             7'b0010011: begin // I-type (addi, etc.)
//                 rd    = instr[11:7];
//                 rs1   = instr[19:15];
//                 immext = {{20{instr[31]}}, instr[31:20]};
//                 reg_write_request = 1;
//                 imm_enable = 1;
//                 case (funct3)
//                     3'b000: alu_op = 4'b0000; // addi
//                     default: alu_op = 4'bxxxx;
//                 endcase
//                 $display("immext1: %h (opcode: %b)", immext, opcode);
//             end

//             7'b0000011: begin // I-type (lw)
//                 rd    = instr[11:7];
//                 rs1   = instr[19:15];
//                 immext = {{20{instr[31]}}, instr[31:20]};
//                 reg_write_request = 1;
//                 mem_read_request  = 1;
//                 imm_enable = 1;
//                 alu_op = 4'b0000; // address = rs1 + imm
//                 $display("immext1: %h (opcode: %b)", immext, opcode);
//             end

//             7'b0100011: begin // S-type (sw)
//                 rs1   = instr[19:15];
//                 rs2   = instr[24:20];
//                 immext = {{27{instr[11]}}, instr[11:7]};
//                 mem_write_request = 1;
//                 imm_enable = 1;
//                 alu_op = 4'b0000; // address = rs1 + imm
//                 $display("immext2: %h (opcode: %b)", immext, opcode);
//             end

//             7'b1100011: begin // B-type (e.g., beq)
//                 rs1   = instr[19:15];
//                 rs2   = instr[24:20];
//                 immext = {{20{instr[31]}}, instr[7], instr[30:25], instr[11:8], 1'b0};
//                 alu_op = 4'b1010; // 仮: 比較命令
//                 imm_enable = 1;
//             end

//             7'b0110111: begin // LUI
//                 rd = instr[11:7];
//                 immext = {instr[31:12], 12'b0};
//                 reg_write_request = 1;
//                 imm_enable = 1;
//                 alu_op = 4'b0000;
//             end

//             7'b0010111: begin // AUIPC
//                 rd = instr[11:7];
//                 immext = {instr[31:12], 12'b0};
//                 reg_write_request = 1;
//                 imm_enable = 1;
//                 alu_op = 4'b0000;
//             end

//             7'b1101111: begin // JAL
//                 rd = instr[11:7];
//                 immext = {{12{instr[31]}}, instr[19:12], instr[20], instr[30:21], 1'b0};
//                 reg_write_request = 1;
//                 imm_enable = 1;
//                 alu_op = 4'b0000;
//             end

//             default: begin
//                 alu_op = 4'bxxxx;
//             end
//         endcase
//     end
// endmodule

src/haconiwa_core.v
module HACONIWA_CORE(
    input   clk,
    input   reset,
    output reg [31:0]   pc,
    input  [31:0]   instr,
    output  core2mem_write_request,
    output [31:0]   mem_access_address,
    output [31:0]   writedata,
    input  [31:0]   readdata
);

/* IF */
// pc counter
always @ (posedge clk) begin
    if (reset) begin
        pc <= 32'h0;
    end else begin
        pc <= pc + 32'h4;
    end
    $display("PC: %h, instr: %h", pc, instr);
end


/* DECODE */
wire         reg_write_request_raw, mem_read_request_raw, mem_write_request_raw;
wire [3:0]   alu_op;
wire [31:0]  immext;
wire [4:0]   rd_raw, rs1, rs2;
wire [31:0]  read_reg_data1, read_reg_data2, aluout_raw;
wire imm_enable;
reg reg_write_request;
reg mem_read_request;
reg mem_write_request;
reg [31:0] aluout, mem_write_data;
reg [4:0] reg_write_addr;

// decoder
DECODER dec(
    .instr(instr),
    .alu_op(alu_op),
    .immext(immext),
    .rd(rd_raw),
    .rs1(rs1),
    .rs2(rs2),
    .reg_write_request(reg_write_request_raw),
    .mem_write_request(mem_write_request_raw),
    .mem_read_request(mem_read_request_raw),
    .imm_enable(imm_enable)
);

// reg
wire [31:0] reg_write_data = (mem_read_request) ? readdata : aluout;

REGFILE regfile(
    .clk(clk),
    .write_request(reg_write_request),
    .write_address(reg_write_addr),
    .read_address1(rs1),
    .read_address2(rs2),
    .write_data(reg_write_data),
    .read_data1(read_reg_data1),
    .read_data2(read_reg_data2)
);

/* EXE */
wire [31:0] alu_src1, alu_src2;

assign alu_src1 = read_reg_data1;
assign alu_src2 = imm_enable ? immext : read_reg_data2;

// alu
ALU alu(
    .alu_op(alu_op),
    .src1(alu_src1),
    .src2(alu_src2),
    .aluout(aluout_raw)
);

/* WB preparation */
// latch
always @ (posedge clk) begin
    mem_read_request <= mem_read_request_raw;
    mem_write_request <= mem_write_request_raw;
    reg_write_request <= reg_write_request_raw;
    mem_write_data    <= read_reg_data2;
    aluout   <= aluout_raw;
    reg_write_addr   <= rd_raw;
end

/* MEM */
// mem
assign mem_access_address = (mem_read_request || mem_write_request) ? aluout : 32'bx;
assign core2mem_write_request = mem_write_request;
assign writedata = mem_write_data;

endmodule

src/haconiwa_top.v
module HACONIWA_TOP(
    input   CLOCK_50_B5B, CPU_RESET_n
);

wire [31:0] pc, instr, readdata, mem_access_address, writedata;
wire mem_write_request;

HACONIWA_CORE hcore(
    .clk(CLOCK_50_B5B),
    .reset(!CPU_RESET_n),
    .pc(pc),
    .instr(instr),
    .core2mem_write_request(mem_write_request),
    .mem_access_address(mem_access_address),
    .writedata(writedata),
    .readdata(readdata)    
);

IMEM imem(
    .addr(pc),
    .instr(instr)
);

DMEM dmem(
    .clk(CLOCK_50_B5B),
    .write_request(mem_write_request),
    .mem_access_address(mem_access_address),
    .writedata(writedata),
    .readdata(readdata)
);

endmodule

module SIMTOP();
    reg clk, reset;

    HACONIWA_TOP htop(
        .CLOCK_50_B5B(clk),
        .CPU_RESET_n(!reset)
    );

    initial begin
        clk = 0;
        forever #5 clk = ~clk;
    end

    initial begin
        #10 reset = 1;
        #20 reset = 0;
        $dumpfile("sim_top_haconiwa.vcd");
        $dumpvars(0, htop);

        #120 $finish;
    end
endmodule

test/sim_top_haconiwa.vcd
$date
	Fri May  2 01:05:42 2025
$end
$version
	Icarus Verilog
$end
$timescale
	1s
$end
$scope module SIMTOP $end
$scope module htop $end
$var wire 1 ! CLOCK_50_B5B $end
$var wire 1 " CPU_RESET_n $end
$var wire 32 # writedata [31:0] $end
$var wire 32 $ readdata [31:0] $end
$var wire 32 % pc [31:0] $end
$var wire 1 & mem_write_request $end
$var wire 32 ' mem_access_address [31:0] $end
$var wire 32 ( instr [31:0] $end
$scope module dmem $end
$var wire 1 ! clk $end
$var wire 32 ) readdata [31:0] $end
$var wire 32 * writedata [31:0] $end
$var wire 1 & write_request $end
$var wire 32 + mem_access_address [31:0] $end
$var integer 32 , i [31:0] $end
$upscope $end
$scope module hcore $end
$var wire 32 - alu_src1 [31:0] $end
$var wire 1 ! clk $end
$var wire 1 & core2mem_write_request $end
$var wire 32 . readdata [31:0] $end
$var wire 1 / reset $end
$var wire 32 0 writedata [31:0] $end
$var wire 5 1 rs2 [4:0] $end
$var wire 5 2 rs1 [4:0] $end
$var wire 1 3 reg_write_request_raw $end
$var wire 32 4 reg_write_data [31:0] $end
$var wire 32 5 read_reg_data2 [31:0] $end
$var wire 32 6 read_reg_data1 [31:0] $end
$var wire 5 7 rd_raw [4:0] $end
$var wire 1 8 mem_write_request_raw $end
$var wire 1 9 mem_read_request_raw $end
$var wire 32 : mem_access_address [31:0] $end
$var wire 32 ; instr [31:0] $end
$var wire 32 < immext [31:0] $end
$var wire 1 = imm_enable $end
$var wire 32 > aluout_raw [31:0] $end
$var wire 32 ? alu_src2 [31:0] $end
$var wire 4 @ alu_op [3:0] $end
$var reg 32 A aluout [31:0] $end
$var reg 1 B mem_read_request $end
$var reg 32 C mem_write_data [31:0] $end
$var reg 1 D mem_write_request $end
$var reg 32 E pc [31:0] $end
$var reg 5 F reg_write_addr [4:0] $end
$var reg 1 G reg_write_request $end
$scope module alu $end
$var wire 32 H src1 [31:0] $end
$var wire 32 I src2 [31:0] $end
$var wire 4 J alu_op [3:0] $end
$var reg 32 K aluout [31:0] $end
$upscope $end
$scope module dec $end
$var wire 7 L opcode [6:0] $end
$var wire 32 M instr [31:0] $end
$var reg 4 N alu_op [3:0] $end
$var reg 1 O debug_isload $end
$var reg 1 P debug_isstore $end
$var reg 3 Q funct3 [2:0] $end
$var reg 7 R funct7 [6:0] $end
$var reg 1 = imm_enable $end
$var reg 32 S immext [31:0] $end
$var reg 1 9 mem_read_request $end
$var reg 1 8 mem_write_request $end
$var reg 5 T rd [4:0] $end
$var reg 1 3 reg_write_request $end
$var reg 5 U rs1 [4:0] $end
$var reg 5 V rs2 [4:0] $end
$upscope $end
$scope module regfile $end
$var wire 1 ! clk $end
$var wire 5 W read_address1 [4:0] $end
$var wire 5 X read_address2 [4:0] $end
$var wire 5 Y write_address [4:0] $end
$var wire 32 Z write_data [31:0] $end
$var wire 1 G write_request $end
$var wire 32 [ read_data2 [31:0] $end
$var wire 32 \ read_data1 [31:0] $end
$var integer 32 ] i [31:0] $end
$upscope $end
$upscope $end
$scope module imem $end
$var wire 32 ^ addr [31:0] $end
$var wire 32 _ instr [31:0] $end
$upscope $end
$upscope $end
$upscope $end
$enddefinitions $end
$comment Show the parameter values. $end
$dumpall
$end
#30
$dumpvars
b10100000000000010010011 _
b0 ^
b100000 ]
b0 \
bx [
b101 Z
b1 Y
bx X
b0 W
bx V
b0 U
b1 T
b101 S
bx R
b0 Q
0P
0O
b0 N
b10100000000000010010011 M
b10011 L
b101 K
b0 J
b101 I
b0 H
1G
b1 F
b0 E
0D
bx C
0B
b101 A
b0 @
b101 ?
b101 >
1=
b101 <
b10100000000000010010011 ;
bx :
09
08
b1 7
b0 6
bx 5
b101 4
13
b0 2
bx 1
bx 0
0/
bx .
b0 -
b100000 ,
bx +
bx *
bx )
b10100000000000010010011 (
bx '
0&
b0 %
bx $
bx #
1"
0!
$end
#35
b1010 >
b1010 K
b1010 ?
b1010 I
b1010 <
b1010 S
b0 2
b0 U
b0 W
b10 7
b10 T
b0 Q
1=
13
b101000000000000100010011 (
b101000000000000100010011 ;
b101000000000000100010011 M
b101000000000000100010011 _
b100 %
b100 E
b100 ^
1!
#40
0!
#45
b0 >
b0 K
b0 ?
b0 I
b0 <
b0 S
b0 2
b0 U
b0 W
b0 7
b0 T
b0 Q
1=
13
b10011 (
b10011 ;
b10011 M
b10011 _
b1010 4
b1010 Z
b1000 %
b1000 E
b1000 ^
b10 F
b10 Y
b1010 A
1!
#50
0!
#55
b1111 >
b1111 K
b1010 5
b1010 [
b101 -
b101 H
b101 6
b101 \
b10 1
b10 V
b10 X
b0 R
b0 @
b0 J
b0 N
b1010 ?
b1010 I
b110011 L
bx <
bx S
b1 2
b1 U
b1 W
b11 7
b11 T
b0 Q
0=
13
b0 4
b0 Z
b1000001000000110110011 (
b1000001000000110110011 ;
b1000001000000110110011 M
b1000001000000110110011 _
b0 F
b0 Y
b0 A
b1100 %
b1100 E
b1100 ^
1!
#60
0!
#65
b0 >
b0 K
b0 ?
b0 I
bx 5
bx [
b0 -
b0 H
b0 6
b0 \
1=
b0 <
b0 S
b10011 L
bx 1
bx V
bx X
b0 2
b0 U
b0 W
b0 7
b0 T
b0 Q
bx R
13
b10011 (
b10011 ;
b10011 M
b10011 _
b1111 4
b1111 Z
b10000 %
b10000 E
b10000 ^
b11 F
b11 Y
b1111 A
b1010 #
b1010 *
b1010 0
b1010 C
1!
#70
0!
#75
b100 >
b100 K
b1111 5
b1111 [
1P
b11 1
b11 V
b11 X
b0 R
18
b100 ?
b100 I
b100011 L
b100 <
b100 S
b0 2
b0 U
b0 W
bx 7
bx T
b10 Q
1=
03
b0 4
b0 Z
b1100000010001000100011 (
b1100000010001000100011 ;
b1100000010001000100011 M
b1100000010001000100011 _
b0 F
b0 Y
b0 A
bx #
bx *
bx 0
bx C
b10100 %
b10100 E
b10100 ^
1!
#80
0!
#85
bx 5
bx [
13
b100 7
b100 T
b0 $
b0 )
b0 .
b10011 L
0P
b100 <
b100 S
bx 1
bx V
bx X
b0 2
b0 U
b0 W
b0 Q
bx R
1=
08
b100 '
b100 +
b100 :
b10000000000001000010011 (
b10000000000001000010011 ;
b10000000000001000010011 M
b10000000000001000010011 _
b100 4
b100 Z
b11000 %
b11000 E
b11000 ^
bx F
bx Y
b100 A
b1111 #
b1111 *
b1111 0
b1111 C
0G
1&
1D
1!
#90
0!
#95
b0 >
b0 K
b0 ?
b0 I
bx '
bx +
bx :
b0 <
b0 S
b0 2
b0 U
b0 W
b0 7
b0 T
b0 Q
1=
13
b10011 (
b10011 ;
b10011 M
b10011 _
bx $
bx )
bx .
b100 F
b100 Y
bx #
bx *
bx 0
bx C
1G
0&
0D
b11100 %
b11100 E
b11100 ^
1!
#100
0!
#105
b100 >
b100 K
b100 -
b100 H
b100 6
b100 \
1O
19
b11 L
b0 <
b0 S
b100 2
b100 U
b100 W
b101 7
b101 T
b10 Q
1=
13
b100010001010000011 (
b100010001010000011 ;
b100010001010000011 M
b100010001010000011 _
b0 4
b0 Z
b100000 %
b100000 E
b100000 ^
b0 F
b0 Y
b0 A
1!
#110
0!
#115
b0 >
b0 K
b0 -
b0 H
b0 6
b0 \
b1111 $
b1111 )
b1111 .
b100 '
b100 +
b100 :
b10011 L
0O
b0 <
b0 S
b0 2
b0 U
b0 W
b0 7
b0 T
b0 Q
1=
09
13
b1111 4
b1111 Z
b10011 (
b10011 ;
b10011 M
b10011 _
b101 F
b101 Y
b100 A
1B
b100100 %
b100100 E
b100100 ^
1!
#120
0!
#125
b10100 >
b10100 K
b1111 5
b1111 [
b101 -
b101 H
b101 6
b101 \
b101 1
b101 V
b101 X
b0 R
b0 @
b0 J
b0 N
b1111 ?
b1111 I
b110011 L
bx <
bx S
b1 2
b1 U
b1 W
b110 7
b110 T
b0 Q
0=
13
bx $
bx )
bx .
b10100001000001100110011 (
b10100001000001100110011 ;
b10100001000001100110011 M
b10100001000001100110011 _
bx '
bx +
bx :
b0 4
b0 Z
b101000 %
b101000 E
b101000 ^
b0 F
b0 Y
b0 A
0B
1!
#130
0!
#135
bx ?
bx I
bx 5
bx [
bx -
bx H
bx 6
bx \
bx @
bx J
bx N
bx L
bx 1
bx V
bx X
bx 2
bx U
bx W
bx 7
bx T
bx Q
bx R
03
b10100 4
b10100 Z
bx (
bx ;
bx M
bx _
b110 F
b110 Y
b10100 A
b1111 #
b1111 *
b1111 0
b1111 C
b101100 %
b101100 E
b101100 ^
1!
#140
0!
#145
b110000 %
b110000 E
b110000 ^
bx F
bx Y
bx #
bx *
bx 0
bx C
0G
1!
