src/dmem_iverilog.v
module DMEM(
    input           clk, write_enable,
    input [31:0]    dataaddr, writedata,
    output [31:0]   readdata
);

reg [31:0] RAM[63:0];

assign readdata = RAM[dataaddr[31:2]];

always @ (posedge clk)
    if (write_enable)
        RAM[dataaddr[31:2]] <= writedata;

/* データメモリの初期化(シミュレーション用) */
integer i;
initial begin
    for (i = 0; i < 32; i = i + 1) begin
        RAM[i] = 64'b0;
    end
end

endmodule

src/imem_iverilog.v
`define MEMDATA "memory.data"

module IMEM(
    input   [31:0]  addr,
    output  [31:0]  instr
);

reg [31:0]  ROM[63:0];

initial begin
    $readmemh(`MEMDATA, ROM, 0, 63);
end

assign  instr = ROM[addr[31:2]];    // pc <= pc + 32'h4;に対応

endmodule

src/alu.v
module ALU(
    input       [3:0]   alu_op,
    input       [31:0]  src1,
    input       [31:0]  src2,
    output reg  [31:0]  aluout
);

always @* begin
    case (alu_op)
        4'b0000,
        4'b1010:
        begin
            aluout <= src1 + src2;  // add, addi
        end
        4'b0001: aluout = src1 - src2;  // sub
        4'b0010: aluout = src1 & src2;  // and
        4'b0011: aluout = src1 | src2;  // or
        4'b0100: aluout = src1 ^ src2;  // xor
        4'b1100: aluout = (src1 == src2) ? 32'b1 : 32'b0; // beq
        4'b1101: aluout = (src1 != src2) ? 32'b1 : 32'b0; // bne
        4'b1110: aluout = ($signed(src1) < $signed(src2)) ? 32'b1 : 32'b0; // blt, slt
        4'b1111: aluout = ($signed(src1) >= $signed(src2)) ? 32'b1 : 32'b0; // bge
    endcase
end

endmodule

src/regfile.v
module REGFILE(
    input clk,
    input write_enable,
    input   [4:0] write_address,
    input   [4:0] read_address1,
    input   [4:0] read_address2,
    input  [31:0] write_data,
    output  [31:0] read_data1,
    output  [31:0] read_data2
);

reg [31:0] register_file [31:0];

// always @ (posedge clk) begin
//     if (write_enable) register_file[write_address] <= write_data;
// end

/* レジスタの初期化(シミュレーション用) */
integer i;
initial begin
    for (i = 0; i < 32; i = i + 1) begin
        register_file[i] = 32'b0;
    end
end

assign read_data1 = (read_address1 != 0) ? register_file[read_address1] : 0;
assign read_data2 = (read_address2 != 0) ? register_file[read_address2] : 0;

endmodule

src/decoder.v

/*
    少なくともaddはよさそう
*/

module DECODER(
    input       [31:0]  instr,
    output reg  [3:0]   alu_op,
    output reg  [31:0]  immext,
    output reg  [4:0]   rd, rs1, rs2,
    output reg          write_enable
);

wire [6:0] opcode = instr[6:0];
reg [6:0] funct7;
reg [2:0] funct3;

always @* begin
    case (opcode)
        /* R-type */
        7'b0110011:
        begin
            funct7          = instr[31:25];
            funct3          = instr[14:12];
            immext          = 32'bx;
            rd              = instr[11:7];
            rs1             = instr[19:15];
            rs2             = instr[24:20];
            write_enable    = 1'b1;
        end

        /* I-type */
        7'b0010011,
        7'b0000011,
        7'b1100011:
        begin
            funct7  = 7'bx;
            funct3  = 3'bx;
            immext  = 32'bx;
            rd      = 4'bx;
            rs1     = 4'bx;
            rs2     = 4'bx;
        end

        /* S-type */
        7'b0100011:
        begin
            funct7  = 7'bx;
            funct3  = 3'bx;
            immext  = 32'bx;
            rd      = 4'bx;
            rs1     = 4'bx;
            rs2     = 4'bx;
        end

        /* B-type */
        7'b1100011:
        begin
            funct7  = 7'bx;
            funct3  = 3'bx;
            immext  = 32'bx;
            rd      = 4'bx;
            rs1     = 4'bx;
            rs2     = 4'bx;
        end

        /* U-type */
        7'b011011,
        7'b0010111:
        begin
            funct7  = 7'bx;
            funct3  = 3'bx;
            immext  = 32'bx;
            rd      = 4'bx;
            rs1     = 4'bx;
            rs2     = 4'bx;
        end

        /* J-type */
        7'b1101111:
        begin
            funct7  = 7'bx;
            funct3  = 3'bx;
            immext  = 32'bx;
            rd      = 4'bx;
            rs1     = 4'bx;
            rs2     = 4'bx;
        end

        default:
        begin
            funct7  = 7'bx;
            funct3  = 3'bx;
            immext  = 32'bx;
            rd      = 4'bx;
            rs1     = 4'bx;
            rs2     = 4'bx;
        end
    endcase
end

always @* begin
    case (funct3)
        3'b000: begin
            case (funct7)
                7'b0000000: alu_op = 4'b0000;  // add
                7'b0100000: alu_op = 4'b0001;  // sub
                default:    alu_op = 4'bx;
            endcase
        end
        3'b001: alu_op = 4'b0010;  // sll
        3'b010: alu_op = 4'b0011;  // slt
        3'b011: alu_op = 4'b0100;  // sltu
        3'b100: alu_op = 4'b0101;  // xor
        3'b101: begin
            case (funct7)
                7'b0000000: alu_op = 4'b0110;  // srl
                7'b0100000: alu_op = 4'b0111;  // sra
                default:    alu_op = 4'bx;
            endcase
        end
        3'b110: alu_op = 4'b1000;  // or
        3'b111: alu_op = 4'b1001;  // and
        default:
            alu_op = 4'bx;
    endcase
end

endmodule

// module SIM_DEC();
//     reg clk;
//     reg[31:0] instr;
//     wire[31:0] immext;
//     wire[3:0] alu_op;
//     wire[4:0] rd, rs1, rs2;

//     DECODER dec(
//         .instr(instr),
//         .alu_op(alu_op),
//         .immext(immext),
//         .rd(rd),
//         .rs1(rs1),
//         .rs2(rs2)
//     );

//     initial begin
//         clk = 0;
//         forever #10 clk = ~clk;
//     end

//     initial begin
//         $dumpfile("sim_dec.vcd");
//         $dumpvars(0, dec);
        
//         #10
//         instr = 32'b00000001000010000000100000110011;
        
//         #10 $finish;
//     end

// endmodule

src/haconiwa_core.v
module HACONIWA_CORE(
    input   clk,
    input   reset,
    output reg [31:0]   pc,
    input  [31:0]   instr,
    output  mem_write_enable,
    output [31:0]   dataaddr,
    output [31:0]   writedata,
    input  [31:0]   readdata
);

/* IF */
// pc counter
always @ (posedge clk) begin
    if (reset) begin
        pc <= 32'h0;
    end else begin
        pc <= pc + 32'h4;
    end
    // $display("PC: %h", pc);
end


/* DECODE */
wire         reg_write_enable_raw;
wire [3:0]   alu_op;
wire [31:0]  immext;
wire [4:0]   rd_raw, rs1, rs2;
wire [31:0]  read_reg_data1, read_reg_data2, aluout_raw;
reg reg_write_enable;
reg [31:0] reg_write_data;
reg [4:0] reg_write_addr;

// decoder
DECODER dec(
    .instr(instr),
    .alu_op(alu_op),
    .immext(immext),
    .rd(rd_raw),
    .rs1(rs1),
    .rs2(rs2),
    .write_enable(reg_write_enable_raw)
);

// reg
REGFILE regfile(
    .clk(clk),
    .write_enable(reg_write_enable),
    .write_address(reg_write_addr),
    .read_address1(rs1),
    .read_address2(rs2),
    .write_data(reg_write_data),
    .read_data1(read_reg_data1),
    .read_data2(read_reg_data2)
);

/* EXE */
// alu
ALU alu(
    .alu_op(alu_op),
    .src1(read_reg_data1),
    .src2(read_reg_data2),
    .aluout(aluout_raw)
);

/* WB preparation */
// latch
always @ (posedge clk) begin
    reg_write_enable <= reg_write_enable_raw;
    reg_write_data   <= aluout_raw;
    reg_write_addr   <= rd_raw;
end

/* MEM */
// mem


endmodule

src/haconiwa_top.v
module HACONIWA_TOP(
    input   CLOCK_50_B5B, CPU_RESET_n
);

wire [31:0] pc, instr, readdata, dataaddr, writedata;
wire mem_write_enable;

HACONIWA_CORE hcore(
    .clk(CLOCK_50_B5B),
    .reset(!CPU_RESET_n),
    .pc(pc),
    .instr(instr),
    .mem_write_enable(mem_write_enable),
    .dataaddr(dataaddr),
    .writedata(writedata),
    .readdata(readdata)    
);

IMEM imem(
    .addr(pc),
    .instr(instr)
);

DMEM dmem(
    .clk(CLOCK_50_B5B),
    .write_enable(mem_write_enable),
    .dataaddr(dataaddr),
    .writedata(writedata),
    .readdata(readdata)
);

endmodule

module SIMTOP();
    reg clk, reset;

    HACONIWA_TOP htop(
        .CLOCK_50_B5B(clk),
        .CPU_RESET_n(!reset)
    );

    initial begin
        clk = 0;
        forever #5 clk = ~clk;
    end

    initial begin
        #10 reset = 1;
        #20 reset = 0;
        $dumpfile("sim_top_haconiwa.vcd");
        $dumpvars(0, htop);

        #1000 $finish;
    end
endmodule

test/sim_top_haconiwa.vcd
$date
	Thu May  1 00:40:16 2025
$end
$version
	Icarus Verilog
$end
$timescale
	1s
$end
$scope module SIMTOP $end
$scope module htop $end
$var wire 1 ! CLOCK_50_B5B $end
$var wire 1 " CPU_RESET_n $end
$var wire 32 # dataaddr [31:0] $end
$var wire 1 $ mem_write_enable $end
$var wire 32 % writedata [31:0] $end
$var wire 32 & readdata [31:0] $end
$var wire 32 ' pc [31:0] $end
$var wire 32 ( instr [31:0] $end
$scope module dmem $end
$var wire 1 ! clk $end
$var wire 32 ) dataaddr [31:0] $end
$var wire 32 * readdata [31:0] $end
$var wire 1 $ write_enable $end
$var wire 32 + writedata [31:0] $end
$var integer 32 , i [31:0] $end
$upscope $end
$scope module hcore $end
$var wire 1 ! clk $end
$var wire 32 - dataaddr [31:0] $end
$var wire 1 $ mem_write_enable $end
$var wire 32 . readdata [31:0] $end
$var wire 1 / reset $end
$var wire 32 0 writedata [31:0] $end
$var wire 5 1 rs2 [4:0] $end
$var wire 5 2 rs1 [4:0] $end
$var wire 1 3 reg_write_enable_raw $end
$var wire 32 4 read_reg_data2 [31:0] $end
$var wire 32 5 read_reg_data1 [31:0] $end
$var wire 5 6 rd_raw [4:0] $end
$var wire 32 7 instr [31:0] $end
$var wire 32 8 immext [31:0] $end
$var wire 32 9 aluout_raw [31:0] $end
$var wire 4 : alu_op [3:0] $end
$var reg 32 ; pc [31:0] $end
$var reg 5 < reg_write_addr [4:0] $end
$var reg 32 = reg_write_data [31:0] $end
$var reg 1 > reg_write_enable $end
$scope module alu $end
$var wire 32 ? src2 [31:0] $end
$var wire 32 @ src1 [31:0] $end
$var wire 4 A alu_op [3:0] $end
$var reg 32 B aluout [31:0] $end
$upscope $end
$scope module dec $end
$var wire 7 C opcode [6:0] $end
$var wire 32 D instr [31:0] $end
$var reg 4 E alu_op [3:0] $end
$var reg 3 F funct3 [2:0] $end
$var reg 7 G funct7 [6:0] $end
$var reg 32 H immext [31:0] $end
$var reg 5 I rd [4:0] $end
$var reg 5 J rs1 [4:0] $end
$var reg 5 K rs2 [4:0] $end
$var reg 1 3 write_enable $end
$upscope $end
$scope module regfile $end
$var wire 1 ! clk $end
$var wire 5 L read_address1 [4:0] $end
$var wire 5 M read_address2 [4:0] $end
$var wire 5 N write_address [4:0] $end
$var wire 32 O write_data [31:0] $end
$var wire 1 > write_enable $end
$var wire 32 P read_data2 [31:0] $end
$var wire 32 Q read_data1 [31:0] $end
$var integer 32 R i [31:0] $end
$upscope $end
$upscope $end
$scope module imem $end
$var wire 32 S addr [31:0] $end
$var wire 32 T instr [31:0] $end
$upscope $end
$upscope $end
$upscope $end
$enddefinitions $end
$comment Show the parameter values. $end
$dumpall
$end
#30
$dumpvars
b10100000000000100010011 T
b0 S
b100000 R
bx Q
bx P
bx O
b0xxxx N
b0xxxx M
b0xxxx L
b0xxxx K
b0xxxx J
b0xxxx I
bx H
bx G
bx F
bx E
b10100000000000100010011 D
b10011 C
bx B
bx A
bx @
bx ?
x>
bx =
b0xxxx <
b0 ;
bx :
bx 9
bx 8
b10100000000000100010011 7
b0xxxx 6
bx 5
bx 4
x3
b0xxxx 2
b0xxxx 1
bz 0
0/
bx .
bz -
b100000 ,
bz +
bx *
bz )
b10100000000000100010011 (
b0 '
bx &
bz %
z$
bz #
1"
0!
$end
#35
b110000000000000110010011 (
b110000000000000110010011 7
b110000000000000110010011 D
b110000000000000110010011 T
b100 '
b100 ;
b100 S
1!
#40
0!
#45
b11111111011100011000001110010011 (
b11111111011100011000001110010011 7
b11111111011100011000001110010011 D
b11111111011100011000001110010011 T
b1000 '
b1000 ;
b1000 S
1!
#50
0!
#55
b0 4
b0 ?
b0 P
b0 5
b0 @
b0 Q
b1000 :
b1000 A
b1000 E
13
b10 1
b10 K
b10 M
b111 2
b111 J
b111 L
b100 6
b100 I
b110 F
b0 G
b110011 C
b1000111110001000110011 (
b1000111110001000110011 7
b1000111110001000110011 D
b1000111110001000110011 T
b1100 '
b1100 ;
b1100 S
1!
#60
0!
#65
b1001 :
b1001 A
b1001 E
b100 1
b100 K
b100 M
b11 2
b11 J
b11 L
b101 6
b101 I
b111 F
b10000011111001010110011 (
b10000011111001010110011 7
b10000011111001010110011 D
b10000011111001010110011 T
b10000 '
b10000 ;
b10000 S
b100 <
b100 N
1>
1!
#70
0!
#75
b0 9
b0 B
b0 :
b0 A
b0 E
b101 2
b101 J
b101 L
b0 F
b10000101000001010110011 (
b10000101000001010110011 7
b10000101000001010110011 D
b10000101000001010110011 T
b101 <
b101 N
b10100 '
b10100 ;
b10100 S
1!
#80
0!
#85
bx 4
bx ?
bx P
bx 5
bx @
bx Q
b0xxxx 2
b0xxxx J
b0xxxx L
bx F
bx :
bx A
bx E
b1100011 C
b0xxxx 1
b0xxxx K
b0xxxx M
b0xxxx 6
b0xxxx I
bx G
b10011100101000011001100011 (
b10011100101000011001100011 7
b10011100101000011001100011 D
b10011100101000011001100011 T
b11000 '
b11000 ;
b11000 S
b0 =
b0 O
1!
#90
0!
#95
b0 9
b0 B
b0 4
b0 ?
b0 P
b0 5
b0 @
b0 Q
b11 :
b11 A
b11 E
b100 1
b100 K
b100 M
b11 2
b11 J
b11 L
b100 6
b100 I
b10 F
b0 G
b110011 C
b10000011010001000110011 (
b10000011010001000110011 7
b10000011010001000110011 D
b10000011010001000110011 T
b0xxxx <
b0xxxx N
b11100 '
b11100 ;
b11100 S
1!
#100
0!
#105
bx 4
bx ?
bx P
bx 5
bx @
bx Q
bx G
bx :
bx A
bx E
b1100011 C
b0xxxx 1
b0xxxx K
b0xxxx M
b0xxxx 2
b0xxxx J
b0xxxx L
b0xxxx 6
b0xxxx I
bx F
b100000010001100011 (
b100000010001100011 7
b100000010001100011 D
b100000010001100011 T
b100000 '
b100000 ;
b100000 S
b100 <
b100 N
1!
#110
0!
#115
b10011 C
b1010010011 (
b1010010011 7
b1010010011 D
b1010010011 T
b0xxxx <
b0xxxx N
b100100 '
b100100 ;
b100100 S
1!
#120
0!
#125
b0 9
b0 B
b0 4
b0 ?
b0 P
b0 5
b0 @
b0 Q
b11 :
b11 A
b11 E
b10 1
b10 K
b10 M
b111 2
b111 J
b111 L
b100 6
b100 I
b10 F
b0 G
b110011 C
b1000111010001000110011 (
b1000111010001000110011 7
b1000111010001000110011 D
b1000111010001000110011 T
b101000 '
b101000 ;
b101000 S
1!
#130
0!
#135
b0 :
b0 A
b0 E
b101 1
b101 K
b101 M
b100 2
b100 J
b100 L
b111 6
b111 I
b0 F
b10100100000001110110011 (
b10100100000001110110011 7
b10100100000001110110011 D
b10100100000001110110011 T
b100 <
b100 N
b101100 '
b101100 ;
b101100 S
1!
#140
0!
#145
b1 :
b1 A
b1 E
b10 1
b10 K
b10 M
b111 2
b111 J
b111 L
b100000 G
b1000000001000111000001110110011 (
b1000000001000111000001110110011 7
b1000000001000111000001110110011 D
b1000000001000111000001110110011 T
b110000 '
b110000 ;
b110000 S
b111 <
b111 N
1!
#150
0!
#155
bx 4
bx ?
bx P
bx 5
bx @
bx Q
bx :
bx A
bx E
b100011 C
b0xxxx 1
b0xxxx K
b0xxxx M
b0xxxx 2
b0xxxx J
b0xxxx L
b0xxxx 6
b0xxxx I
bx F
bx G
b100011100011010001000100011 (
b100011100011010001000100011 7
b100011100011010001000100011 D
b100011100011010001000100011 T
b110100 '
b110100 ;
b110100 S
1!
#160
0!
#165
b11 C
b101000000000010000100000011 (
b101000000000010000100000011 7
b101000000000010000100000011 D
b101000000000010000100000011 T
b111000 '
b111000 ;
b111000 S
b0xxxx <
b0xxxx N
1!
#170
0!
#175
b1101111 C
b100000000000000001101111 (
b100000000000000001101111 7
b100000000000000001101111 D
b100000000000000001101111 T
b111100 '
b111100 ;
b111100 S
1!
#180
0!
#185
b10011 C
b100000000000100010011 (
b100000000000100010011 7
b100000000000100010011 D
b100000000000100010011 T
b1000000 '
b1000000 ;
b1000000 S
1!
#190
0!
#195
b100011 C
b100001000000010101000100011 (
b100001000000010101000100011 7
b100001000000010101000100011 D
b100001000000010101000100011 T
b1000100 '
b1000100 ;
b1000100 S
1!
#200
0!
#205
bx C
bx (
bx 7
bx D
bx T
b1001000 '
b1001000 ;
b1001000 S
1!
#210
0!
#215
b1001100 '
b1001100 ;
b1001100 S
1!
#220
0!
#225
b1010000 '
b1010000 ;
b1010000 S
1!
#230
0!
#235
b1010100 '
b1010100 ;
b1010100 S
1!
#240
0!
#245
b1011000 '
b1011000 ;
b1011000 S
1!
#250
0!
#255
b1011100 '
b1011100 ;
b1011100 S
1!
#260
0!
#265
b1100000 '
b1100000 ;
b1100000 S
1!
#270
0!
#275
b1100100 '
b1100100 ;
b1100100 S
1!
#280
0!
#285
b1101000 '
b1101000 ;
b1101000 S
1!
#290
0!
#295
b1101100 '
b1101100 ;
b1101100 S
1!
#300
0!
#305
b1110000 '
b1110000 ;
b1110000 S
1!
#310
0!
#315
b1110100 '
b1110100 ;
b1110100 S
1!
#320
0!
#325
b1111000 '
b1111000 ;
b1111000 S
1!
#330
0!
#335
b1111100 '
b1111100 ;
b1111100 S
1!
#340
0!
#345
b10000000 '
b10000000 ;
b10000000 S
1!
#350
0!
#355
b10000100 '
b10000100 ;
b10000100 S
1!
#360
0!
#365
b10001000 '
b10001000 ;
b10001000 S
1!
#370
0!
#375
b10001100 '
b10001100 ;
b10001100 S
1!
#380
0!
#385
b10010000 '
b10010000 ;
b10010000 S
1!
#390
0!
#395
b10010100 '
b10010100 ;
b10010100 S
1!
#400
0!
#405
b10011000 '
b10011000 ;
b10011000 S
1!
#410
0!
#415
b10011100 '
b10011100 ;
b10011100 S
1!
#420
0!
#425
b10100000 '
b10100000 ;
b10100000 S
1!
#430
0!
#435
b10100100 '
b10100100 ;
b10100100 S
1!
#440
0!
#445
b10101000 '
b10101000 ;
b10101000 S
1!
#450
0!
#455
b10101100 '
b10101100 ;
b10101100 S
1!
#460
0!
#465
b10110000 '
b10110000 ;
b10110000 S
1!
#470
0!
#475
b10110100 '
b10110100 ;
b10110100 S
1!
#480
0!
#485
b10111000 '
b10111000 ;
b10111000 S
1!
#490
0!
#495
b10111100 '
b10111100 ;
b10111100 S
1!
#500
0!
#505
b11000000 '
b11000000 ;
b11000000 S
1!
#510
0!
#515
b11000100 '
b11000100 ;
b11000100 S
1!
#520
0!
#525
b11001000 '
b11001000 ;
b11001000 S
1!
#530
0!
#535
b11001100 '
b11001100 ;
b11001100 S
1!
#540
0!
#545
b11010000 '
b11010000 ;
b11010000 S
1!
#550
0!
#555
b11010100 '
b11010100 ;
b11010100 S
1!
#560
0!
#565
b11011000 '
b11011000 ;
b11011000 S
1!
#570
0!
#575
b11011100 '
b11011100 ;
b11011100 S
1!
#580
0!
#585
b11100000 '
b11100000 ;
b11100000 S
1!
#590
0!
#595
b11100100 '
b11100100 ;
b11100100 S
1!
#600
0!
#605
b11101000 '
b11101000 ;
b11101000 S
1!
#610
0!
#615
b11101100 '
b11101100 ;
b11101100 S
1!
#620
0!
#625
b11110000 '
b11110000 ;
b11110000 S
1!
#630
0!
#635
b11110100 '
b11110100 ;
b11110100 S
1!
#640
0!
#645
b11111000 '
b11111000 ;
b11111000 S
1!
#650
0!
#655
b11111100 '
b11111100 ;
b11111100 S
1!
#660
0!
#665
b100000000 '
b100000000 ;
b100000000 S
1!
#670
0!
#675
b100000100 '
b100000100 ;
b100000100 S
1!
#680
0!
#685
b100001000 '
b100001000 ;
b100001000 S
1!
#690
0!
#695
b100001100 '
b100001100 ;
b100001100 S
1!
#700
0!
#705
b100010000 '
b100010000 ;
b100010000 S
1!
#710
0!
#715
b100010100 '
b100010100 ;
b100010100 S
1!
#720
0!
#725
b100011000 '
b100011000 ;
b100011000 S
1!
#730
0!
#735
b100011100 '
b100011100 ;
b100011100 S
1!
#740
0!
#745
b100100000 '
b100100000 ;
b100100000 S
1!
#750
0!
#755
b100100100 '
b100100100 ;
b100100100 S
1!
#760
0!
#765
b100101000 '
b100101000 ;
b100101000 S
1!
#770
0!
#775
b100101100 '
b100101100 ;
b100101100 S
1!
#780
0!
#785
b100110000 '
b100110000 ;
b100110000 S
1!
#790
0!
#795
b100110100 '
b100110100 ;
b100110100 S
1!
#800
0!
#805
b100111000 '
b100111000 ;
b100111000 S
1!
#810
0!
#815
b100111100 '
b100111100 ;
b100111100 S
1!
#820
0!
#825
b101000000 '
b101000000 ;
b101000000 S
1!
#830
0!
#835
b101000100 '
b101000100 ;
b101000100 S
1!
#840
0!
#845
b101001000 '
b101001000 ;
b101001000 S
1!
#850
0!
#855
b101001100 '
b101001100 ;
b101001100 S
1!
#860
0!
#865
b101010000 '
b101010000 ;
b101010000 S
1!
#870
0!
#875
b101010100 '
b101010100 ;
b101010100 S
1!
#880
0!
#885
b101011000 '
b101011000 ;
b101011000 S
1!
#890
0!
#895
b101011100 '
b101011100 ;
b101011100 S
1!
#900
0!
#905
b101100000 '
b101100000 ;
b101100000 S
1!
#910
0!
#915
b101100100 '
b101100100 ;
b101100100 S
1!
#920
0!
#925
b101101000 '
b101101000 ;
b101101000 S
1!
#930
0!
#935
b101101100 '
b101101100 ;
b101101100 S
1!
#940
0!
#945
b101110000 '
b101110000 ;
b101110000 S
1!
#950
0!
#955
b101110100 '
b101110100 ;
b101110100 S
1!
#960
0!
#965
b101111000 '
b101111000 ;
b101111000 S
1!
#970
0!
#975
b101111100 '
b101111100 ;
b101111100 S
1!
#980
0!
#985
b110000000 '
b110000000 ;
b110000000 S
1!
#990
0!
#995
b110000100 '
b110000100 ;
b110000100 S
1!
#1000
0!
#1005
b110001000 '
b110001000 ;
b110001000 S
1!
#1010
0!
#1015
b110001100 '
b110001100 ;
b110001100 S
1!
#1020
0!
#1025
b110010000 '
b110010000 ;
b110010000 S
1!
