src/dmem_iverilog.v
`define DRAM_depth 4096

module DMEM(
    input           clk, write_request,
    input   [31:0]  access_address, write_data,
    output  [31:0]  read_data
);

reg [31:0] RAM[0:`DRAM_depth-1];

assign read_data = RAM[access_address[31:2]];

always @ (posedge clk) begin
    if (write_request) begin
        RAM[access_address[31:2]] <= write_data;

        if (access_address == 32'h0000FFFC) begin
            $display("writedata: %d", write_data);
        end
    end
end

/* データメモリの初期化(シミュレーション用) */
integer i;
initial begin
    for (i = 0; i < `DRAM_depth; i = i + 1) begin
        RAM[i] = 32'b0;
    end
end

endmodule

src/imem_iverilog.v
`define MEMDATA "memory.data"

module IMEM(
    input   [31:0]  addr,
    output  [31:0]  instr
);

reg [31:0]  ROM[63:0];

initial begin
    $readmemh(`MEMDATA, ROM, 0, 63);
end

assign  instr = ROM[addr[31:2]];    // pc <= pc + 32'h4;に対応

endmodule

src/alu.v
module ALU(
    input       [3:0]   alu_op,
    input       [31:0]  src1,
    input       [31:0]  src2,
    output reg  [31:0]  aluout
);

always @* begin
    case (alu_op)
        4'b0000,
        4'b1010:
        begin
            aluout <= src1 + src2;  // add, addi
        end
        4'b0001: aluout = src1 - src2;  // sub
        4'b0010: aluout = src1 & src2;  // and
        4'b0011: aluout = src1 | src2;  // or
        4'b0100: aluout = src1 ^ src2;  // xor
        4'b1100: aluout = (src1 == src2) ? 32'b1 : 32'b0; // beq
        4'b1101: aluout = (src1 != src2) ? 32'b1 : 32'b0; // bne
        4'b1110: aluout = ($signed(src1) < $signed(src2)) ? 32'b1 : 32'b0; // blt, slt
        4'b1111: aluout = ($signed(src1) >= $signed(src2)) ? 32'b1 : 32'b0; // bge
    endcase
end

endmodule

src/regfile.v
module REGFILE(
    input clk,
    input write_request,
    input   [4:0] write_address,
    input   [4:0] read_address1,
    input   [4:0] read_address2,
    input  [31:0] write_data,
    output  [31:0] read_data1,
    output  [31:0] read_data2
);

reg [31:0] register_file [31:0];

always @ (posedge clk) begin
    if (write_request) register_file[write_address] <= write_data;
end

/* レジスタの初期化(シミュレーション用) */
integer i;
initial begin
    for (i = 0; i < 32; i = i + 1) begin
        register_file[i] = 32'b0;
    end
end

assign read_data1 = (read_address1 != 0) ? register_file[read_address1] : 0;
assign read_data2 = (read_address2 != 0) ? register_file[read_address2] : 0;

endmodule

src/decoder.v
module DECODER(
    input       [31:0]  instr,
    output reg  [3:0]   alu_op,
    output reg  [31:0]  immext,
    output reg  [4:0]   rd, rs1, rs2,
    output reg          reg_write_request,
    output reg          mem_write_request,
    output reg          mem_read_request,
    output reg          imm_enable,
    output reg  [2:0]   branch_type,
    output reg          is_branch,
    output reg          is_jal,
    output reg          is_jalr
);

    wire [6:0] opcode = instr[6:0];
    reg [6:0] funct7;
    reg [2:0] funct3;

    // 初期化（デフォルト値設定）
    always @* begin
        reg_write_request = 1'b0;
        mem_write_request = 1'b0;
        mem_read_request  = 1'b0;
        imm_enable        = 1'b0;
        funct7            = 7'bx;
        funct3            = 3'bx;
        rd                = 5'bx;
        rs1               = 5'bx;
        rs2               = 5'bx;
        immext            = 32'bx;
        is_branch         = 1'b0;
        branch_type      = 3'b0;
        is_jal            = 1'b0;
        is_jalr           = 1'b0;

        case (opcode)
            /* R-type */
            7'b0110011: begin
                funct7          = instr[31:25];
                funct3          = instr[14:12];
                immext          = 32'bx;
                rd              = instr[11:7];
                rs1             = instr[19:15];
                rs2             = instr[24:20];
                reg_write_request = 1'b1;
                imm_enable      = 1'b0;
                is_branch         = 1'b0;
                branch_type      = 3'bx;
            end

            /* I-type */
            7'b0010011, // addi, ori
            7'b0000011: // lw
            begin
                funct7          = 7'bx;
                funct3          = instr[14:12];
                immext          = {{20{instr[31]}}, instr[31:20]};
                rd              = instr[11:7];
                rs1             = instr[19:15];
                rs2             = 5'bx;
                reg_write_request = 1'b1;
                imm_enable      = 1'b1;
                is_branch         = 1'b0;
                branch_type      = 3'bx;
            end

            /* S-type */
            7'b0100011: // sw
            begin
                funct7          = instr[31:25];
                funct3          = instr[14:12];
                immext          = {{20{instr[31]}}, instr[31:25], instr[11:7]};
                rd              = 5'bx;
                rs1             = instr[19:15];
                rs2             = instr[24:20];
                reg_write_request = 1'b0;
                imm_enable          = 1'b1;
                is_branch         = 1'b0;
                branch_type      = 3'bx;
            end

            /* B-type */
            7'b1100011: begin // branch instructions
                funct3          = instr[14:12];
                immext          = {{20{instr[31]}}, instr[7], instr[30:25], instr[11:8], 1'b0}; // B型即値
                rd              = 5'bx;
                rs1             = instr[19:15];
                rs2             = instr[24:20];
                reg_write_request = 1'b0;
                imm_enable      = 1'b0;
                is_branch         = 1'b1;
            end

            /* U-type */
            7'b0110111,  // LUI
            7'b0010111: begin  // AUIPC
                funct7          = 7'bx;
                funct3          = 3'bx;
                immext          = {instr[31:12], 12'b0};
                rd              = instr[11:7];
                rs1             = 5'b0;
                rs2             = 5'b0;
                reg_write_request = 1'b1;
                imm_enable         = 1'b1;
                is_branch         = 1'b0;
                branch_type      = 3'bx;
            end

            /* J-type */
            7'b1101111: begin // jal
                funct7           = 7'bx;
                funct3           = 3'bx;
                immext           = {{12{instr[31]}}, instr[19:12], instr[20], instr[30:21], 1'b0}; // J型即値
                rd               = instr[11:7];
                rs1              = 5'bx;
                rs2              = 5'bx;
                reg_write_request = 1'b1;
                imm_enable        = 1'b1;
                is_branch         = 1'b0;
                is_jal            = 1'b1;
                is_jalr           = 1'b0;
                branch_type       = 3'bx;
            end
            7'b1100111: begin // jalr
                funct7           = 7'bx;
                funct3           = instr[14:12];
                immext           = {{20{instr[31]}}, instr[31:20]};
                rd               = instr[11:7];
                rs1              = instr[19:15];
                rs2              = 5'bx;
                reg_write_request = 1'b1;
                imm_enable        = 1'b1;
                is_branch         = 1'b0;
                is_jal            = 1'b0;
                is_jalr           = 1'b1;
                branch_type       = 3'bx;
            end

            default: begin
                funct7          = 7'bx;
                funct3          = 3'bx;
                immext          = 32'bx;
                rd              = 5'bx;
                rs1             = 5'bx;
                rs2             = 5'bx;
                is_branch         = 1'b0;
                branch_type      = 3'bx;
            end
        endcase
    end

    // ALU operation decoding
    always @* begin
        case (funct3)
            3'b000: begin
                if (opcode == 7'b0110011) // R-type
                begin
                    case (funct7)
                        7'b0000000: alu_op = 4'b0000;  // add
                        7'b0100000: alu_op = 4'b0001;  // sub
                        default:    alu_op = 4'bx;
                    endcase
                end
                else if (opcode == 7'b0010011) // I-type (addi)
                begin
                    alu_op = 4'b0000;   // addi
                end
                else begin
                    alu_op = 4'bx;
                end
            end

            3'b001: alu_op = 4'b0010;  // sll
            3'b010: begin
                case (opcode)
                    7'b0000011: begin // lw
                        alu_op = 4'b0000; // addでアドレス計算
                        reg_write_request = 1;
                        mem_read_request  = 1;
                    end
                    7'b0100011: begin // sw
                        alu_op = 4'b0000;
                        mem_write_request = 1;
                    end
                    7'b0110011: begin // slt
                        alu_op = 4'b1110;
                        mem_write_request = 1'b0;
                        mem_read_request = 1'b0;
                    end
                    default: alu_op = 4'bx;
                endcase
            end

            3'b011: alu_op = 4'b0100;  // sltu
            3'b100: alu_op = 4'b0101;  // xor
            3'b101: begin
                case (funct7)
                    7'b0000000: alu_op = 4'b0110;  // srl
                    7'b0100000: alu_op = 4'b0111;  // sra
                    default:    alu_op = 4'bx;
                endcase
            end
            3'b110: alu_op = 4'b1000;  // ori
            3'b111: alu_op = 4'b1001;  // and
            default: alu_op = 4'bx;
        endcase
        if (opcode == 7'b1100011) begin
            case (funct3)
                3'b000: begin
                    alu_op = 4'b1100; // beq
                    branch_type = 3'b000;
                end
                3'b001: begin
                    alu_op = 4'b1101; // bne
                    branch_type = 3'b001;
                end
                3'b100: begin
                    alu_op = 4'b1110; // blt
                    branch_type = 3'b100;
                end
                3'b101: begin
                    alu_op = 4'b1111; // bge
                    branch_type = 3'b101;
                end
            endcase
        end else if (opcode == 7'b0110111) begin
            alu_op = 4'b1011;   // lui
        end else if (opcode == 7'b0010111) begin
            alu_op = 4'b0000;    // auipc
        end
    end

endmodule

src/haconiwa_core.v
module HACONIWA_CORE(
    input               clk,
    input               reset,
    output reg  [31:0]  pc,
    input       [31:0]  instr,
    output      [31:0]  core2mem_access_address,
    input       [31:0]  mem2core_read_data,
    output      [31:0]  core2mem_write_data,
    output              core2mem_write_request
);

/* === Pipeline Registers === */
reg         stall, flush;

reg [31:0]  IF_ID_pc, IF_ID_instr;

reg [3:0]   ID_EXE_alu_op;
reg [2:0]   ID_EXE_branch_type;
reg [31:0]  ID_EXE_pc, next_pc, ID_EXE_immext, ID_EXE_read_reg_data1, ID_EXE_read_reg_data2;
reg [4:0]   ID_EXE_rd, ID_EXE_rs1, ID_EXE_rs2;
reg         ID_EXE_reg_write_request, ID_EXE_mem_write_request, ID_EXE_mem_read_request, ID_EXE_imm_enable, ID_EXE_is_branch, ID_EXE_is_jal, ID_EXE_is_jalr;

reg [4:0]   EXE_MEM_rd;
reg [31:0]  EXE_MEM_pc, EXE_MEM_aluout, EXE_MEM_write_data;
reg         EXE_MEM_reg_write_request, EXE_MEM_mem_write_request, EXE_MEM_mem_read_request, EXE_MEM_is_jal, EXE_MEM_is_jalr;

reg         MEM_WB_reg_write_request;
reg [4:0]   MEM_WB_rd;
reg [31:0]  MEM_WB_reg_write_data;

/* === IF Stage === */
always @* begin
    if (flush) begin
        if (ID_EXE_is_jalr) begin
            next_pc = (ID_EXE_read_reg_data1 + ID_EXE_immext) & ~32'b1;
        end else if (ID_EXE_is_jal) begin
            next_pc = ID_EXE_pc + ID_EXE_immext;
        end else begin
            next_pc = ID_EXE_pc + ID_EXE_immext;
        end
    end else begin
        next_pc = pc + 4;
    end
end

always @ (posedge clk) begin
    if (reset) begin
        pc <= 32'h0;
    end else if (!stall) begin
        pc <= next_pc;
        IF_ID_pc <= pc;
        IF_ID_instr <= (flush) ? 32'h00000013 : instr;  // flushがexeされた場合に2つ後の命令をnop化
    end
end

/* === ID Stage === */
wire [3:0] alu_op;
wire [31:0] immext, read_reg_data1, read_reg_data2;
wire [4:0] rd, rs1, rs2;
wire [2:0] dec_branch_type;
wire dec_reg_write_request, dec_mem_write_request, dec_mem_read_request, dec_imm_enable, dec_is_branch, dec_is_jal, dec_is_jalr;

DECODER dec(
    .instr(IF_ID_instr),
    .alu_op(alu_op),
    .rd(rd),
    .rs1(rs1),
    .rs2(rs2),
    .immext(immext),
    .imm_enable(dec_imm_enable),
    .reg_write_request(dec_reg_write_request),
    .mem_write_request(dec_mem_write_request),
    .mem_read_request(dec_mem_read_request),
    .branch_type(dec_branch_type),
    .is_branch(dec_is_branch),
    .is_jal(dec_is_jal),
    .is_jalr(dec_is_jalr)
);

REGFILE regfile(
    .clk(clk),
    .read_address1(rs1),
    .read_address2(rs2),
    .read_data1(read_reg_data1),
    .read_data2(read_reg_data2),
    .write_request(MEM_WB_reg_write_request),
    .write_address(MEM_WB_rd),
    .write_data(MEM_WB_reg_write_data)
);

wire [31:0] id_fwd_src1, id_fwd_src2;
assign id_fwd_src1 = (MEM_WB_reg_write_request && MEM_WB_rd != 0 && MEM_WB_rd == rs1)
                        ? MEM_WB_reg_write_data : read_reg_data1;
assign id_fwd_src2 = (MEM_WB_reg_write_request && MEM_WB_rd != 0 && MEM_WB_rd == rs2)
                        ? MEM_WB_reg_write_data : read_reg_data2;

always @ (posedge clk) begin
    if (!stall && !flush) begin // flushがexeされた場合に既にとりこんだ1つ後の命令をnop化
        ID_EXE_pc                   <= IF_ID_pc;
        ID_EXE_alu_op               <= alu_op;
        ID_EXE_immext               <= immext;
        ID_EXE_read_reg_data1       <= id_fwd_src1;
        ID_EXE_read_reg_data2       <= id_fwd_src2;
        ID_EXE_rd                   <= rd;
        ID_EXE_rs1                  <= rs1;
        ID_EXE_rs2                  <= rs2;
        ID_EXE_reg_write_request    <= dec_reg_write_request;
        ID_EXE_mem_write_request    <= dec_mem_write_request;
        ID_EXE_mem_read_request     <= dec_mem_read_request;
        ID_EXE_imm_enable           <= dec_imm_enable;
        ID_EXE_branch_type          <= dec_branch_type;
        ID_EXE_is_branch            <= dec_is_branch;
        ID_EXE_is_jal               <= dec_is_jal;
        ID_EXE_is_jalr              <= dec_is_jalr;
    end else begin
        ID_EXE_pc                   <= 32'b0;
        ID_EXE_alu_op               <= 4'b0;
        ID_EXE_immext               <= 32'b0;
        ID_EXE_read_reg_data1       <= 32'b0;
        ID_EXE_read_reg_data2       <= 32'b0;
        ID_EXE_rd                   <= 5'b0;
        ID_EXE_rs1                  <= 5'b0;
        ID_EXE_rs2                  <= 5'b0;
        ID_EXE_reg_write_request    <= 1'b0;
        ID_EXE_mem_write_request    <= 1'b0;
        ID_EXE_mem_read_request     <= 1'b0;
        ID_EXE_imm_enable           <= 1'b0;
        ID_EXE_branch_type          <= 1'b0; 
        ID_EXE_is_branch            <= 1'b0;
        ID_EXE_is_jal               <= 1'b0;
        ID_EXE_is_jalr              <= 1'b0;
    end
end

// load-use hazard detection
wire load_use_hazard;
assign load_use_hazard = (ID_EXE_mem_read_request &&
                            ((ID_EXE_rd == rs1 && ID_EXE_rd != 0) ||
                            (ID_EXE_rd == rs2 && ID_EXE_rd != 0)));
always @* begin
    if (reset) begin
        stall = 1'b0;
    end else begin
        stall = load_use_hazard;
    end
end

/* === EXE Stage === */
wire [31:0] exe_fwd_src1, exe_fwd_src2;
assign exe_fwd_src1 = (EXE_MEM_reg_write_request && EXE_MEM_rd != 0 && EXE_MEM_rd == ID_EXE_rs1)
                    ? EXE_MEM_aluout
                    : (MEM_WB_reg_write_request && MEM_WB_rd != 0 && MEM_WB_rd == ID_EXE_rs1)
                        ? MEM_WB_reg_write_data
                        : ID_EXE_read_reg_data1;

assign exe_fwd_src2 = (EXE_MEM_reg_write_request && EXE_MEM_rd != 0 && EXE_MEM_rd == ID_EXE_rs2)
                    ? EXE_MEM_aluout
                    : (MEM_WB_reg_write_request && MEM_WB_rd != 0 && MEM_WB_rd == ID_EXE_rs2)
                        ? MEM_WB_reg_write_data
                        : ID_EXE_read_reg_data2;

wire [31:0] alu_src1, alu_src2, exe_aluout;
assign alu_src1 = exe_fwd_src1;
assign alu_src2 = ID_EXE_imm_enable ? ID_EXE_immext : exe_fwd_src2;

ALU alu(
    .alu_op(ID_EXE_alu_op),
    .src1(alu_src1),
    .src2(alu_src2),
    .aluout(exe_aluout)
);

wire branch_taken;
assign branch_taken = (ID_EXE_is_branch && (exe_aluout == 1'b1)) ? 1'b1 : 1'b0 ;
// assign branch_taken =   (ID_EXE_branch_type == 3'b000) ? (fwd_src1 == fwd_src2) :
//                         (ID_EXE_branch_type == 3'b001) ? (fwd_src1 != fwd_src2) :
//                         (ID_EXE_branch_type == 3'b100) ? (fwd_src1 < fwd_src2) :
//                         (ID_EXE_branch_type == 3'b101) ? (fwd_src1 >= fwd_src2) : 1'b0;

always @* begin
    flush = (ID_EXE_is_branch && branch_taken) || ID_EXE_is_jal || ID_EXE_is_jalr;
end

always @ (posedge clk) begin
    EXE_MEM_aluout <= exe_aluout;
    EXE_MEM_rd <= ID_EXE_rd;
    EXE_MEM_write_data <= exe_fwd_src2;
    EXE_MEM_reg_write_request <= ID_EXE_reg_write_request;
    EXE_MEM_mem_write_request <= ID_EXE_mem_write_request;
    EXE_MEM_mem_read_request <= ID_EXE_mem_read_request;
    EXE_MEM_pc <= ID_EXE_pc;
    EXE_MEM_is_jal <= ID_EXE_is_jal;
    EXE_MEM_is_jalr <= ID_EXE_is_jalr;
end

/* === MEM Stage === */
assign core2mem_write_request = EXE_MEM_mem_write_request;
assign core2mem_access_address = EXE_MEM_aluout;
assign core2mem_write_data = EXE_MEM_write_data;

always @ (posedge clk) begin
    MEM_WB_reg_write_request <= EXE_MEM_reg_write_request;
    MEM_WB_rd <= EXE_MEM_rd;
    MEM_WB_reg_write_data <=    (EXE_MEM_mem_read_request) ? mem2core_read_data :
                                (EXE_MEM_is_jal || EXE_MEM_is_jalr) ? EXE_MEM_pc + 32'h4 :
                                EXE_MEM_aluout;
end

endmodule

src/haconiwa_top.v
module HACONIWA_TOP(
    input   CLOCK_50_B5B, CPU_RESET_n
);

wire [31:0] pc, instr, core2mem_access_address, mem2core_read_data, core2mem_write_data;
wire core2mem_write_request;

HACONIWA_CORE hcore(
    .clk(CLOCK_50_B5B),
    .reset(!CPU_RESET_n),
    .pc(pc),
    .instr(instr),
    .core2mem_access_address(core2mem_access_address),
    .mem2core_read_data(mem2core_read_data),
    .core2mem_write_data(core2mem_write_data),
    .core2mem_write_request(core2mem_write_request)
);

IMEM imem(
    .addr(pc),
    .instr(instr)
);

DMEM dmem(
    .clk(CLOCK_50_B5B),
    .access_address(core2mem_access_address),
    .read_data(mem2core_read_data),
    .write_data(core2mem_write_data),
    .write_request(core2mem_write_request)
);

endmodule

module SIMTOP();
    reg clk, reset;

    HACONIWA_TOP htop(
        .CLOCK_50_B5B(clk),
        .CPU_RESET_n(!reset)
    );

    initial begin
        clk = 0;
        forever #5 clk = ~clk;
    end

    initial begin
        #10 reset = 1;
        #20 reset = 0;
        $dumpfile("sim_top_haconiwa.vcd");
        $dumpvars(0, htop);

        #2000 $finish;
    end
endmodule

test/sim_top_haconiwa.vcd
$date
	Sun May  4 12:56:41 2025
$end
$version
	Icarus Verilog
$end
$timescale
	1s
$end
$scope module SIMTOP $end
$scope module htop $end
$var wire 1 ! CLOCK_50_B5B $end
$var wire 1 " CPU_RESET_n $end
$var wire 32 # pc [31:0] $end
$var wire 32 $ mem2core_read_data [31:0] $end
$var wire 32 % instr [31:0] $end
$var wire 1 & core2mem_write_request $end
$var wire 32 ' core2mem_write_data [31:0] $end
$var wire 32 ( core2mem_access_address [31:0] $end
$scope module dmem $end
$var wire 1 ! clk $end
$var wire 32 ) read_data [31:0] $end
$var wire 1 & write_request $end
$var wire 32 * write_data [31:0] $end
$var wire 32 + access_address [31:0] $end
$var integer 32 , i [31:0] $end
$upscope $end
$scope module hcore $end
$var wire 32 - alu_src1 [31:0] $end
$var wire 1 ! clk $end
$var wire 32 . core2mem_access_address [31:0] $end
$var wire 32 / core2mem_write_data [31:0] $end
$var wire 1 & core2mem_write_request $end
$var wire 1 0 load_use_hazard $end
$var wire 32 1 mem2core_read_data [31:0] $end
$var wire 1 2 reset $end
$var wire 5 3 rs2 [4:0] $end
$var wire 5 4 rs1 [4:0] $end
$var wire 32 5 read_reg_data2 [31:0] $end
$var wire 32 6 read_reg_data1 [31:0] $end
$var wire 5 7 rd [4:0] $end
$var wire 32 8 instr [31:0] $end
$var wire 32 9 immext [31:0] $end
$var wire 32 : id_fwd_src2 [31:0] $end
$var wire 32 ; id_fwd_src1 [31:0] $end
$var wire 32 < exe_fwd_src2 [31:0] $end
$var wire 32 = exe_fwd_src1 [31:0] $end
$var wire 32 > exe_aluout [31:0] $end
$var wire 1 ? dec_reg_write_request $end
$var wire 1 @ dec_mem_write_request $end
$var wire 1 A dec_mem_read_request $end
$var wire 1 B dec_is_jalr $end
$var wire 1 C dec_is_jal $end
$var wire 1 D dec_is_branch $end
$var wire 1 E dec_imm_enable $end
$var wire 3 F dec_branch_type [2:0] $end
$var wire 1 G branch_taken $end
$var wire 32 H alu_src2 [31:0] $end
$var wire 4 I alu_op [3:0] $end
$var reg 32 J EXE_MEM_aluout [31:0] $end
$var reg 1 K EXE_MEM_is_jal $end
$var reg 1 L EXE_MEM_is_jalr $end
$var reg 1 M EXE_MEM_mem_read_request $end
$var reg 1 N EXE_MEM_mem_write_request $end
$var reg 32 O EXE_MEM_pc [31:0] $end
$var reg 5 P EXE_MEM_rd [4:0] $end
$var reg 1 Q EXE_MEM_reg_write_request $end
$var reg 32 R EXE_MEM_write_data [31:0] $end
$var reg 4 S ID_EXE_alu_op [3:0] $end
$var reg 3 T ID_EXE_branch_type [2:0] $end
$var reg 1 U ID_EXE_imm_enable $end
$var reg 32 V ID_EXE_immext [31:0] $end
$var reg 1 W ID_EXE_is_branch $end
$var reg 1 X ID_EXE_is_jal $end
$var reg 1 Y ID_EXE_is_jalr $end
$var reg 1 Z ID_EXE_mem_read_request $end
$var reg 1 [ ID_EXE_mem_write_request $end
$var reg 32 \ ID_EXE_pc [31:0] $end
$var reg 5 ] ID_EXE_rd [4:0] $end
$var reg 32 ^ ID_EXE_read_reg_data1 [31:0] $end
$var reg 32 _ ID_EXE_read_reg_data2 [31:0] $end
$var reg 1 ` ID_EXE_reg_write_request $end
$var reg 5 a ID_EXE_rs1 [4:0] $end
$var reg 5 b ID_EXE_rs2 [4:0] $end
$var reg 32 c IF_ID_instr [31:0] $end
$var reg 32 d IF_ID_pc [31:0] $end
$var reg 5 e MEM_WB_rd [4:0] $end
$var reg 32 f MEM_WB_reg_write_data [31:0] $end
$var reg 1 g MEM_WB_reg_write_request $end
$var reg 1 h flush $end
$var reg 32 i next_pc [31:0] $end
$var reg 32 j pc [31:0] $end
$var reg 1 k stall $end
$scope module alu $end
$var wire 4 l alu_op [3:0] $end
$var wire 32 m src1 [31:0] $end
$var wire 32 n src2 [31:0] $end
$var reg 32 o aluout [31:0] $end
$upscope $end
$scope module dec $end
$var wire 32 p instr [31:0] $end
$var wire 7 q opcode [6:0] $end
$var reg 4 r alu_op [3:0] $end
$var reg 3 s branch_type [2:0] $end
$var reg 3 t funct3 [2:0] $end
$var reg 7 u funct7 [6:0] $end
$var reg 1 E imm_enable $end
$var reg 32 v immext [31:0] $end
$var reg 1 D is_branch $end
$var reg 1 C is_jal $end
$var reg 1 B is_jalr $end
$var reg 1 A mem_read_request $end
$var reg 1 @ mem_write_request $end
$var reg 5 w rd [4:0] $end
$var reg 1 ? reg_write_request $end
$var reg 5 x rs1 [4:0] $end
$var reg 5 y rs2 [4:0] $end
$upscope $end
$scope module regfile $end
$var wire 1 ! clk $end
$var wire 5 z read_address1 [4:0] $end
$var wire 5 { read_address2 [4:0] $end
$var wire 5 | write_address [4:0] $end
$var wire 32 } write_data [31:0] $end
$var wire 1 g write_request $end
$var wire 32 ~ read_data2 [31:0] $end
$var wire 32 !" read_data1 [31:0] $end
$var integer 32 "" i [31:0] $end
$upscope $end
$upscope $end
$scope module imem $end
$var wire 32 #" addr [31:0] $end
$var wire 32 $" instr [31:0] $end
$upscope $end
$upscope $end
$upscope $end
$enddefinitions $end
$comment Show the parameter values. $end
$dumpall
$end
#30
$dumpvars
b10011 $"
b0 #"
b100000 ""
bx !"
bx ~
bx }
b0 |
bx {
bx z
bx y
bx x
bx w
bx v
bx u
bx t
bx s
bx r
bx q
bx p
bx o
bx n
bx m
b0 l
0k
b0 j
b100 i
0h
0g
bx f
b0 e
bx d
bx c
b0 b
b0 a
0`
b0 _
b0 ^
b0 ]
b0 \
0[
0Z
0Y
0X
0W
b0 V
0U
b0 T
b0 S
bx R
xQ
bx P
bx O
xN
xM
xL
xK
bx J
bx I
bx H
0G
bx F
xE
xD
xC
xB
xA
x@
x?
bx >
bx =
bx <
bx ;
bx :
bx 9
b10011 8
bx 7
bx 6
bx 5
bx 4
bx 3
02
bx 1
00
bx /
bx .
bx -
b100000 ,
bx +
bx *
bx )
bx (
bx '
x&
b10011 %
bx $
b0 #
1"
0!
$end
#35
xk
x0
b0 6
b0 !"
xG
b0 I
b0 r
xh
b0 4
b0 x
b0 z
b0 7
b0 w
b0 9
b0 v
b0 t
0B
0C
bx F
bx s
0D
1E
0A
0@
1?
b10011 q
b1000 i
bx e
bx |
xg
0L
0K
b0 O
0M
0&
0N
0Q
b0 P
xY
xX
xW
bx T
xU
xZ
x[
x`
bx b
bx a
bx ]
bx _
bx ^
bx V
bx S
bx l
bx \
b10011 c
b10011 p
b0 d
b100 #
b100 j
b100 #"
1!
#40
0!
#45
0G
0k
b0 ;
0h
00
0Y
0X
0W
b0 T
0U
0Z
0[
0`
b0 b
b0 a
b0 ]
b0 _
b0 ^
b0 V
b0 S
b0 l
b0 \
xL
xK
bx O
xM
x&
xN
xQ
bx P
b0 e
b0 |
0g
1!
#50
0!
#55
bx >
bx o
bx ;
bx -
bx m
bx =
b0 H
b0 n
b1100 i
bx e
bx |
xg
0L
0K
b0 O
0M
0&
0N
0Q
b0 P
bx T
1U
1`
bx b
bx _
b100 d
b1000 #
b1000 j
b1000 #"
1!
#60
0!
#65
b0 ;
b10000 i
b1000 d
b1100 #
b1100 j
b1100 #"
bx ^
b100 \
1Q
b0 e
b0 |
0g
1!
#70
0!
#75
b0 >
b0 o
b0 -
b0 m
b0 =
b10100 i
1g
b100 O
b0 ^
b1000 \
b1100 d
b10000 #
b10000 j
b10000 #"
1!
#80
0!
#85
b11000 i
b0 $
b0 )
b0 1
b10000 d
b10100 #
b10100 j
b10100 #"
b1100 \
b1000 O
b0 (
b0 +
b0 .
b0 J
1!
#90
0!
#95
b11100 i
b10000000000000000011101111 %
b10000000000000000011101111 8
b10000000000000000011101111 $"
b0 f
b0 }
b1100 O
b10000 \
b10100 d
b11000 #
b11000 j
b11000 #"
1!
#100
0!
#105
bx ;
bx 6
bx !"
bx I
bx r
1C
bx F
bx s
b100000 9
b100000 v
bx 4
bx x
bx z
b1 7
b1 w
bx t
1E
1?
b1101111 q
b11100000000010000010011 %
b11100000000010000010011 8
b11100000000010000010011 $"
b100000 i
b10000000000000000011101111 c
b10000000000000000011101111 p
b11000 d
b11100 #
b11100 j
b11100 #"
b10100 \
b10000 O
1!
#110
0!
#115
b0 ;
b0 6
b0 !"
bx -
bx m
bx =
b0 I
b0 r
1h
b100000 H
b100000 n
b0 4
b0 x
b0 z
b0 t
0C
bx F
bx s
b111 9
b111 v
b1000 7
b1000 w
1E
1?
b10011 q
b111000 i
b100000000000010000010011 %
b100000000000010000010011 8
b100000000000010000010011 $"
b10100 O
1X
bx a
b1 ]
bx ^
b100000 V
bx S
bx l
b11000 \
b11100000000010000010011 c
b11100000000010000010011 p
b11100 d
b100000 #
b100000 j
b100000 #"
1!
#120
0!
#125
b0 >
b0 o
b0 <
b0 -
b0 m
b0 =
bx F
bx s
b0 9
b0 v
b0 4
b0 x
b0 z
b0 7
b0 w
b0 t
1E
1?
b10101010101010100000000110110111 %
b10101010101010100000000110110111 8
b10101010101010100000000110110111 $"
0h
b0 H
b0 n
b111100 i
b10011 c
b10011 p
b100000 d
b111000 #
b111000 j
b111000 #"
0X
b0 T
0U
0`
b0 b
b0 a
b0 ]
b0 _
b0 ^
b0 V
b0 S
b0 l
b0 \
1K
b11000 O
b1 P
1!
#130
0!
#135
b0 :
b0 5
b0 ~
bx <
b1011 I
b1011 r
b0 3
b0 y
b0 {
bx F
bx s
b10101010101010100000000000000000 9
b10101010101010100000000000000000 v
b0 4
b0 x
b0 z
b11 7
b11 w
bx t
1E
1?
b110111 q
b1000000 i
b10010001100011000000110010011 %
b10010001100011000000110010011 8
b10010001100011000000110010011 $"
b11100 f
b11100 }
b1 e
b1 |
0K
b0 O
0Q
b0 '
b0 *
b0 /
b0 R
b0 P
bx T
1U
1`
bx b
bx _
b100000 \
b10101010101010100000000110110111 c
b10101010101010100000000110110111 p
b111000 d
b111100 #
b111100 j
b111100 #"
1!
#140
0!
#145
bx :
bx 5
bx ~
b0 I
b0 r
b10101010101010100000000000000000 >
b10101010101010100000000000000000 o
b0 <
b0 t
bx F
bx s
b100100011 9
b100100011 v
bx 3
bx y
bx {
b11 4
b11 x
b11 z
b11 7
b11 w
1E
1?
b10011 q
b1001100110111 %
b1001100110111 8
b1001100110111 $"
b10101010101010100000000000000000 H
b10101010101010100000000000000000 n
b1000100 i
b10010001100011000000110010011 c
b10010001100011000000110010011 p
b111100 d
b1000000 #
b1000000 j
b1000000 #"
b0 b
b11 ]
b0 _
b10101010101010100000000000000000 V
b1011 S
b1011 l
b111000 \
b100000 O
1Q
bx '
bx *
bx /
bx R
b0 f
b0 }
b0 e
b0 |
0g
1!
#150
0!
#155
b10101010101010100000000100100011 >
b10101010101010100000000100100011 o
b10101010101010100000000000000000 -
b10101010101010100000000000000000 m
b10101010101010100000000000000000 =
b0 :
b0 5
b0 ~
bx <
b1011 I
b1011 r
bx $
bx )
bx 1
b100100011 H
b100100011 n
b0 3
b0 y
b0 {
bx F
bx s
b1000000000000 9
b1000000000000 v
b0 4
b0 x
b0 z
b110 7
b110 w
bx t
1E
1?
b110111 q
b1001000 i
b1100110010000000100011 %
b1100110010000000100011 8
b1100110010000000100011 $"
1g
b111000 O
b0 '
b0 *
b0 /
b0 R
b11 P
b10101010101010100000000000000000 (
b10101010101010100000000000000000 +
b10101010101010100000000000000000 .
b10101010101010100000000000000000 J
bx b
b11 a
bx _
b100100011 V
b0 S
b0 l
b111100 \
b1001100110111 c
b1001100110111 p
b1000000 d
b1000100 #
b1000100 j
b1000100 #"
1!
#160
0!
#165
b10101010101010100000000000000000 :
1@
b0 I
b0 r
b0 <
b10 t
b0 u
bx F
bx s
b0 9
b0 v
b11 3
b11 y
b11 {
b110 4
b110 x
b110 z
bx 7
bx w
1E
0?
b100011 q
b1110010111 %
b1110010111 8
b1110010111 $"
b1000000000000 H
b1000000000000 n
b1000000000000 >
b1000000000000 o
b1001100 i
b0 -
b0 m
b0 =
b1100110010000000100011 c
b1100110010000000100011 p
b1000100 d
b1001000 #
b1001000 j
b1001000 #"
b0 b
b0 a
b110 ]
b0 _
b1000000000000 V
b1011 S
b1011 l
b1000000 \
b111100 O
bx '
bx *
bx /
bx R
b10101010101010100000000100100011 (
b10101010101010100000000100100011 +
b10101010101010100000000100100011 .
b10101010101010100000000100100011 J
b10101010101010100000000000000000 f
b10101010101010100000000000000000 }
b11 e
b11 |
1!
#170
0!
