src/dmem_iverilog.v
`define DRAM_depth 4096

module DMEM(
    input           clk, write_request,
    input   [31:0]  access_address, write_data,
    output  [31:0]  read_data
);

reg [31:0] RAM[0:`DRAM_depth-1];

assign read_data = RAM[access_address[31:2]];

always @ (posedge clk) begin
    if (write_request) begin
        RAM[access_address[31:2]] <= write_data;

        if (access_address == 32'h0000FFFC) begin
            $display("writedata: %d", write_data);
        end
    end
end

/* データメモリの初期化(シミュレーション用) */
integer i;
initial begin
    for (i = 0; i < `DRAM_depth; i = i + 1) begin
        RAM[i] = 32'b0;
    end
end

endmodule

src/imem_iverilog.v
`define MEMDATA "memory.data"

module IMEM(
    input   [31:0]  addr,
    output  [31:0]  instr
);

reg [31:0]  ROM[63:0];

initial begin
    $readmemh(`MEMDATA, ROM, 0, 63);
end

assign  instr = ROM[addr[31:2]];    // pc <= pc + 32'h4;に対応

endmodule

src/alu.v
module ALU(
    input       [3:0]   alu_op,
    input       [31:0]  src1,
    input       [31:0]  src2,
    output reg  [31:0]  aluout
);

always @* begin
    case (alu_op)
        4'b0000,
        4'b1010:
        begin
            aluout <= src1 + src2;  // add, addi
        end
        4'b0001: aluout = src1 - src2;  // sub
        4'b0010: aluout = src1 & src2;  // and
        4'b1000: aluout = src1 | src2;  // or
        4'b0100: aluout = src1 ^ src2;  // xor
        4'b1100: aluout = (src1 == src2) ? 32'b1 : 32'b0; // beq
        4'b1101: aluout = (src1 != src2) ? 32'b1 : 32'b0; // bne
        4'b1110: aluout = ($signed(src1) < $signed(src2)) ? 32'b1 : 32'b0; // blt, slt
        4'b1111: aluout = ($signed(src1) >= $signed(src2)) ? 32'b1 : 32'b0; // bge
        4'b1011: aluout = src2; // lui
        // 4'b1001: aluout = src2; // lui
    endcase
end

endmodule

src/regfile.v
module REGFILE(
    input clk,
    input write_request,
    input   [4:0] write_address,
    input   [4:0] read_address1,
    input   [4:0] read_address2,
    input  [31:0] write_data,
    output  [31:0] read_data1,
    output  [31:0] read_data2
);

reg [31:0] register_file [31:0];

always @ (posedge clk) begin
    if (write_request) register_file[write_address] <= write_data;
end

/* レジスタの初期化(シミュレーション用) */
integer i;
initial begin
    for (i = 0; i < 32; i = i + 1) begin
        register_file[i] = 32'b0;
    end
end

assign read_data1 = (read_address1 != 0) ? register_file[read_address1] : 0;
assign read_data2 = (read_address2 != 0) ? register_file[read_address2] : 0;

endmodule

src/decoder.v
module DECODER(
    input       [31:0]  instr,
    output reg  [3:0]   alu_op,
    output reg  [31:0]  immext,
    output reg  [4:0]   rd, rs1, rs2,
    output reg          reg_write_request,
    output reg          mem_write_request,
    output reg          mem_read_request,
    output reg          imm_enable,
    output reg          is_branch,
    output reg  [2:0]   branch_type
);

    wire [6:0] opcode = instr[6:0];
    reg [6:0] funct7;
    reg [2:0] funct3;

    // 初期化（デフォルト値設定）
    always @* begin
        reg_write_request = 1'b0;
        mem_write_request = 1'b0;
        mem_read_request  = 1'b0;
        imm_enable        = 1'b0;
        funct7            = 7'bx;
        funct3            = 3'bx;
        rd                = 5'bx;
        rs1               = 5'bx;
        rs2               = 5'bx;
        immext            = 32'bx;
        is_branch         = 1'b0;
        branch_type      = 3'b0;

        case (opcode)
            /* R-type */
            7'b0110011: begin
                funct7          = instr[31:25];
                funct3          = instr[14:12];
                immext          = 32'bx;
                rd              = instr[11:7];
                rs1             = instr[19:15];
                rs2             = instr[24:20];
                reg_write_request = 1'b1;
                imm_enable      = 1'b0;
                is_branch         = 1'b0;
                branch_type      = 3'bx;
            end

            /* I-type */
            7'b0010011, // addi, ori
            7'b0000011: // lw
            begin
                funct7          = 7'bx;
                funct3          = instr[14:12];
                immext          = {{20{instr[31]}}, instr[31:20]};
                rd              = instr[11:7];
                rs1             = instr[19:15];
                rs2             = 5'bx;
                reg_write_request = 1'b1;
                imm_enable      = 1'b1;
                is_branch         = 1'b0;
                branch_type      = 3'bx;
            end

            /* S-type */
            7'b0100011: // sw
            begin
                funct7          = instr[31:25];
                funct3          = instr[14:12];
                immext          = {{20{instr[31]}}, instr[31:25], instr[11:7]};
                rd              = 5'bx;
                rs1             = instr[19:15];
                rs2             = instr[24:20];
                reg_write_request = 1'b0;
                imm_enable          = 1'b1;
                is_branch         = 1'b0;
                branch_type      = 3'bx;
            end

            /* B-type */
            7'b1100011: begin // branch instructions
                funct3          = instr[14:12];
                immext          = {{20{instr[31]}}, instr[7], instr[30:25], instr[11:8], 1'b0}; // B型即値
                rd              = 5'bx;
                rs1             = instr[19:15];
                rs2             = instr[24:20];
                reg_write_request = 1'b0;
                imm_enable      = 1'b0;
                is_branch         = 1'b1;
            end

            /* U-type */
            7'b0110111,  // LUI
            7'b0010111: begin  // AUIPC
                funct7          = 7'bx;
                funct3          = 3'bx;
                immext          = {instr[31:12], 12'b0};
                rd              = instr[11:7];
                rs1             = 5'b0;
                rs2             = 5'b0;
                reg_write_request = 1'b1;
                imm_enable         = 1'b1;
                is_branch         = 1'b0;
                branch_type      = 3'bx;
            end

            /* J-type */
            7'b1101111: begin // jal
                funct7          = 7'bx;
                funct3          = 3'bx;
                immext          = 32'bx;
                rd              = instr[11:7];
                rs1             = 5'bx;
                rs2             = 5'bx;
                is_branch         = 1'b0;
                branch_type      = 3'bx;
            end

            default: begin
                funct7          = 7'bx;
                funct3          = 3'bx;
                immext          = 32'bx;
                rd              = 5'bx;
                rs1             = 5'bx;
                rs2             = 5'bx;
                is_branch         = 1'b0;
                branch_type      = 3'bx;
            end
        endcase
    end

    // ALU operation decoding
    always @* begin
        case (funct3)
            3'b000: begin
                if (opcode == 7'b0110011) // R-type
                begin
                    case (funct7)
                        7'b0000000: alu_op = 4'b0000;  // add
                        7'b0100000: alu_op = 4'b0001;  // sub
                        default:    alu_op = 4'bx;
                    endcase
                end
                else if (opcode == 7'b0010011) // I-type (addi)
                begin
                    alu_op = 4'b0000;   // addi
                end
                else begin
                    alu_op = 4'bx;
                end
            end

            3'b001: alu_op = 4'b0010;  // sll
            3'b010: begin
                case (opcode)
                    7'b0000011: begin // lw
                        alu_op = 4'b0000; // addでアドレス計算
                        reg_write_request = 1;
                        mem_read_request  = 1;
                    end
                    7'b0100011: begin // sw
                        alu_op = 4'b0000;
                        mem_write_request = 1;
                    end
                    7'b0110011: begin // slt
                        alu_op = 4'b1110;
                        mem_write_request = 1'b0;
                        mem_read_request = 1'b0;
                    end
                    default: alu_op = 4'bx;
                endcase
            end

            3'b011: alu_op = 4'b0100;  // sltu
            3'b100: alu_op = 4'b0101;  // xor
            3'b101: begin
                case (funct7)
                    7'b0000000: alu_op = 4'b0110;  // srl
                    7'b0100000: alu_op = 4'b0111;  // sra
                    default:    alu_op = 4'bx;
                endcase
            end
            3'b110: alu_op = 4'b1000;  // ori
            3'b111: alu_op = 4'b1001;  // and
            default: alu_op = 4'bx;
        endcase
        if (opcode == 7'b1100011) begin
            case (funct3)
                3'b000: begin
                    alu_op = 4'b1100; // beq
                    branch_type = 3'b000;
                end
                3'b001: begin
                    alu_op = 4'b1101; // bne
                    branch_type = 3'b001;
                end
                3'b100: begin
                    alu_op = 4'b1110; // blt
                    branch_type = 3'b100;
                end
                3'b101: begin
                    alu_op = 4'b1111; // bge
                    branch_type = 3'b101;
                end
            endcase
        end else if (opcode == 7'b0110111) begin
            alu_op = 4'b1011;   // lui
        end else if (opcode == 7'b0010111) begin
            alu_op = 4'b0000;    // auipc
        end
    end

endmodule

src/haconiwa_core.v
module HACONIWA_CORE(
    input               clk,
    input               reset,
    output reg  [31:0]  pc,
    input       [31:0]  instr,
    output      [31:0]  core2mem_access_address,
    input       [31:0]  mem2core_read_data,
    output      [31:0]  core2mem_write_data,
    output              core2mem_write_request
);

/* === Pipeline Registers === */
reg         stall, flush;

reg [31:0]  IF_ID_pc, IF_ID_instr;

reg [3:0]   ID_EXE_alu_op;
reg [2:0]   ID_EXE_branch_type;
reg [31:0]  ID_EXE_pc, next_pc, ID_EXE_immext, ID_EXE_read_reg_data1, ID_EXE_read_reg_data2;
reg [4:0]   ID_EXE_rd, ID_EXE_rs1, ID_EXE_rs2;
reg         ID_EXE_reg_write_request, ID_EXE_mem_write_request, ID_EXE_mem_read_request, ID_EXE_imm_enable, ID_EXE_is_branch;

reg [4:0]   EXE_MEM_rd;
reg [31:0]  EXE_MEM_aluout, EXE_MEM_write_data;
reg         EXE_MEM_reg_write_request, EXE_MEM_mem_write_request, EXE_MEM_mem_read_request;

reg         MEM_WB_reg_write_request;
reg [4:0]   MEM_WB_rd;
reg [31:0]  MEM_WB_reg_write_data;

/* === IF Stage === */
always @* begin
    if (flush) begin
        next_pc = ID_EXE_pc + ID_EXE_immext;
    end else begin
        next_pc = pc + 4;
    end
end

always @ (posedge clk) begin
    if (reset) begin
        pc <= 32'h0;
    end else if (!stall) begin
        pc <= next_pc;
        IF_ID_pc <= pc;
        IF_ID_instr <= (flush) ? 32'h00000013 : instr;
    end
end

/* === ID Stage === */
wire [3:0] alu_op;
wire [31:0] immext, read_reg_data1, read_reg_data2;
wire [4:0] rd, rs1, rs2;
wire [2:0] branch_type;
wire dec_reg_write_request, dec_mem_write_request, dec_mem_read_request, dec_imm_enable, dec_is_branch;

DECODER dec(
    .instr(IF_ID_instr),
    .alu_op(alu_op),
    .rd(rd),
    .rs1(rs1),
    .rs2(rs2),
    .immext(immext),
    .imm_enable(dec_imm_enable),
    .reg_write_request(dec_reg_write_request),
    .mem_write_request(dec_mem_write_request),
    .mem_read_request(dec_mem_read_request),
    .is_branch(is_branch),
    .branch_type(branch_type)
);

REGFILE regfile(
    .clk(clk),
    .read_address1(rs1),
    .read_address2(rs2),
    .read_data1(read_reg_data1),
    .read_data2(read_reg_data2),
    .write_request(MEM_WB_reg_write_request),
    .write_address(MEM_WB_rd),
    .write_data(MEM_WB_reg_write_data)
);

wire [31:0] id_fwd_src1, id_fwd_src2;
assign id_fwd_src1 = (MEM_WB_reg_write_request && MEM_WB_rd != 0 && MEM_WB_rd == rs1)
                        ? MEM_WB_reg_write_data : read_reg_data1;
assign id_fwd_src2 = (MEM_WB_reg_write_request && MEM_WB_rd != 0 && MEM_WB_rd == rs2)
                        ? MEM_WB_reg_write_data : read_reg_data2;

always @ (posedge clk) begin
    if (!stall) begin
        ID_EXE_pc                   <= IF_ID_pc;
        ID_EXE_alu_op               <= alu_op;
        ID_EXE_immext               <= immext;
        ID_EXE_read_reg_data1       <= id_fwd_src1;
        ID_EXE_read_reg_data2       <= id_fwd_src2;
        ID_EXE_rd                   <= rd;
        ID_EXE_rs1                  <= rs1;
        ID_EXE_rs2                  <= rs2;
        ID_EXE_reg_write_request    <= dec_reg_write_request;
        ID_EXE_mem_write_request    <= dec_mem_write_request;
        ID_EXE_mem_read_request     <= dec_mem_read_request;
        ID_EXE_imm_enable           <= dec_imm_enable;
        ID_EXE_is_branch            <= is_branch;
        ID_EXE_branch_type          <= branch_type;
    end else begin
        ID_EXE_pc                   <= 32'b0;
        ID_EXE_alu_op               <= 4'b0;
        ID_EXE_immext               <= 32'b0;
        ID_EXE_read_reg_data1       <= 32'b0;
        ID_EXE_read_reg_data2       <= 32'b0;
        ID_EXE_rd                   <= 5'b0;
        ID_EXE_rs1                  <= 5'b0;
        ID_EXE_rs2                  <= 5'b0;
        ID_EXE_reg_write_request    <= 1'b0;
        ID_EXE_mem_write_request    <= 1'b0;
        ID_EXE_mem_read_request     <= 1'b0;
        ID_EXE_imm_enable           <= 1'b0; 
        ID_EXE_is_branch            <= 1'b0;
        ID_EXE_branch_type          <= 1'b0;
    end
end

// load-use hazard detection
wire load_use_hazard;
assign load_use_hazard = (ID_EXE_mem_read_request &&
                            ((ID_EXE_rd == rs1 && ID_EXE_rd != 0) ||
                            (ID_EXE_rd == rs2 && ID_EXE_rd != 0)));
always @* begin
    if (reset) begin
        stall = 1'b0;
    end else begin
        stall = load_use_hazard;
    end
end

/* === EXE Stage === */
wire [31:0] exe_fwd_src1, exe_fwd_src2;
assign exe_fwd_src1 = (EXE_MEM_reg_write_request && EXE_MEM_rd != 0 && EXE_MEM_rd == ID_EXE_rs1)
                    ? EXE_MEM_aluout
                    : (MEM_WB_reg_write_request && MEM_WB_rd != 0 && MEM_WB_rd == ID_EXE_rs1)
                        ? MEM_WB_reg_write_data
                        : ID_EXE_read_reg_data1;

assign exe_fwd_src2 = (EXE_MEM_reg_write_request && EXE_MEM_rd != 0 && EXE_MEM_rd == ID_EXE_rs2)
                    ? EXE_MEM_aluout
                    : (MEM_WB_reg_write_request && MEM_WB_rd != 0 && MEM_WB_rd == ID_EXE_rs2)
                        ? MEM_WB_reg_write_data
                        : ID_EXE_read_reg_data2;

wire [31:0] alu_src1, alu_src2, exe_aluout;
assign alu_src1 = exe_fwd_src1;
assign alu_src2 = ID_EXE_imm_enable ? ID_EXE_immext : exe_fwd_src2;

ALU alu(
    .alu_op(ID_EXE_alu_op),
    .src1(alu_src1),
    .src2(alu_src2),
    .aluout(exe_aluout)
);

wire branch_taken;
assign branch_taken = (ID_EXE_is_branch && (exe_aluout == 1'b1)) ? 1'b1 : 1'b0 ;
// assign branch_taken =   (ID_EXE_branch_type == 3'b000) ? (fwd_src1 == fwd_src2) :
//                         (ID_EXE_branch_type == 3'b001) ? (fwd_src1 != fwd_src2) :
//                         (ID_EXE_branch_type == 3'b100) ? (fwd_src1 < fwd_src2) :
//                         (ID_EXE_branch_type == 3'b101) ? (fwd_src1 >= fwd_src2) : 1'b0;

always @* begin
    flush = ID_EXE_is_branch && branch_taken;
end

always @ (posedge clk) begin
    EXE_MEM_aluout <= exe_aluout;
    EXE_MEM_rd <= ID_EXE_rd;
    EXE_MEM_write_data <= exe_fwd_src2;
    EXE_MEM_reg_write_request <= ID_EXE_reg_write_request;
    EXE_MEM_mem_write_request <= ID_EXE_mem_write_request;
    EXE_MEM_mem_read_request <= ID_EXE_mem_read_request;
end

/* === MEM Stage === */
assign core2mem_write_request = EXE_MEM_mem_write_request;
assign core2mem_access_address = EXE_MEM_aluout;
assign core2mem_write_data = EXE_MEM_write_data;

always @ (posedge clk) begin
    MEM_WB_reg_write_request <= EXE_MEM_reg_write_request;
    MEM_WB_rd <= EXE_MEM_rd;
    MEM_WB_reg_write_data <= (EXE_MEM_mem_read_request) ? mem2core_read_data : EXE_MEM_aluout;
end

endmodule

src/haconiwa_top.v
module HACONIWA_TOP(
    input   CLOCK_50_B5B, CPU_RESET_n
);

wire [31:0] pc, instr, core2mem_access_address, mem2core_read_data, core2mem_write_data;
wire core2mem_write_request;

HACONIWA_CORE hcore(
    .clk(CLOCK_50_B5B),
    .reset(!CPU_RESET_n),
    .pc(pc),
    .instr(instr),
    .core2mem_access_address(core2mem_access_address),
    .mem2core_read_data(mem2core_read_data),
    .core2mem_write_data(core2mem_write_data),
    .core2mem_write_request(core2mem_write_request)
);

IMEM imem(
    .addr(pc),
    .instr(instr)
);

DMEM dmem(
    .clk(CLOCK_50_B5B),
    .access_address(core2mem_access_address),
    .read_data(mem2core_read_data),
    .write_data(core2mem_write_data),
    .write_request(core2mem_write_request)
);

endmodule

module SIMTOP();
    reg clk, reset;

    HACONIWA_TOP htop(
        .CLOCK_50_B5B(clk),
        .CPU_RESET_n(!reset)
    );

    initial begin
        clk = 0;
        forever #5 clk = ~clk;
    end

    initial begin
        #10 reset = 1;
        #20 reset = 0;
        $dumpfile("sim_top_haconiwa.vcd");
        $dumpvars(0, htop);

        #2000 $finish;
    end
endmodule

test/sim_top_haconiwa.vcd
$date
	Sun May  4 02:17:19 2025
$end
$version
	Icarus Verilog
$end
$timescale
	1s
$end
$scope module SIMTOP $end
$scope module htop $end
$var wire 1 ! CLOCK_50_B5B $end
$var wire 1 " CPU_RESET_n $end
$var wire 32 # pc [31:0] $end
$var wire 32 $ mem2core_read_data [31:0] $end
$var wire 32 % instr [31:0] $end
$var wire 1 & core2mem_write_request $end
$var wire 32 ' core2mem_write_data [31:0] $end
$var wire 32 ( core2mem_access_address [31:0] $end
$scope module dmem $end
$var wire 1 ! clk $end
$var wire 32 ) read_data [31:0] $end
$var wire 1 & write_request $end
$var wire 32 * write_data [31:0] $end
$var wire 32 + access_address [31:0] $end
$var integer 32 , i [31:0] $end
$upscope $end
$scope module hcore $end
$var wire 32 - alu_src1 [31:0] $end
$var wire 1 ! clk $end
$var wire 32 . core2mem_access_address [31:0] $end
$var wire 32 / core2mem_write_data [31:0] $end
$var wire 1 & core2mem_write_request $end
$var wire 1 0 load_use_hazard $end
$var wire 32 1 mem2core_read_data [31:0] $end
$var wire 1 2 reset $end
$var wire 5 3 rs2 [4:0] $end
$var wire 5 4 rs1 [4:0] $end
$var wire 32 5 read_reg_data2 [31:0] $end
$var wire 32 6 read_reg_data1 [31:0] $end
$var wire 5 7 rd [4:0] $end
$var wire 1 8 is_branch $end
$var wire 32 9 instr [31:0] $end
$var wire 32 : immext [31:0] $end
$var wire 32 ; id_fwd_src2 [31:0] $end
$var wire 32 < id_fwd_src1 [31:0] $end
$var wire 32 = exe_fwd_src2 [31:0] $end
$var wire 32 > exe_fwd_src1 [31:0] $end
$var wire 32 ? exe_aluout [31:0] $end
$var wire 1 @ dec_reg_write_request $end
$var wire 1 A dec_mem_write_request $end
$var wire 1 B dec_mem_read_request $end
$var wire 1 C dec_imm_enable $end
$var wire 3 D branch_type [2:0] $end
$var wire 1 E branch_taken $end
$var wire 32 F alu_src2 [31:0] $end
$var wire 4 G alu_op [3:0] $end
$var reg 32 H EXE_MEM_aluout [31:0] $end
$var reg 1 I EXE_MEM_mem_read_request $end
$var reg 1 J EXE_MEM_mem_write_request $end
$var reg 5 K EXE_MEM_rd [4:0] $end
$var reg 1 L EXE_MEM_reg_write_request $end
$var reg 32 M EXE_MEM_write_data [31:0] $end
$var reg 4 N ID_EXE_alu_op [3:0] $end
$var reg 3 O ID_EXE_branch_type [2:0] $end
$var reg 1 P ID_EXE_imm_enable $end
$var reg 32 Q ID_EXE_immext [31:0] $end
$var reg 1 R ID_EXE_is_branch $end
$var reg 1 S ID_EXE_mem_read_request $end
$var reg 1 T ID_EXE_mem_write_request $end
$var reg 32 U ID_EXE_pc [31:0] $end
$var reg 5 V ID_EXE_rd [4:0] $end
$var reg 32 W ID_EXE_read_reg_data1 [31:0] $end
$var reg 32 X ID_EXE_read_reg_data2 [31:0] $end
$var reg 1 Y ID_EXE_reg_write_request $end
$var reg 5 Z ID_EXE_rs1 [4:0] $end
$var reg 5 [ ID_EXE_rs2 [4:0] $end
$var reg 32 \ IF_ID_instr [31:0] $end
$var reg 32 ] IF_ID_pc [31:0] $end
$var reg 5 ^ MEM_WB_rd [4:0] $end
$var reg 32 _ MEM_WB_reg_write_data [31:0] $end
$var reg 1 ` MEM_WB_reg_write_request $end
$var reg 1 a flush $end
$var reg 32 b next_pc [31:0] $end
$var reg 32 c pc [31:0] $end
$var reg 1 d stall $end
$scope module alu $end
$var wire 4 e alu_op [3:0] $end
$var wire 32 f src1 [31:0] $end
$var wire 32 g src2 [31:0] $end
$var reg 32 h aluout [31:0] $end
$upscope $end
$scope module dec $end
$var wire 32 i instr [31:0] $end
$var wire 7 j opcode [6:0] $end
$var reg 4 k alu_op [3:0] $end
$var reg 3 l branch_type [2:0] $end
$var reg 3 m funct3 [2:0] $end
$var reg 7 n funct7 [6:0] $end
$var reg 1 C imm_enable $end
$var reg 32 o immext [31:0] $end
$var reg 1 8 is_branch $end
$var reg 1 B mem_read_request $end
$var reg 1 A mem_write_request $end
$var reg 5 p rd [4:0] $end
$var reg 1 @ reg_write_request $end
$var reg 5 q rs1 [4:0] $end
$var reg 5 r rs2 [4:0] $end
$upscope $end
$scope module regfile $end
$var wire 1 ! clk $end
$var wire 5 s read_address1 [4:0] $end
$var wire 5 t read_address2 [4:0] $end
$var wire 5 u write_address [4:0] $end
$var wire 32 v write_data [31:0] $end
$var wire 1 ` write_request $end
$var wire 32 w read_data2 [31:0] $end
$var wire 32 x read_data1 [31:0] $end
$var integer 32 y i [31:0] $end
$upscope $end
$upscope $end
$scope module imem $end
$var wire 32 z addr [31:0] $end
$var wire 32 { instr [31:0] $end
$upscope $end
$upscope $end
$upscope $end
$enddefinitions $end
$comment Show the parameter values. $end
$dumpall
$end
#30
$dumpvars
b10011 {
b0 z
b100000 y
bx x
bx w
bx v
b0 u
bx t
bx s
bx r
bx q
bx p
bx o
bx n
bx m
bx l
bx k
bx j
bx i
bx h
bx g
bx f
bx e
xd
b0 c
b100 b
xa
0`
bx _
b0 ^
bx ]
bx \
bx [
bx Z
xY
bx X
bx W
bx V
bx U
xT
xS
xR
bx Q
xP
bx O
bx N
bx M
xL
bx K
xJ
xI
bx H
bx G
bx F
xE
bx D
xC
xB
xA
x@
bx ?
bx >
bx =
bx <
bx ;
bx :
b10011 9
x8
bx 7
bx 6
bx 5
bx 4
bx 3
02
bx 1
x0
bx /
bx .
bx -
b100000 ,
bx +
bx *
bx )
bx (
bx '
x&
b10011 %
bx $
b0 #
1"
0!
$end
#35
0E
0d
0a
00
bx ^
bx u
x`
b0 O
0R
0P
0S
0T
0Y
b0 [
b0 Z
b0 V
b0 X
b0 W
b0 Q
b0 N
b0 e
b0 U
1!
#40
0!
#45
xd
x0
b0 6
b0 x
xa
b0 G
b0 k
xE
b0 4
b0 q
b0 s
b0 7
b0 p
b0 :
b0 o
b0 m
bx D
bx l
08
1C
0B
0A
1@
b10011 j
b1000 b
b10011 \
b10011 i
b0 ]
b100 #
b100 c
b100 z
bx O
xR
xP
xS
xT
xY
bx [
bx Z
bx V
bx X
bx W
bx Q
bx N
bx e
bx U
0I
0&
0J
0L
b0 K
1!
#50
0!
#55
b0 <
0E
0d
0a
00
b0 ^
b0 u
0`
xI
x&
xJ
xL
bx K
b0 O
0R
0P
0S
0T
0Y
b0 [
b0 Z
b0 V
b0 X
b0 W
b0 Q
b0 N
b0 e
b0 U
1!
#60
0!
#65
bx ?
bx h
bx <
bx -
bx f
bx >
b1100 b
b0 F
b0 g
b100 ]
b1000 #
b1000 c
b1000 z
bx O
1P
1Y
bx [
bx X
0I
0&
0J
0L
b0 K
bx ^
bx u
x`
1!
#70
0!
#75
b0 <
b10000 b
b0 ^
b0 u
0`
1L
bx W
b100 U
b1000 ]
b1100 #
b1100 c
b1100 z
1!
#80
0!
#85
b0 ?
b0 h
b0 -
b0 f
b0 >
b10100 b
b1100 ]
b10000 #
b10000 c
b10000 z
b0 W
b1000 U
1`
1!
#90
0!
#95
b0 $
b0 )
b0 1
b11000 b
b0 (
b0 +
b0 .
b0 H
b1100 U
b10000 ]
b10100 #
b10100 c
b10100 z
1!
#100
0!
#105
b1000000010110111 %
b1000000010110111 9
b1000000010110111 {
b11100 b
b10100 ]
b11000 #
b11000 c
b11000 z
b10000 U
b0 _
b0 v
1!
#110
0!
#115
b0 ;
b0 5
b0 w
b1011 G
b1011 k
b0 3
b0 r
b0 t
bx D
bx l
b1000000000000000 :
b1000000000000000 o
b0 4
b0 q
b0 s
b1 7
b1 p
bx m
1C
1@
b110111 j
b100000 b
b100000000000100010011 %
b100000000000100010011 9
b100000000000100010011 {
b10100 U
b1000000010110111 \
b1000000010110111 i
b11000 ]
b11100 #
b11100 c
b11100 z
1!
#120
0!
#125
bx ;
bx 5
bx w
b0 G
b0 k
b0 =
b1000000000000000 ?
b1000000000000000 h
b0 m
bx D
bx l
b1 :
b1 o
bx 3
bx r
bx t
b0 4
b0 q
b0 s
b10 7
b10 p
1C
1@
b10011 j
b101100000000000110010011 %
b101100000000000110010011 9
b101100000000000110010011 {
b1000000000000000 F
b1000000000000000 g
b100100 b
b100000000000100010011 \
b100000000000100010011 i
b11100 ]
b100000 #
b100000 c
b100000 z
b0 [
b1 V
b0 X
b1000000000000000 Q
b1011 N
b1011 e
b11000 U
1!
#130
0!
#135
b1 ?
b1 h
bx =
bx $
bx )
bx 1
b1 F
b1 g
bx D
bx l
b1011 :
b1011 o
b0 4
b0 q
b0 s
b11 7
b11 p
b0 m
1C
1@
b101000 b
b100000000001000010011 %
b100000000001000010011 9
b100000000001000010011 {
b0 '
b0 *
b0 /
b0 M
b1 K
b1000000000000000 (
b1000000000000000 +
b1000000000000000 .
b1000000000000000 H
bx [
b10 V
bx X
b1 Q
b0 N
b0 e
b11100 U
b101100000000000110010011 \
b101100000000000110010011 i
b100000 ]
b100100 #
b100100 c
b100100 z
1!
#140
0!
#145
b1011 ?
b1011 h
bx D
bx l
b1 :
b1 o
b0 4
b0 q
b0 s
b100 7
b100 p
b0 m
1C
1@
b1000001000000010110011 %
b1000001000000010110011 9
b1000001000000010110011 {
b1011 F
b1011 g
b101100 b
b0 $
b0 )
b0 1
b100000000001000010011 \
b100000000001000010011 i
b100100 ]
b101000 #
b101000 c
b101000 z
b11 V
b1011 Q
b100000 U
bx '
bx *
bx /
bx M
b10 K
b1 (
b1 +
b1 .
b1 H
b1000000000000000 _
b1000000000000000 v
b1 ^
b1 u
1!
#150
0!
#155
b1 ?
b1 h
b1000000000000000 <
b0 5
b0 w
b1 ;
b1000000000000000 6
b1000000000000000 x
b1 F
b1 g
b10 3
b10 r
b10 t
b0 n
bx D
bx l
bx :
bx o
b1 4
b1 q
b1 s
b1 7
b1 p
b0 m
0C
1@
b110011 j
b110000 b
b100010000000100010011 %
b100010000000100010011 9
b100010000000100010011 {
b1 _
b1 v
b10 ^
b10 u
b11 K
b1011 (
b1011 +
b1011 .
b1011 H
b100 V
b1 Q
b100100 U
b1000001000000010110011 \
b1000001000000010110011 i
b101000 ]
b101100 #
b101100 c
b101100 z
1!
#160
0!
#165
b1000000000000001 ?
b1000000000000001 h
b1 <
b1 6
b1 x
b1000000000000000 -
b1000000000000000 f
b1000000000000000 >
bx 5
bx w
1C
b1 :
b1 o
bx D
bx l
bx 3
bx r
bx t
b10 4
b10 q
b10 s
b10 7
b10 p
b0 m
bx n
1@
b10011 j
b1100010010001010110011 %
b1100010010001010110011 9
b1100010010001010110011 {
b1 F
b1 g
b110100 b
b1 =
bx ;
b100010000000100010011 \
b100010000000100010011 i
b101100 ]
b110000 #
b110000 c
b110000 z
0P
b10 [
b1 Z
b1 V
b1 X
b1000000000000000 W
bx Q
b101000 U
b100 K
b1 (
b1 +
b1 .
b1 H
b1011 _
b1011 v
b11 ^
b11 u
1!
#170
0!
#175
b10 ?
b10 h
b1011 ;
b1011 5
b1011 w
bx =
b1 -
b1 f
b1 >
b1110 G
b1110 k
bx $
bx )
bx 1
b11 3
b11 r
b11 t
b0 n
bx D
bx l
bx :
bx o
b10 4
b10 q
b10 s
b101 7
b101 p
b10 m
0C
1@
b110011 j
b111000 b
b11111110010000101000101011100011 %
b11111110010000101000101011100011 9
b11111110010000101000101011100011 {
b1 _
b1 v
b100 ^
b100 u
b1 '
b1 *
b1 /
b1 M
b1 K
b1000000000000001 (
b1000000000000001 +
b1000000000000001 .
b1000000000000001 H
1P
bx [
b10 Z
b10 V
bx X
b1 W
b1 Q
b101100 U
b1100010010001010110011 \
b1100010010001010110011 i
b110000 ]
b110100 #
b110100 c
b110100 z
1!
#180
0!
#185
b1 ;
b0 <
b1 5
b1 w
b0 6
b0 x
b1100 G
b1100 k
b10 -
b10 f
b10 >
18
b11111111111111111111111111110100 :
b11111111111111111111111111110100 o
b0 D
b0 l
b100 3
b100 r
b100 t
b101 4
b101 q
b101 s
bx 7
bx p
b0 m
bx n
0@
b1100011 j
b10000000000001110000010010011 %
b10000000000001110000010010011 9
b10000000000001110000010010011 {
b1011 F
b1011 g
b1 ?
b1 h
b111100 b
b1011 =
b0 $
b0 )
b0 1
b11111110010000101000101011100011 \
b11111110010000101000101011100011 i
b110100 ]
b111000 #
b111000 c
b111000 z
0P
b11 [
b101 V
b1011 X
bx Q
b1110 N
b1110 e
b110000 U
bx '
bx *
bx /
bx M
b10 K
b10 (
b10 +
b10 .
b10 H
b1000000000000001 _
b1000000000000001 v
b1 ^
b1 u
1!
#190
0!
#195
1a
1E
b1000000000000001 <
b1 F
b1 g
bx 5
bx w
bx ;
b1000000000000001 6
b1000000000000001 x
b1 =
b1000 G
b1000 k
b1 -
b1 f
b1 >
b1 ?
b1 h
bx D
bx l
1C
1@
b1 7
b1 p
08
b100000000 :
b100000000 o
bx 3
bx r
bx t
b1 4
b1 q
b1 s
b110 m
b10011 j
b101000 b
b100000100000010101000100011 %
b100000100000010101000100011 9
b100000100000010101000100011 {
b10 _
b10 v
b10 ^
b10 u
b1011 '
b1011 *
b1011 /
b1011 M
b101 K
b1 (
b1 +
b1 .
b1 H
b0 O
1R
0Y
b100 [
b101 Z
bx V
b1 X
b0 W
b11111111111111111111111111110100 Q
b1100 N
b1100 e
b110100 U
b10000000000001110000010010011 \
b10000000000001110000010010011 i
b111000 ]
b111100 #
b111100 c
b111100 z
1!
#200
0!
#205
b0 <
b0 6
b0 x
b0 G
b0 k
0E
b1000000100000001 ?
b1000000100000001 h
b1000000000000001 -
b1000000000000001 f
b1000000000000001 >
bx =
bx D
bx l
b0 :
b0 o
b0 4
b0 q
b0 s
b0 7
b0 p
b0 m
1C
1@
b1000001000000010110011 %
b1000001000000010110011 9
b1000001000000010110011 {
0a
b100000000 F
b100000000 g
b101100 b
b10011 \
b10011 i
b111100 ]
b101000 #
b101000 c
b101000 z
bx O
0R
1P
1Y
bx [
b1 Z
b1 V
bx X
b1000000000000001 W
b100000000 Q
b1000 N
b1000 e
b111000 U
0L
b1 '
b1 *
b1 /
b1 M
bx K
b1 _
b1 v
b101 ^
b101 u
1!
#210
0!
