src/dmem_iverilog.v
`define DRAM_depth 4096

module DMEM(
    input           clk, write_request,
    input   [31:0]  access_address, write_data,
    output  [31:0]  read_data
);

reg [31:0] RAM[0:`DRAM_depth-1];

assign read_data = RAM[access_address[31:2]];

always @ (posedge clk) begin
    if (write_request) begin
        RAM[access_address[31:2]] <= write_data;

        if (access_address == 32'h0000FFFC) begin
            $display("writedata: %d", write_data);
        end
    end
end

/* データメモリの初期化(シミュレーション用) */
integer i;
initial begin
    for (i = 0; i < `DRAM_depth; i = i + 1) begin
        RAM[i] = 32'b0;
    end
end

endmodule

src/imem_iverilog.v
`define MEMDATA "memory.data"

module IMEM(
    input   [31:0]  addr,
    output  [31:0]  instr
);

reg [31:0]  ROM[63:0];

initial begin
    $readmemh(`MEMDATA, ROM, 0, 63);
end

assign  instr = ROM[addr[31:2]];    // pc <= pc + 32'h4;に対応

endmodule

src/alu.v
module ALU(
    input       [3:0]   alu_op,
    input       [31:0]  src1,
    input       [31:0]  src2,
    output reg  [31:0]  aluout
);

always @* begin
    case (alu_op)
        4'b0000,
        4'b1010:
        begin
            aluout <= src1 + src2;  // add, addi
        end
        4'b0001: aluout = src1 - src2;  // sub
        4'b0010: aluout = src1 & src2;  // and
        4'b0011: aluout = src1 | src2;  // or
        4'b0100: aluout = src1 ^ src2;  // xor
        4'b1100: aluout = (src1 == src2) ? 32'b1 : 32'b0; // beq
        4'b1101: aluout = (src1 != src2) ? 32'b1 : 32'b0; // bne
        4'b1110: aluout = ($signed(src1) < $signed(src2)) ? 32'b1 : 32'b0; // blt, slt
        4'b1111: aluout = ($signed(src1) >= $signed(src2)) ? 32'b1 : 32'b0; // bge
    endcase
end

endmodule

src/regfile.v
module REGFILE(
    input clk,
    input write_request,
    input   [4:0] write_address,
    input   [4:0] read_address1,
    input   [4:0] read_address2,
    input  [31:0] write_data,
    output  [31:0] read_data1,
    output  [31:0] read_data2
);

reg [31:0] register_file [31:0];

always @ (posedge clk) begin
    if (write_request) register_file[write_address] <= write_data;
end

/* レジスタの初期化(シミュレーション用) */
integer i;
initial begin
    for (i = 0; i < 32; i = i + 1) begin
        register_file[i] = 32'b0;
    end
end

assign read_data1 = (read_address1 != 0) ? register_file[read_address1] : 0;
assign read_data2 = (read_address2 != 0) ? register_file[read_address2] : 0;

endmodule

src/decoder.v
module DECODER(
    input       [31:0]  instr,
    output reg  [3:0]   alu_op,
    output reg  [31:0]  immext,
    output reg  [4:0]   rd, rs1, rs2,
    output reg          reg_write_request,
    output reg          mem_write_request,
    output reg          mem_read_request,
    output reg          imm_enable
);

    reg debug_isload;
    reg debug_isstore;
    wire [6:0] opcode = instr[6:0];
    reg [6:0] funct7;
    reg [2:0] funct3;

    // 初期化（デフォルト値設定）
    always @* begin
        reg_write_request = 1'b0;
        mem_write_request = 1'b0;
        mem_read_request  = 1'b0;
        imm_enable        = 1'b0;
        funct7            = 7'bx;
        funct3            = 3'bx;
        rd                = 5'bx;
        rs1               = 5'bx;
        rs2               = 5'bx;
        immext            = 32'bx;
        debug_isload = 0;
        debug_isstore = 0;

        case (opcode)
            /* R-type */
            7'b0110011: begin
                funct7          = instr[31:25];
                funct3          = instr[14:12];
                immext          = 32'bx;
                rd              = instr[11:7];
                rs1             = instr[19:15];
                rs2             = instr[24:20];
                reg_write_request = 1'b1;
                imm_enable      = 1'b0;
            end

            /* I-type */
            7'b0010011, // addi
            7'b0000011: // lw
            begin
                funct7          = 7'bx;
                funct3          = instr[14:12];
                immext          = {{20{instr[31]}}, instr[31:20]};
                rd              = instr[11:7];
                rs1             = instr[19:15];
                rs2             = 5'bx;
                reg_write_request = 1'b1;
                imm_enable      = 1'b1;
                // $display("immext1: %h (opcode: %b)", immext, opcode);
            end

            /* S-type */
            7'b0100011: // sw
            begin
                funct7          = instr[31:25];
                funct3          = instr[14:12];
                immext          = {{20{instr[31]}}, instr[31:25], instr[11:7]};
                rd              = 5'bx;
                rs1             = instr[19:15];
                rs2             = instr[24:20];
                reg_write_request = 1'b0;
                imm_enable          = 1'b1;
                debug_isstore = 1'b1;
                $display("immext2: %h (opcode: %b)", immext, opcode);
            end

            /* B-type */
            7'b1100011: begin // branch instructions
                funct7          = 7'bx;
                funct3          = 3'bx;
                immext          = 32'bx;
                rd              = 5'bx;
                rs1             = 5'bx;
                rs2             = 5'bx;
            end

            /* U-type */
            7'b0110111,  // LUI
            7'b0010111: begin  // AUIPC
                funct7          = 7'bx;
                funct3          = 3'bx;
                immext          = 32'bx;
                rd              = instr[11:7];
                rs1             = 5'bx;
                rs2             = 5'bx;
            end

            /* J-type */
            7'b1101111: begin // jal
                funct7          = 7'bx;
                funct3          = 3'bx;
                immext          = 32'bx;
                rd              = instr[11:7];
                rs1             = 5'bx;
                rs2             = 5'bx;
            end

            default: begin
                funct7          = 7'bx;
                funct3          = 3'bx;
                immext          = 32'bx;
                rd              = 5'bx;
                rs1             = 5'bx;
                rs2             = 5'bx;
            end
        endcase
    end

    // ALU operation decoding
    always @* begin
        case (funct3)
            3'b000: begin
                if (opcode == 7'b0110011) // R-type
                begin
                    case (funct7)
                        7'b0000000: alu_op = 4'b0000;  // add
                        7'b0100000: alu_op = 4'b0001;  // sub
                        default:    alu_op = 4'bx;
                    endcase
                end
                else if (opcode == 7'b0010011) // I-type (addi)
                begin
                    alu_op = 4'b0000;   // addi
                end
                else begin
                    alu_op = 4'bx;
                end
            end

            3'b001: alu_op = 4'b0010;  // sll
            3'b010: begin
                case (opcode)
                    7'b0000011: begin // lw
                        alu_op = 4'b0000; // addでアドレス計算
                        reg_write_request = 1;
                        mem_read_request  = 1;
                        debug_isload = 1;
                    end

                    7'b0100011: begin // sw
                        alu_op = 4'b0000;
                        mem_write_request = 1;
                    end
                    default: alu_op = 4'bx;
                endcase
            end

            3'b011: alu_op = 4'b0100;  // sltu
            3'b100: alu_op = 4'b0101;  // xor
            3'b101: begin
                case (funct7)
                    7'b0000000: alu_op = 4'b0110;  // srl
                    7'b0100000: alu_op = 4'b0111;  // sra
                    default:    alu_op = 4'bx;
                endcase
            end
            3'b110: alu_op = 4'b1000;  // or
            3'b111: alu_op = 4'b1001;  // and
            default: alu_op = 4'bx;
        endcase
    end

endmodule


// module DECODER(
//     input       [31:0]  instr,
//     output reg  [3:0]   alu_op,
//     output reg  [31:0]  immext,
//     output reg  [4:0]   rd, rs1, rs2,
//     output reg          reg_write_request,
//     output reg          mem_write_request,
//     output reg          mem_read_request,
//     output reg          imm_enable
// );

//     wire [6:0] opcode = instr[6:0];
//     wire [2:0] funct3 = instr[14:12];
//     wire [6:0] funct7 = instr[31:25];

//     always @* begin
//         // デフォルト値の設定
//         alu_op             = 4'bxxxx;
//         immext             = 32'b0;
//         rd                 = 5'b0;
//         rs1                = 5'b0;
//         rs2                = 5'b0;
//         reg_write_request  = 1'b0;
//         mem_write_request  = 1'b0;
//         mem_read_request   = 1'b0;
//         imm_enable         = 1'b0;

//         case (opcode)
//             7'b0110011: begin // R-type
//                 rd    = instr[11:7];
//                 rs1   = instr[19:15];
//                 rs2   = instr[24:20];
//                 reg_write_request = 1;
//                 imm_enable = 0;
//                 case (funct3)
//                     3'b000: alu_op = (funct7 == 7'b0100000) ? 4'b0001 : 4'b0000; // sub : add
//                     3'b001: alu_op = 4'b0010; // sll
//                     3'b010: alu_op = 4'b0011; // slt
//                     3'b011: alu_op = 4'b0100; // sltu
//                     3'b100: alu_op = 4'b0101; // xor
//                     3'b101: alu_op = (funct7 == 7'b0100000) ? 4'b0111 : 4'b0110; // sra : srl
//                     3'b110: alu_op = 4'b1000; // or
//                     3'b111: alu_op = 4'b1001; // and
//                     default: alu_op = 4'bxxxx;
//                 endcase
//             end

//             7'b0010011: begin // I-type (addi, etc.)
//                 rd    = instr[11:7];
//                 rs1   = instr[19:15];
//                 immext = {{20{instr[31]}}, instr[31:20]};
//                 reg_write_request = 1;
//                 imm_enable = 1;
//                 case (funct3)
//                     3'b000: alu_op = 4'b0000; // addi
//                     default: alu_op = 4'bxxxx;
//                 endcase
//                 $display("immext1: %h (opcode: %b)", immext, opcode);
//             end

//             7'b0000011: begin // I-type (lw)
//                 rd    = instr[11:7];
//                 rs1   = instr[19:15];
//                 immext = {{20{instr[31]}}, instr[31:20]};
//                 reg_write_request = 1;
//                 mem_read_request  = 1;
//                 imm_enable = 1;
//                 alu_op = 4'b0000; // address = rs1 + imm
//                 $display("immext1: %h (opcode: %b)", immext, opcode);
//             end

//             7'b0100011: begin // S-type (sw)
//                 rs1   = instr[19:15];
//                 rs2   = instr[24:20];
//                 immext = {{27{instr[11]}}, instr[11:7]};
//                 mem_write_request = 1;
//                 imm_enable = 1;
//                 alu_op = 4'b0000; // address = rs1 + imm
//                 $display("immext2: %h (opcode: %b)", immext, opcode);
//             end

//             7'b1100011: begin // B-type (e.g., beq)
//                 rs1   = instr[19:15];
//                 rs2   = instr[24:20];
//                 immext = {{20{instr[31]}}, instr[7], instr[30:25], instr[11:8], 1'b0};
//                 alu_op = 4'b1010; // 仮: 比較命令
//                 imm_enable = 1;
//             end

//             7'b0110111: begin // LUI
//                 rd = instr[11:7];
//                 immext = {instr[31:12], 12'b0};
//                 reg_write_request = 1;
//                 imm_enable = 1;
//                 alu_op = 4'b0000;
//             end

//             7'b0010111: begin // AUIPC
//                 rd = instr[11:7];
//                 immext = {instr[31:12], 12'b0};
//                 reg_write_request = 1;
//                 imm_enable = 1;
//                 alu_op = 4'b0000;
//             end

//             7'b1101111: begin // JAL
//                 rd = instr[11:7];
//                 immext = {{12{instr[31]}}, instr[19:12], instr[20], instr[30:21], 1'b0};
//                 reg_write_request = 1;
//                 imm_enable = 1;
//                 alu_op = 4'b0000;
//             end

//             default: begin
//                 alu_op = 4'bxxxx;
//             end
//         endcase
//     end
// endmodule

src/haconiwa_core.v
module HACONIWA_CORE(
    input               clk,
    input               reset,
    output reg  [31:0]  pc,
    input       [31:0]  instr,
    output      [31:0]  core2mem_access_address,
    input       [31:0]  mem2core_read_data,
    output      [31:0]  core2mem_write_data,
    output              core2mem_write_request
);

/* === Pipeline Registers === */
reg [31:0]  IF_ID_instr;
reg         stall;
reg [3:0]   ID_EXE_alu_op;
reg [31:0]  ID_EXE_immext, ID_EXE_read_reg_data1, ID_EXE_read_reg_data2;
reg [4:0]   ID_EXE_rd, ID_EXE_rs1, ID_EXE_rs2;
reg         ID_EXE_reg_write_request, ID_EXE_mem_write_request, ID_EXE_mem_read_request, ID_EXE_imm_enable;
reg [4:0]   EXE_MEM_rd;
reg [31:0]  EXE_MEM_aluout, EXE_MEM_write_data;
reg         EXE_MEM_reg_write_request, EXE_MEM_mem_write_request, EXE_MEM_mem_read_request;
reg         MEM_WB_reg_write_request;
reg [4:0]   MEM_WB_rd;
reg [31:0]  MEM_WB_reg_write_data;

/* === IF Stage === */
always @ (posedge clk) begin
    if (reset) begin
        pc <= 32'h0;
    end else if (!stall) begin
        pc <= pc + 32'h4;
        IF_ID_instr <= instr;
    end else begin
        pc <= pc;
        IF_ID_instr <= IF_ID_instr;
    end
end

/* === ID Stage === */
wire [3:0] alu_op;
wire [31:0] immext, read_reg_data1, read_reg_data2;
wire [4:0] rd, rs1, rs2;
wire dec_reg_write_request, dec_mem_write_request, dec_mem_read_request, dec_imm_enable;

DECODER dec(
    .instr(IF_ID_instr),
    .alu_op(alu_op),
    .rd(rd),
    .rs1(rs1),
    .rs2(rs2),
    .immext(immext),
    .imm_enable(dec_imm_enable),
    .reg_write_request(dec_reg_write_request),
    .mem_write_request(dec_mem_write_request),
    .mem_read_request(dec_mem_read_request)
);

REGFILE regfile(
    .clk(clk),
    .read_address1(rs1),
    .read_address2(rs2),
    .read_data1(read_reg_data1),
    .read_data2(read_reg_data2),
    .write_request(MEM_WB_reg_write_request),
    .write_address(MEM_WB_rd),
    .write_data(MEM_WB_reg_write_data)
);

always @ (posedge clk) begin
    if (!stall) begin
        ID_EXE_alu_op               <= alu_op;
        ID_EXE_immext               <= immext;
        ID_EXE_read_reg_data1       <= read_reg_data1;
        ID_EXE_read_reg_data2       <= read_reg_data2;
        ID_EXE_rd                   <= rd;
        ID_EXE_rs1                  <= rs1;
        ID_EXE_rs2                  <= rs2;
        ID_EXE_reg_write_request    <= dec_reg_write_request;
        ID_EXE_mem_write_request    <= dec_mem_write_request;
        ID_EXE_mem_read_request     <= dec_mem_read_request;
        ID_EXE_imm_enable           <= dec_imm_enable;
    end else begin
        ID_EXE_alu_op               <= 4'b0;
        ID_EXE_immext               <= 32'b0;
        ID_EXE_read_reg_data1       <= 32'b0;
        ID_EXE_read_reg_data2       <= 32'b0;
        ID_EXE_rd                   <= 5'b0;
        ID_EXE_rs1                  <= 5'b0;
        ID_EXE_rs2                  <= 5'b0;
        ID_EXE_reg_write_request    <= 1'b0;
        ID_EXE_mem_write_request    <= 1'b0;
        ID_EXE_mem_read_request     <= 1'b0;
        ID_EXE_imm_enable           <= 1'b0; 
    end
end

// load-use hazard detection
wire load_use_hazard;
assign load_use_hazard = (ID_EXE_mem_read_request &&
                            ((ID_EXE_rd == rs1 && ID_EXE_rd != 0) ||
                            (ID_EXE_rd == rs2 && ID_EXE_rd != 0)));
always @* begin
    if (reset) begin
        stall = 1'b0;
    end else begin
        stall = load_use_hazard;
    end
end

/* === EXE Stage === */
wire [31:0] fwd_src1, fwd_src2;
assign fwd_src1 = (EXE_MEM_reg_write_request && EXE_MEM_rd != 0 && EXE_MEM_rd == ID_EXE_rs1)
                    ? EXE_MEM_aluout
                    : (MEM_WB_reg_write_request && MEM_WB_rd != 0 && MEM_WB_rd == ID_EXE_rs1)
                        ? MEM_WB_reg_write_data
                        : ID_EXE_read_reg_data1;

assign fwd_src2 = (EXE_MEM_reg_write_request && EXE_MEM_rd != 0 && EXE_MEM_rd == ID_EXE_rs2)
                    ? EXE_MEM_aluout
                    : (MEM_WB_reg_write_request && MEM_WB_rd != 0 && MEM_WB_rd == ID_EXE_rs2)
                        ? MEM_WB_reg_write_data
                        : ID_EXE_read_reg_data2;

wire [31:0] alu_src1, alu_src2, exe_aluout;
assign alu_src1 = fwd_src1;
assign alu_src2 = ID_EXE_imm_enable ? ID_EXE_immext : fwd_src2;

ALU alu(
    .alu_op(ID_EXE_alu_op),
    .src1(alu_src1),
    .src2(alu_src2),
    .aluout(exe_aluout)
);

always @ (posedge clk) begin
    EXE_MEM_aluout <= exe_aluout;
    EXE_MEM_rd <= ID_EXE_rd;
    EXE_MEM_write_data <= fwd_src2;
    EXE_MEM_reg_write_request <= ID_EXE_reg_write_request;
    EXE_MEM_mem_write_request <= ID_EXE_mem_write_request;
    EXE_MEM_mem_read_request <= ID_EXE_mem_read_request;
end

/* === MEM Stage === */
assign core2mem_write_request = EXE_MEM_mem_write_request;
assign core2mem_access_address = EXE_MEM_aluout;
assign core2mem_write_data = EXE_MEM_write_data;

always @ (posedge clk) begin
    MEM_WB_reg_write_request <= EXE_MEM_reg_write_request;
    MEM_WB_rd <= EXE_MEM_rd;
    MEM_WB_reg_write_data <= (EXE_MEM_mem_read_request) ? mem2core_read_data : EXE_MEM_aluout;
end

endmodule

src/haconiwa_top.v
module HACONIWA_TOP(
    input   CLOCK_50_B5B, CPU_RESET_n
);

wire [31:0] pc, instr, core2mem_access_address, mem2core_read_data, core2mem_write_data;
wire core2mem_write_request;

HACONIWA_CORE hcore(
    .clk(CLOCK_50_B5B),
    .reset(!CPU_RESET_n),
    .pc(pc),
    .instr(instr),
    .core2mem_access_address(core2mem_access_address),
    .mem2core_read_data(mem2core_read_data),
    .core2mem_write_data(core2mem_write_data),
    .core2mem_write_request(core2mem_write_request)
);

IMEM imem(
    .addr(pc),
    .instr(instr)
);

DMEM dmem(
    .clk(CLOCK_50_B5B),
    .access_address(core2mem_access_address),
    .read_data(mem2core_read_data),
    .write_data(core2mem_write_data),
    .write_request(core2mem_write_request)
);

endmodule

module SIMTOP();
    reg clk, reset;

    HACONIWA_TOP htop(
        .CLOCK_50_B5B(clk),
        .CPU_RESET_n(!reset)
    );

    initial begin
        clk = 0;
        forever #5 clk = ~clk;
    end

    initial begin
        #10 reset = 1;
        #20 reset = 0;
        $dumpfile("sim_top_haconiwa.vcd");
        $dumpvars(0, htop);

        #2000 $finish;
    end
endmodule

test/sim_top_haconiwa.vcd
$date
	Fri May  2 16:03:11 2025
$end
$version
	Icarus Verilog
$end
$timescale
	1s
$end
$scope module SIMTOP $end
$scope module htop $end
$var wire 1 ! CLOCK_50_B5B $end
$var wire 1 " CPU_RESET_n $end
$var wire 32 # pc [31:0] $end
$var wire 32 $ mem2core_read_data [31:0] $end
$var wire 32 % instr [31:0] $end
$var wire 1 & core2mem_write_request $end
$var wire 32 ' core2mem_write_data [31:0] $end
$var wire 32 ( core2mem_access_address [31:0] $end
$scope module dmem $end
$var wire 1 ! clk $end
$var wire 32 ) read_data [31:0] $end
$var wire 1 & write_request $end
$var wire 32 * write_data [31:0] $end
$var wire 32 + access_address [31:0] $end
$var integer 32 , i [31:0] $end
$upscope $end
$scope module hcore $end
$var wire 32 - alu_src1 [31:0] $end
$var wire 1 ! clk $end
$var wire 32 . core2mem_access_address [31:0] $end
$var wire 32 / core2mem_write_data [31:0] $end
$var wire 1 & core2mem_write_request $end
$var wire 1 0 load_use_hazard $end
$var wire 32 1 mem2core_read_data [31:0] $end
$var wire 1 2 reset $end
$var wire 5 3 rs2 [4:0] $end
$var wire 5 4 rs1 [4:0] $end
$var wire 32 5 read_reg_data2 [31:0] $end
$var wire 32 6 read_reg_data1 [31:0] $end
$var wire 5 7 rd [4:0] $end
$var wire 32 8 instr [31:0] $end
$var wire 32 9 immext [31:0] $end
$var wire 32 : fwd_src2 [31:0] $end
$var wire 32 ; fwd_src1 [31:0] $end
$var wire 32 < exe_aluout [31:0] $end
$var wire 1 = dec_reg_write_request $end
$var wire 1 > dec_mem_write_request $end
$var wire 1 ? dec_mem_read_request $end
$var wire 1 @ dec_imm_enable $end
$var wire 32 A alu_src2 [31:0] $end
$var wire 4 B alu_op [3:0] $end
$var reg 32 C EXE_MEM_aluout [31:0] $end
$var reg 1 D EXE_MEM_mem_read_request $end
$var reg 1 E EXE_MEM_mem_write_request $end
$var reg 5 F EXE_MEM_rd [4:0] $end
$var reg 1 G EXE_MEM_reg_write_request $end
$var reg 32 H EXE_MEM_write_data [31:0] $end
$var reg 4 I ID_EXE_alu_op [3:0] $end
$var reg 1 J ID_EXE_imm_enable $end
$var reg 32 K ID_EXE_immext [31:0] $end
$var reg 1 L ID_EXE_mem_read_request $end
$var reg 1 M ID_EXE_mem_write_request $end
$var reg 5 N ID_EXE_rd [4:0] $end
$var reg 32 O ID_EXE_read_reg_data1 [31:0] $end
$var reg 32 P ID_EXE_read_reg_data2 [31:0] $end
$var reg 1 Q ID_EXE_reg_write_request $end
$var reg 5 R ID_EXE_rs1 [4:0] $end
$var reg 5 S ID_EXE_rs2 [4:0] $end
$var reg 32 T IF_ID_instr [31:0] $end
$var reg 5 U MEM_WB_rd [4:0] $end
$var reg 32 V MEM_WB_reg_write_data [31:0] $end
$var reg 1 W MEM_WB_reg_write_request $end
$var reg 32 X pc [31:0] $end
$var reg 1 Y stall $end
$scope module alu $end
$var wire 4 Z alu_op [3:0] $end
$var wire 32 [ src1 [31:0] $end
$var wire 32 \ src2 [31:0] $end
$var reg 32 ] aluout [31:0] $end
$upscope $end
$scope module dec $end
$var wire 32 ^ instr [31:0] $end
$var wire 7 _ opcode [6:0] $end
$var reg 4 ` alu_op [3:0] $end
$var reg 1 a debug_isload $end
$var reg 1 b debug_isstore $end
$var reg 3 c funct3 [2:0] $end
$var reg 7 d funct7 [6:0] $end
$var reg 1 @ imm_enable $end
$var reg 32 e immext [31:0] $end
$var reg 1 ? mem_read_request $end
$var reg 1 > mem_write_request $end
$var reg 5 f rd [4:0] $end
$var reg 1 = reg_write_request $end
$var reg 5 g rs1 [4:0] $end
$var reg 5 h rs2 [4:0] $end
$upscope $end
$scope module regfile $end
$var wire 1 ! clk $end
$var wire 5 i read_address1 [4:0] $end
$var wire 5 j read_address2 [4:0] $end
$var wire 5 k write_address [4:0] $end
$var wire 32 l write_data [31:0] $end
$var wire 1 W write_request $end
$var wire 32 m read_data2 [31:0] $end
$var wire 32 n read_data1 [31:0] $end
$var integer 32 o i [31:0] $end
$upscope $end
$upscope $end
$scope module imem $end
$var wire 32 p addr [31:0] $end
$var wire 32 q instr [31:0] $end
$upscope $end
$upscope $end
$upscope $end
$enddefinitions $end
$comment Show the parameter values. $end
$dumpall
$end
#30
$dumpvars
b10011 q
b0 p
b100000 o
bx n
bx m
bx l
b0 k
bx j
bx i
bx h
bx g
bx f
bx e
bx d
bx c
xb
xa
bx `
bx _
bx ^
bx ]
bx \
bx [
bx Z
xY
b0 X
0W
bx V
b0 U
bx T
bx S
bx R
xQ
bx P
bx O
bx N
xM
xL
bx K
xJ
bx I
bx H
xG
bx F
xE
xD
bx C
bx B
bx A
x@
x?
x>
x=
bx <
bx ;
bx :
bx 9
b10011 8
bx 7
bx 6
bx 5
bx 4
bx 3
02
bx 1
x0
bx /
bx .
bx -
b100000 ,
bx +
bx *
bx )
bx (
bx '
x&
b10011 %
bx $
b0 #
1"
0!
$end
#35
0Y
00
bx U
bx k
xW
0J
0L
0M
0Q
b0 S
b0 R
b0 N
b0 P
b0 O
b0 K
b0 I
b0 Z
1!
#40
0!
#45
xY
x0
b0 6
b0 n
b0 B
b0 `
b0 4
b0 g
b0 i
b0 7
b0 f
b0 9
b0 e
b0 c
0b
0a
1@
0?
0>
1=
b10011 _
b10011 T
b10011 ^
b100 #
b100 X
b100 p
xJ
xL
xM
xQ
bx S
bx R
bx N
bx P
bx O
bx K
bx I
bx Z
0D
0&
0E
0G
b0 F
1!
#50
0!
#55
0Y
00
b0 U
b0 k
0W
xD
x&
xE
xG
bx F
0J
0L
0M
0Q
b0 S
b0 R
b0 N
b0 P
b0 O
b0 K
b0 I
b0 Z
1!
#60
0!
#65
bx <
bx ]
bx -
bx [
bx ;
b0 A
b0 \
b1000 #
b1000 X
b1000 p
1J
1Q
bx S
bx P
0D
0&
0E
0G
b0 F
bx U
bx k
xW
1!
#70
0!
#75
b0 <
b0 ]
b0 -
b0 [
b0 ;
b0 U
b0 k
0W
1G
b1100 #
b1100 X
b1100 p
1!
#80
0!
#85
b0 $
b0 )
b0 1
b10000 #
b10000 X
b10000 p
b0 (
b0 +
b0 .
b0 C
1W
1!
#90
0!
#95
b0 V
b0 l
b10100 #
b10100 X
b10100 p
1!
#100
0!
#105
b10100000000000010010011 %
b10100000000000010010011 8
b10100000000000010010011 q
b11000 #
b11000 X
b11000 p
1!
#110
0!
#115
b101 9
b101 e
b0 4
b0 g
b0 i
b1 7
b1 f
b0 c
1@
1=
b101000000000000100010011 %
b101000000000000100010011 8
b101000000000000100010011 q
b10100000000000010010011 T
b10100000000000010010011 ^
b11100 #
b11100 X
b11100 p
1!
#120
0!
#125
b101 <
b101 ]
b1010 9
b1010 e
b0 4
b0 g
b0 i
b10 7
b10 f
b0 c
1@
1=
b1000001000000110110011 %
b1000001000000110110011 8
b1000001000000110110011 q
b101 A
b101 \
b101000000000000100010011 T
b101000000000000100010011 ^
b100000 #
b100000 X
b100000 p
b1 N
b101 K
1!
#130
0!
#135
b1010 <
b1010 ]
b0 5
b0 m
b1010 A
b1010 \
b10 3
b10 h
b10 j
b0 d
bx 9
bx e
b1 4
b1 g
b1 i
b11 7
b11 f
b0 c
0@
1=
b110011 _
b1100000010001000100011 %
b1100000010001000100011 8
b1100000010001000100011 q
b1 F
b101 (
b101 +
b101 .
b101 C
b10 N
b1010 K
b1000001000000110110011 T
b1000001000000110110011 ^
b100100 #
b100100 X
b100100 p
1!
#140
0!
#145
b1111 <
b1111 ]
b101 -
b101 [
b101 ;
1>
b1010 :
1b
1@
b100 9
b100 e
b11 3
b11 h
b11 j
b0 4
b0 g
b0 i
bx 7
bx f
b10 c
b0 d
0=
b100011 _
b10000000000001000010011 %
b10000000000001000010011 8
b10000000000001000010011 q
b1010 A
b1010 \
b1100000010001000100011 T
b1100000010001000100011 ^
b101000 #
b101000 X
b101000 p
0J
b10 S
b1 R
b11 N
b0 P
bx K
b10 F
b1010 (
b1010 +
b1010 .
b1010 C
b101 V
b101 l
b1 U
b1 k
1!
#150
0!
#155
b100 <
b100 ]
bx 5
bx m
b0 -
b0 [
b0 ;
b1111 :
b100 A
b100 \
1=
b100 7
b100 f
0b
b100 9
b100 e
bx 3
bx h
bx j
b0 4
b0 g
b0 i
b0 c
bx d
1@
0>
b10011 _
b100010001010000011 %
b100010001010000011 8
b100010001010000011 q
b1010 V
b1010 l
b10 U
b10 k
b1010 '
b1010 *
b1010 /
b1010 H
b11 F
b1111 (
b1111 +
b1111 .
b1111 C
1J
1M
0Q
b11 S
b0 R
bx N
b100 K
b10000000000001000010011 T
b10000000000001000010011 ^
b101100 #
b101100 X
b101100 p
1!
#160
0!
#165
b100 <
b100 ]
1a
1?
b0 -
b0 [
b0 ;
b0 9
b0 e
b100 4
b100 g
b100 i
b101 7
b101 f
b10 c
1@
1=
b11 _
b10100001000001100110011 %
b10100001000001100110011 8
b10100001000001100110011 q
bx :
b100010001010000011 T
b100010001010000011 ^
b110000 #
b110000 X
b110000 p
0M
1Q
bx S
b100 N
bx P
1&
1E
0G
b1111 '
b1111 *
b1111 /
b1111 H
bx F
b100 (
b100 +
b100 .
b100 C
b1111 V
b1111 l
b11 U
b11 k
1!
#170
0!
#175
b100 <
b100 ]
b100 -
b100 [
b100 ;
b0 5
b0 m
b101 6
b101 n
1Y
10
b0 A
b0 \
b101 3
b101 h
b101 j
b0 d
0a
bx 9
bx e
b1 4
b1 g
b1 i
b110 7
b110 f
b0 c
0@
0?
1=
b110011 _
bx %
bx 8
bx q
b1111 $
b1111 )
b1111 1
b100 V
b100 l
bx U
bx k
0W
0&
0E
1G
bx '
bx *
bx /
bx H
b100 F
1L
b100 R
b101 N
b0 K
b10100001000001100110011 T
b10100001000001100110011 ^
b110100 #
b110100 X
b110100 p
1!
#180
0!
#185
b0 <
b0 ]
0Y
b0 :
b0 -
b0 [
b0 ;
b0 A
b0 \
00
0J
0L
0Q
b0 S
b0 R
b0 N
b0 P
1D
b101 F
b100 U
b100 k
1W
1!
#190
0!
#195
b10100 <
b10100 ]
b1111 A
b1111 \
b1111 :
bx 5
bx m
bx 6
bx n
b101 -
b101 [
b101 ;
bx B
bx `
b0 $
b0 )
b0 1
bx 3
bx h
bx j
bx 4
bx g
bx i
bx 7
bx f
bx c
bx d
0=
bx _
b1111 V
b1111 l
b101 U
b101 k
0D
0G
b0 '
b0 *
b0 /
b0 H
b0 F
b0 (
b0 +
b0 .
b0 C
1Q
b101 S
b1 R
b110 N
b101 O
bx K
bx T
bx ^
b111000 #
b111000 X
b111000 p
1!
#200
0!
#205
bx A
bx \
bx -
bx [
bx ;
bx :
b111100 #
b111100 X
b111100 p
0Q
bx S
bx R
bx N
bx P
bx O
bx I
bx Z
1G
b1111 '
b1111 *
b1111 /
b1111 H
b110 F
b10100 (
b10100 +
b10100 .
b10100 C
b0 V
b0 l
b0 U
b0 k
0W
1!
#210
0!
#215
b10100 V
b10100 l
b110 U
b110 k
1W
0G
bx '
bx *
bx /
bx H
bx F
b1000000 #
b1000000 X
b1000000 p
1!
#220
0!
#225
b1000100 #
b1000100 X
b1000100 p
bx U
bx k
0W
1!
#230
0!
#235
b1001000 #
b1001000 X
b1001000 p
1!
#240
0!
#245
b1001100 #
b1001100 X
b1001100 p
1!
#250
0!
#255
b1010000 #
b1010000 X
b1010000 p
1!
#260
0!
#265
b1010100 #
b1010100 X
b1010100 p
1!
#270
0!
#275
b1011000 #
b1011000 X
b1011000 p
1!
#280
0!
#285
b1011100 #
b1011100 X
b1011100 p
1!
#290
0!
#295
b1100000 #
b1100000 X
b1100000 p
1!
#300
0!
#305
b1100100 #
b1100100 X
b1100100 p
1!
#310
0!
#315
b1101000 #
b1101000 X
b1101000 p
1!
#320
0!
#325
b1101100 #
b1101100 X
b1101100 p
1!
#330
0!
#335
b1110000 #
b1110000 X
b1110000 p
1!
#340
0!
#345
b1110100 #
b1110100 X
b1110100 p
1!
#350
0!
#355
b1111000 #
b1111000 X
b1111000 p
1!
#360
0!
#365
b1111100 #
b1111100 X
b1111100 p
1!
#370
0!
#375
b10000000 #
b10000000 X
b10000000 p
1!
#380
0!
#385
b10000100 #
b10000100 X
b10000100 p
1!
#390
0!
#395
b10001000 #
b10001000 X
b10001000 p
1!
#400
0!
#405
b10001100 #
b10001100 X
b10001100 p
1!
#410
0!
#415
b10010000 #
b10010000 X
b10010000 p
1!
#420
0!
#425
b10010100 #
b10010100 X
b10010100 p
1!
#430
0!
#435
b10011000 #
b10011000 X
b10011000 p
1!
#440
0!
#445
b10011100 #
b10011100 X
b10011100 p
1!
#450
0!
#455
b10100000 #
b10100000 X
b10100000 p
1!
#460
0!
#465
b10100100 #
b10100100 X
b10100100 p
1!
#470
0!
#475
b10101000 #
b10101000 X
b10101000 p
1!
#480
0!
#485
b10101100 #
b10101100 X
b10101100 p
1!
#490
0!
#495
b10110000 #
b10110000 X
b10110000 p
1!
#500
0!
#505
b10110100 #
b10110100 X
b10110100 p
1!
#510
0!
#515
b10111000 #
b10111000 X
b10111000 p
1!
#520
0!
#525
b10111100 #
b10111100 X
b10111100 p
1!
