src/dmem_iverilog.v
`define DRAM_depth 4096

module DMEM(
    input           clk, write_request,
    input   [31:0]  access_address, write_data,
    output  [31:0]  read_data
);

reg [31:0] RAM[0:`DRAM_depth-1];

assign read_data = RAM[access_address[31:2]];

always @ (posedge clk) begin
    if (write_request) begin
        RAM[access_address[31:2]] <= write_data;
    end
end

/* データメモリの初期化(シミュレーション用) */
integer i;
initial begin
    for (i = 0; i < `DRAM_depth; i = i + 1) begin
        RAM[i] = 32'b0;
    end
end

endmodule

src/imem_iverilog.v
`define MEMDATA "memory.data"

module IMEM(
    input   [31:0]  addr,
    output  [31:0]  instr
);

reg [31:0]  ROM[63:0];

initial begin
    $readmemh(`MEMDATA, ROM, 0, 63);
end

assign  instr = ROM[addr[31:2]];    // pc <= pc + 32'h4;に対応

endmodule

src/alu.v
module ALU(
    input       [3:0]   alu_op,
    input       [31:0]  src1,
    input       [31:0]  src2,
    output reg  [31:0]  aluout
);

always @* begin
    case (alu_op)
        4'b0000,
        4'b1010:
        begin
            aluout <= src1 + src2;  // add, addi
        end
        4'b0001: aluout = src1 - src2;  // sub
        4'b0010: aluout = src1 & src2;  // and
        4'b0011: aluout = src1 | src2;  // or
        4'b0100: aluout = src1 ^ src2;  // xor
        4'b1100: aluout = (src1 == src2) ? 32'b1 : 32'b0; // beq
        4'b1101: aluout = (src1 != src2) ? 32'b1 : 32'b0; // bne
        4'b1110: aluout = ($signed(src1) < $signed(src2)) ? 32'b1 : 32'b0; // blt, slt
        4'b1111: aluout = ($signed(src1) >= $signed(src2)) ? 32'b1 : 32'b0; // bge
    endcase
end

endmodule

src/regfile.v
module REGFILE(
    input clk,
    input write_request,
    input   [4:0] write_address,
    input   [4:0] read_address1,
    input   [4:0] read_address2,
    input  [31:0] write_data,
    output  [31:0] read_data1,
    output  [31:0] read_data2
);

reg [31:0] register_file [31:0];

always @ (posedge clk) begin
    if (write_request) register_file[write_address] <= write_data;
end

/* レジスタの初期化(シミュレーション用) */
integer i;
initial begin
    for (i = 0; i < 32; i = i + 1) begin
        register_file[i] = 32'b0;
    end
end

assign read_data1 = (read_address1 != 0) ? register_file[read_address1] : 0;
assign read_data2 = (read_address2 != 0) ? register_file[read_address2] : 0;

endmodule

src/decoder.v
module DECODER(
    input       [31:0]  instr,
    output reg  [3:0]   alu_op,
    output reg  [31:0]  immext,
    output reg  [4:0]   rd, rs1, rs2,
    output reg          reg_write_request,
    output reg          mem_write_request,
    output reg          mem_read_request,
    output reg          imm_enable,
    output reg  [2:0]   branch_type,
    output reg          is_branch,
    output reg          is_jal,
    output reg          is_jalr
);

    wire [6:0] opcode = instr[6:0];
    reg [6:0] funct7;
    reg [2:0] funct3;

    // 初期化（デフォルト値設定）
    always @* begin
        reg_write_request = 1'b0;
        mem_write_request = 1'b0;
        mem_read_request  = 1'b0;
        imm_enable        = 1'b0;
        funct7            = 7'bx;
        funct3            = 3'bx;
        rd                = 5'bx;
        rs1               = 5'bx;
        rs2               = 5'bx;
        immext            = 32'bx;
        is_branch         = 1'b0;
        branch_type      = 3'b0;
        is_jal            = 1'b0;
        is_jalr           = 1'b0;

        case (opcode)
            /* R-type */
            7'b0110011: begin
                funct7          = instr[31:25];
                funct3          = instr[14:12];
                immext          = 32'bx;
                rd              = instr[11:7];
                rs1             = instr[19:15];
                rs2             = instr[24:20];
                reg_write_request = 1'b1;
                imm_enable      = 1'b0;
                is_branch         = 1'b0;
                branch_type      = 3'bx;
            end

            /* I-type */
            7'b0010011, // addi, ori
            7'b0000011: // lw
            begin
                funct7          = 7'bx;
                funct3          = instr[14:12];
                immext          = {{20{instr[31]}}, instr[31:20]};
                rd              = instr[11:7];
                rs1             = instr[19:15];
                rs2             = 5'bx;
                reg_write_request = 1'b1;
                imm_enable      = 1'b1;
                is_branch         = 1'b0;
                branch_type      = 3'bx;
            end

            /* S-type */
            7'b0100011: // sw
            begin
                funct7          = instr[31:25];
                funct3          = instr[14:12];
                immext          = {{20{instr[31]}}, instr[31:25], instr[11:7]};
                rd              = 5'bx;
                rs1             = instr[19:15];
                rs2             = instr[24:20];
                reg_write_request = 1'b0;
                imm_enable          = 1'b1;
                is_branch         = 1'b0;
                branch_type      = 3'bx;
            end

            /* B-type */
            7'b1100011: begin // branch instructions
                funct3          = instr[14:12];
                immext          = {{20{instr[31]}}, instr[7], instr[30:25], instr[11:8], 1'b0}; // B型即値
                rd              = 5'bx;
                rs1             = instr[19:15];
                rs2             = instr[24:20];
                reg_write_request = 1'b0;
                imm_enable      = 1'b0;
                is_branch         = 1'b1;
            end

            /* U-type */
            7'b0110111,  // LUI
            7'b0010111: begin  // AUIPC
                funct7          = 7'bx;
                funct3          = 3'bx;
                immext          = {instr[31:12], 12'b0};
                rd              = instr[11:7];
                rs1             = 5'b0;
                rs2             = 5'b0;
                reg_write_request = 1'b1;
                imm_enable         = 1'b1;
                is_branch         = 1'b0;
                branch_type      = 3'bx;
            end

            /* J-type */
            7'b1101111: begin // jal
                funct7           = 7'bx;
                funct3           = 3'bx;
                immext           = {{12{instr[31]}}, instr[19:12], instr[20], instr[30:21], 1'b0}; // J型即値
                rd               = instr[11:7];
                rs1              = 5'bx;
                rs2              = 5'bx;
                reg_write_request = 1'b1;
                imm_enable        = 1'b1;
                is_branch         = 1'b0;
                is_jal            = 1'b1;
                is_jalr           = 1'b0;
                branch_type       = 3'bx;
            end
            7'b1100111: begin // jalr
                funct7           = 7'bx;
                funct3           = instr[14:12];
                immext           = {{20{instr[31]}}, instr[31:20]};
                rd               = instr[11:7];
                rs1              = instr[19:15];
                rs2              = 5'bx;
                reg_write_request = 1'b1;
                imm_enable        = 1'b1;
                is_branch         = 1'b0;
                is_jal            = 1'b0;
                is_jalr           = 1'b1;
                branch_type       = 3'bx;
            end

            default: begin
                funct7          = 7'bx;
                funct3          = 3'bx;
                immext          = 32'bx;
                rd              = 5'bx;
                rs1             = 5'bx;
                rs2             = 5'bx;
                is_branch         = 1'b0;
                branch_type      = 3'bx;
            end
        endcase
    end

    // ALU operation decoding
    always @* begin
        case (funct3)
            3'b000: begin
                if (opcode == 7'b0110011) // R-type
                begin
                    case (funct7)
                        7'b0000000: alu_op = 4'b0000;  // add
                        7'b0100000: alu_op = 4'b0001;  // sub
                        default:    alu_op = 4'bx;
                    endcase
                end
                else if (opcode == 7'b0010011) // I-type (addi)
                begin
                    alu_op = 4'b0000;   // addi
                end
                else begin
                    alu_op = 4'bx;
                end
            end

            3'b001: alu_op = 4'b0010;  // sll
            3'b010: begin
                case (opcode)
                    7'b0000011: begin // lw
                        alu_op = 4'b0000; // addでアドレス計算
                        reg_write_request = 1;
                        mem_read_request  = 1;
                    end
                    7'b0100011: begin // sw
                        alu_op = 4'b0000;
                        mem_write_request = 1;
                    end
                    7'b0110011: begin // slt
                        alu_op = 4'b1110;
                        mem_write_request = 1'b0;
                        mem_read_request = 1'b0;
                    end
                    default: alu_op = 4'bx;
                endcase
            end

            3'b011: alu_op = 4'b0100;  // sltu
            3'b100: alu_op = 4'b0101;  // xor
            3'b101: begin
                case (funct7)
                    7'b0000000: alu_op = 4'b0110;  // srl
                    7'b0100000: alu_op = 4'b0111;  // sra
                    default:    alu_op = 4'bx;
                endcase
            end
            3'b110: alu_op = 4'b1000;  // ori
            3'b111: alu_op = 4'b1001;  // and
            default: alu_op = 4'bx;
        endcase
        if (opcode == 7'b1100011) begin
            case (funct3)
                3'b000: begin
                    alu_op = 4'b1100; // beq
                    branch_type = 3'b000;
                end
                3'b001: begin
                    alu_op = 4'b1101; // bne
                    branch_type = 3'b001;
                end
                3'b100: begin
                    alu_op = 4'b1110; // blt
                    branch_type = 3'b100;
                end
                3'b101: begin
                    alu_op = 4'b1111; // bge
                    branch_type = 3'b101;
                end
            endcase
        end else if (opcode == 7'b0110111) begin
            alu_op = 4'b1011;   // lui
        end else if (opcode == 7'b0010111) begin
            alu_op = 4'b0000;    // auipc
        end
    end

endmodule

src/haconiwa_core.v
module HACONIWA_CORE(
    input               clk,
    input               reset,
    output reg  [31:0]  pc,
    input       [31:0]  instr,
    output      [31:0]  core2mem_access_address,
    input       [31:0]  mem2core_read_data,
    output      [31:0]  core2mem_write_data,
    output              core2mem_write_request
);

/* === Pipeline Registers === */
reg         stall, flush;

reg [31:0]  IF_ID_pc, IF_ID_instr;

reg [3:0]   ID_EXE_alu_op;
reg [2:0]   ID_EXE_branch_type;
reg [31:0]  ID_EXE_pc, next_pc, ID_EXE_immext, ID_EXE_read_reg_data1, ID_EXE_read_reg_data2;
reg [4:0]   ID_EXE_rd, ID_EXE_rs1, ID_EXE_rs2;
reg         ID_EXE_reg_write_request, ID_EXE_mem_write_request, ID_EXE_mem_read_request, ID_EXE_imm_enable, ID_EXE_is_branch, ID_EXE_is_jal, ID_EXE_is_jalr;

reg [4:0]   EXE_MEM_rd;
reg [31:0]  EXE_MEM_pc, EXE_MEM_aluout, EXE_MEM_mem_write_data;
reg         EXE_MEM_reg_write_request, EXE_MEM_mem_write_request, EXE_MEM_mem_read_request, EXE_MEM_is_jal, EXE_MEM_is_jalr;

reg         MEM_WB_reg_write_request;
reg [4:0]   MEM_WB_rd;
reg [31:0]  MEM_WB_reg_write_data;

/* === IF Stage === */
always @* begin
    if (flush) begin
        if (ID_EXE_is_jalr) begin
            next_pc = (ID_EXE_read_reg_data1 + ID_EXE_immext) & ~32'b1;
        end else if (ID_EXE_is_jal) begin
            next_pc = ID_EXE_pc + ID_EXE_immext;
        end else begin
            next_pc = ID_EXE_pc + ID_EXE_immext;
        end
    end else begin
        next_pc = pc + 4;
    end
end

always @ (posedge clk) begin
    if (reset) begin
        pc <= 32'h0;
    end else if (!stall) begin
        pc <= next_pc;
        IF_ID_pc <= pc;
        IF_ID_instr <= (flush) ? 32'h00000013 : instr;  // flushがexeされた場合に2つ後の命令をnop化
    end
end

/* === ID Stage === */
wire [3:0] alu_op;
wire [31:0] immext, read_reg_data1, read_reg_data2;
wire [4:0] rd, rs1, rs2;
wire [2:0] dec_branch_type;
wire dec_reg_write_request, dec_mem_write_request, dec_mem_read_request, dec_imm_enable, dec_is_branch, dec_is_jal, dec_is_jalr;

DECODER dec(
    .instr(IF_ID_instr),
    .alu_op(alu_op),
    .rd(rd),
    .rs1(rs1),
    .rs2(rs2),
    .immext(immext),
    .imm_enable(dec_imm_enable),
    .reg_write_request(dec_reg_write_request),
    .mem_write_request(dec_mem_write_request),
    .mem_read_request(dec_mem_read_request),
    .branch_type(dec_branch_type),
    .is_branch(dec_is_branch),
    .is_jal(dec_is_jal),
    .is_jalr(dec_is_jalr)
);

REGFILE regfile(
    .clk(clk),
    .read_address1(rs1),
    .read_address2(rs2),
    .read_data1(read_reg_data1),
    .read_data2(read_reg_data2),
    .write_request(MEM_WB_reg_write_request),
    .write_address(MEM_WB_rd),
    .write_data(MEM_WB_reg_write_data)
);

wire [31:0] id_fwd_src1, id_fwd_src2;
assign id_fwd_src1 = (MEM_WB_reg_write_request && MEM_WB_rd != 0 && MEM_WB_rd == rs1)
                        ? MEM_WB_reg_write_data : read_reg_data1;
assign id_fwd_src2 = (MEM_WB_reg_write_request && MEM_WB_rd != 0 && MEM_WB_rd == rs2)
                        ? MEM_WB_reg_write_data : read_reg_data2;

always @ (posedge clk) begin
    if (!stall && !flush) begin // flushがexeされた場合に既にとりこんだ1つ後の命令をnop化
        ID_EXE_pc                   <= IF_ID_pc;
        ID_EXE_alu_op               <= alu_op;
        ID_EXE_immext               <= immext;
        ID_EXE_read_reg_data1       <= id_fwd_src1;
        ID_EXE_read_reg_data2       <= id_fwd_src2;
        ID_EXE_rd                   <= rd;
        ID_EXE_rs1                  <= rs1;
        ID_EXE_rs2                  <= rs2;
        ID_EXE_reg_write_request    <= dec_reg_write_request;
        ID_EXE_mem_write_request    <= dec_mem_write_request;
        ID_EXE_mem_read_request     <= dec_mem_read_request;
        ID_EXE_imm_enable           <= dec_imm_enable;
        ID_EXE_branch_type          <= dec_branch_type;
        ID_EXE_is_branch            <= dec_is_branch;
        ID_EXE_is_jal               <= dec_is_jal;
        ID_EXE_is_jalr              <= dec_is_jalr;
    end else begin
        ID_EXE_pc                   <= 32'b0;
        ID_EXE_alu_op               <= 4'b0;
        ID_EXE_immext               <= 32'b0;
        ID_EXE_read_reg_data1       <= 32'b0;
        ID_EXE_read_reg_data2       <= 32'b0;
        ID_EXE_rd                   <= 5'b0;
        ID_EXE_rs1                  <= 5'b0;
        ID_EXE_rs2                  <= 5'b0;
        ID_EXE_reg_write_request    <= 1'b0;
        ID_EXE_mem_write_request    <= 1'b0;
        ID_EXE_mem_read_request     <= 1'b0;
        ID_EXE_imm_enable           <= 1'b0;
        ID_EXE_branch_type          <= 1'b0; 
        ID_EXE_is_branch            <= 1'b0;
        ID_EXE_is_jal               <= 1'b0;
        ID_EXE_is_jalr              <= 1'b0;
    end
end

// load-use hazard detection
wire load_use_hazard;
assign load_use_hazard = (ID_EXE_mem_read_request &&
                            ((ID_EXE_rd == rs1 && ID_EXE_rd != 0) ||
                            (ID_EXE_rd == rs2 && ID_EXE_rd != 0)));
always @* begin
    if (reset) begin
        stall = 1'b0;
    end else begin
        stall = load_use_hazard;
    end
end

/* === EXE Stage === */
wire [31:0] exe_fwd_src1, exe_fwd_src2;
assign exe_fwd_src1 = (EXE_MEM_reg_write_request && EXE_MEM_rd != 0 && EXE_MEM_rd == ID_EXE_rs1)
                    ? EXE_MEM_aluout
                    : (MEM_WB_reg_write_request && MEM_WB_rd != 0 && MEM_WB_rd == ID_EXE_rs1)
                        ? MEM_WB_reg_write_data
                        : ID_EXE_read_reg_data1;

assign exe_fwd_src2 = (EXE_MEM_reg_write_request && EXE_MEM_rd != 0 && EXE_MEM_rd == ID_EXE_rs2)
                    ? EXE_MEM_aluout
                    : (MEM_WB_reg_write_request && MEM_WB_rd != 0 && MEM_WB_rd == ID_EXE_rs2)
                        ? MEM_WB_reg_write_data
                        : ID_EXE_read_reg_data2;

wire [31:0] alu_src1, alu_src2, exe_aluout;
assign alu_src1 = exe_fwd_src1;
assign alu_src2 = ID_EXE_imm_enable ? ID_EXE_immext : exe_fwd_src2;

ALU alu(
    .alu_op(ID_EXE_alu_op),
    .src1(alu_src1),
    .src2(alu_src2),
    .aluout(exe_aluout)
);

wire branch_taken;
assign branch_taken = (ID_EXE_is_branch && (exe_aluout == 1'b1)) ? 1'b1 : 1'b0 ;
// assign branch_taken =   (ID_EXE_branch_type == 3'b000) ? (fwd_src1 == fwd_src2) :
//                         (ID_EXE_branch_type == 3'b001) ? (fwd_src1 != fwd_src2) :
//                         (ID_EXE_branch_type == 3'b100) ? (fwd_src1 < fwd_src2) :
//                         (ID_EXE_branch_type == 3'b101) ? (fwd_src1 >= fwd_src2) : 1'b0;

always @* begin
    flush = (ID_EXE_is_branch && branch_taken) || ID_EXE_is_jal || ID_EXE_is_jalr;
end

always @ (posedge clk) begin
    EXE_MEM_aluout <= exe_aluout;
    EXE_MEM_rd <= ID_EXE_rd;
    EXE_MEM_mem_write_data <= exe_fwd_src2;
    EXE_MEM_reg_write_request <= ID_EXE_reg_write_request;
    EXE_MEM_mem_write_request <= ID_EXE_mem_write_request;
    EXE_MEM_mem_read_request <= ID_EXE_mem_read_request;
    EXE_MEM_pc <= ID_EXE_pc;
    EXE_MEM_is_jal <= ID_EXE_is_jal;
    EXE_MEM_is_jalr <= ID_EXE_is_jalr;
end

/* === MEM Stage === */
assign core2mem_write_request = EXE_MEM_mem_write_request;
assign core2mem_access_address = EXE_MEM_aluout;
assign core2mem_write_data = EXE_MEM_mem_write_data;

always @ (posedge clk) begin
    MEM_WB_reg_write_request <= EXE_MEM_reg_write_request;
    MEM_WB_rd <= EXE_MEM_rd;
    MEM_WB_reg_write_data <=    (EXE_MEM_mem_read_request) ? mem2core_read_data :
                                (EXE_MEM_is_jal || EXE_MEM_is_jalr) ? EXE_MEM_pc + 32'h4 :
                                EXE_MEM_aluout;
end

endmodule

src/haconiwa_top.v
module HACONIWA_TOP(
    input           CLOCK_50_B5B, CPU_RESET_n,
    output  [31:0]  debug_pc
);

wire [31:0] pc, instr, core2mem_access_address, mem2core_read_data, core2mem_write_data;
wire core2mem_write_request;

HACONIWA_CORE hcore(
    .clk(CLOCK_50_B5B),
    .reset(!CPU_RESET_n),
    .pc(pc),
    .instr(instr),
    .core2mem_access_address(core2mem_access_address),
    .mem2core_read_data(mem2core_read_data),
    .core2mem_write_data(core2mem_write_data),
    .core2mem_write_request(core2mem_write_request)
);

IMEM imem(
    .addr(pc),
    .instr(instr)
);

DMEM dmem(
    .clk(CLOCK_50_B5B),
    .access_address(core2mem_access_address),
    .read_data(mem2core_read_data),
    .write_data(core2mem_write_data),
    .write_request(core2mem_write_request)
);

assign debug_pc = pc;

endmodule

module SIMTOP();
    reg         clk, reset;
    wire [31:0] debug_pc;

    HACONIWA_TOP htop(
        .CLOCK_50_B5B(clk),
        .CPU_RESET_n(!reset),
        .debug_pc(debug_pc)
    );

    initial begin
        clk = 0;
        forever #5 clk = ~clk;
    end

    initial begin
        #10 reset = 1;
        #20 reset = 0;
        $dumpfile("sim_top_haconiwa.vcd");
        $dumpvars(0, htop);

        #10000
        if (htop.dmem.RAM[32'h00000FFC >> 2] == 42)
            $display("passed");
        else begin
            $display("failed: got = %0d", htop.dmem.RAM[32'h00000FFC >> 2]);
        end

        $finish;
    end
endmodule

test/testrv32I/sim_top_haconiwa.vcd
$date
	Sat Jun 14 21:14:29 2025
$end
$version
	Icarus Verilog
$end
$timescale
	1s
$end
$scope module SIMTOP $end
$scope module htop $end
$var wire 1 ! CLOCK_50_B5B $end
$var wire 1 " CPU_RESET_n $end
$var wire 32 # debug_pc [31:0] $end
$var wire 32 $ pc [31:0] $end
$var wire 32 % mem2core_read_data [31:0] $end
$var wire 32 & instr [31:0] $end
$var wire 1 ' core2mem_write_request $end
$var wire 32 ( core2mem_write_data [31:0] $end
$var wire 32 ) core2mem_access_address [31:0] $end
$scope module dmem $end
$var wire 1 ! clk $end
$var wire 32 * read_data [31:0] $end
$var wire 1 ' write_request $end
$var wire 32 + write_data [31:0] $end
$var wire 32 , access_address [31:0] $end
$var integer 32 - i [31:0] $end
$upscope $end
$scope module hcore $end
$var wire 32 . alu_src1 [31:0] $end
$var wire 1 ! clk $end
$var wire 32 / core2mem_access_address [31:0] $end
$var wire 32 0 core2mem_write_data [31:0] $end
$var wire 1 ' core2mem_write_request $end
$var wire 1 1 load_use_hazard $end
$var wire 32 2 mem2core_read_data [31:0] $end
$var wire 1 3 reset $end
$var wire 5 4 rs2 [4:0] $end
$var wire 5 5 rs1 [4:0] $end
$var wire 32 6 read_reg_data2 [31:0] $end
$var wire 32 7 read_reg_data1 [31:0] $end
$var wire 5 8 rd [4:0] $end
$var wire 32 9 instr [31:0] $end
$var wire 32 : immext [31:0] $end
$var wire 32 ; id_fwd_src2 [31:0] $end
$var wire 32 < id_fwd_src1 [31:0] $end
$var wire 32 = exe_fwd_src2 [31:0] $end
$var wire 32 > exe_fwd_src1 [31:0] $end
$var wire 32 ? exe_aluout [31:0] $end
$var wire 1 @ dec_reg_write_request $end
$var wire 1 A dec_mem_write_request $end
$var wire 1 B dec_mem_read_request $end
$var wire 1 C dec_is_jalr $end
$var wire 1 D dec_is_jal $end
$var wire 1 E dec_is_branch $end
$var wire 1 F dec_imm_enable $end
$var wire 3 G dec_branch_type [2:0] $end
$var wire 1 H branch_taken $end
$var wire 32 I alu_src2 [31:0] $end
$var wire 4 J alu_op [3:0] $end
$var reg 32 K EXE_MEM_aluout [31:0] $end
$var reg 1 L EXE_MEM_is_jal $end
$var reg 1 M EXE_MEM_is_jalr $end
$var reg 1 N EXE_MEM_mem_read_request $end
$var reg 32 O EXE_MEM_mem_write_data [31:0] $end
$var reg 1 P EXE_MEM_mem_write_request $end
$var reg 32 Q EXE_MEM_pc [31:0] $end
$var reg 5 R EXE_MEM_rd [4:0] $end
$var reg 1 S EXE_MEM_reg_write_request $end
$var reg 4 T ID_EXE_alu_op [3:0] $end
$var reg 3 U ID_EXE_branch_type [2:0] $end
$var reg 1 V ID_EXE_imm_enable $end
$var reg 32 W ID_EXE_immext [31:0] $end
$var reg 1 X ID_EXE_is_branch $end
$var reg 1 Y ID_EXE_is_jal $end
$var reg 1 Z ID_EXE_is_jalr $end
$var reg 1 [ ID_EXE_mem_read_request $end
$var reg 1 \ ID_EXE_mem_write_request $end
$var reg 32 ] ID_EXE_pc [31:0] $end
$var reg 5 ^ ID_EXE_rd [4:0] $end
$var reg 32 _ ID_EXE_read_reg_data1 [31:0] $end
$var reg 32 ` ID_EXE_read_reg_data2 [31:0] $end
$var reg 1 a ID_EXE_reg_write_request $end
$var reg 5 b ID_EXE_rs1 [4:0] $end
$var reg 5 c ID_EXE_rs2 [4:0] $end
$var reg 32 d IF_ID_instr [31:0] $end
$var reg 32 e IF_ID_pc [31:0] $end
$var reg 5 f MEM_WB_rd [4:0] $end
$var reg 32 g MEM_WB_reg_write_data [31:0] $end
$var reg 1 h MEM_WB_reg_write_request $end
$var reg 1 i flush $end
$var reg 32 j next_pc [31:0] $end
$var reg 32 k pc [31:0] $end
$var reg 1 l stall $end
$scope module alu $end
$var wire 4 m alu_op [3:0] $end
$var wire 32 n src1 [31:0] $end
$var wire 32 o src2 [31:0] $end
$var reg 32 p aluout [31:0] $end
$upscope $end
$scope module dec $end
$var wire 32 q instr [31:0] $end
$var wire 7 r opcode [6:0] $end
$var reg 4 s alu_op [3:0] $end
$var reg 3 t branch_type [2:0] $end
$var reg 3 u funct3 [2:0] $end
$var reg 7 v funct7 [6:0] $end
$var reg 1 F imm_enable $end
$var reg 32 w immext [31:0] $end
$var reg 1 E is_branch $end
$var reg 1 D is_jal $end
$var reg 1 C is_jalr $end
$var reg 1 B mem_read_request $end
$var reg 1 A mem_write_request $end
$var reg 5 x rd [4:0] $end
$var reg 1 @ reg_write_request $end
$var reg 5 y rs1 [4:0] $end
$var reg 5 z rs2 [4:0] $end
$upscope $end
$scope module regfile $end
$var wire 1 ! clk $end
$var wire 5 { read_address1 [4:0] $end
$var wire 5 | read_address2 [4:0] $end
$var wire 5 } write_address [4:0] $end
$var wire 32 ~ write_data [31:0] $end
$var wire 1 h write_request $end
$var wire 32 !" read_data2 [31:0] $end
$var wire 32 "" read_data1 [31:0] $end
$var integer 32 #" i [31:0] $end
$upscope $end
$upscope $end
$scope module imem $end
$var wire 32 $" addr [31:0] $end
$var wire 32 %" instr [31:0] $end
$upscope $end
$upscope $end
$upscope $end
$enddefinitions $end
$comment Show the parameter values. $end
$dumpall
$end
#30
$dumpvars
b10011 %"
b0 $"
b100000 #"
bx ""
bx !"
bx ~
b0 }
bx |
bx {
bx z
bx y
bx x
bx w
bx v
bx u
bx t
bx s
bx r
bx q
bx p
bx o
bx n
b0 m
0l
b0 k
b100 j
0i
0h
bx g
b0 f
bx e
bx d
b0 c
b0 b
0a
b0 `
b0 _
b0 ^
b0 ]
0\
0[
0Z
0Y
0X
b0 W
0V
b0 U
b0 T
xS
bx R
bx Q
xP
bx O
xN
xM
xL
bx K
bx J
bx I
0H
bx G
xF
xE
xD
xC
xB
xA
x@
bx ?
bx >
bx =
bx <
bx ;
bx :
b10011 9
bx 8
bx 7
bx 6
bx 5
bx 4
03
bx 2
01
bx 0
bx /
bx .
b1000000000000 -
bx ,
bx +
bx *
bx )
bx (
x'
b10011 &
bx %
b0 $
b0 #
1"
0!
$end
#35
xl
x1
b0 7
b0 ""
xH
b0 J
b0 s
xi
b0 5
b0 y
b0 {
b0 8
b0 x
b0 :
b0 w
b0 u
0C
0D
bx G
bx t
0E
1F
0B
0A
1@
b10011 r
b1000 j
bx f
bx }
xh
0M
0L
b0 Q
0N
0'
0P
0S
b0 R
xZ
xY
xX
bx U
xV
x[
x\
xa
bx c
bx b
bx ^
bx `
bx _
bx W
bx T
bx m
bx ]
b10011 d
b10011 q
b0 e
b100 #
b100 $
b100 k
b100 $"
1!
#40
0!
#45
0H
0l
b0 <
0i
01
0Z
0Y
0X
b0 U
0V
0[
0\
0a
b0 c
b0 b
b0 ^
b0 `
b0 _
b0 W
b0 T
b0 m
b0 ]
xM
xL
bx Q
xN
x'
xP
xS
bx R
b0 f
b0 }
0h
1!
#50
0!
#55
bx ?
bx p
bx <
bx .
bx n
bx >
b0 I
b0 o
b1100 j
bx f
bx }
xh
0M
0L
b0 Q
0N
0'
0P
0S
b0 R
bx U
1V
1a
bx c
bx `
b100 e
b1000 #
b1000 $
b1000 k
b1000 $"
1!
#60
0!
#65
b0 <
b10000 j
b1000 e
b1100 #
b1100 $
b1100 k
b1100 $"
bx _
b100 ]
1S
b0 f
b0 }
0h
1!
#70
0!
#75
b0 ?
b0 p
b0 .
b0 n
b0 >
b10100 j
1h
b100 Q
b0 _
b1000 ]
b1100 e
b10000 #
b10000 $
b10000 k
b10000 $"
1!
#80
0!
#85
b11000 j
b0 %
b0 *
b0 2
b10000 e
b10100 #
b10100 $
b10100 k
b10100 $"
b1100 ]
b1000 Q
b0 )
b0 ,
b0 /
b0 K
1!
#90
0!
#95
b11100 j
b1000100110111 &
b1000100110111 9
b1000100110111 %"
b0 g
b0 ~
b1100 Q
b10000 ]
b10100 e
b11000 #
b11000 $
b11000 k
b11000 $"
1!
#100
0!
#105
b0 ;
b0 6
b0 !"
b1011 J
b1011 s
b0 4
b0 z
b0 |
bx G
bx t
b1000000000000 :
b1000000000000 w
b0 5
b0 y
b0 {
b10 8
b10 x
bx u
1F
1@
b110111 r
b10000000000000010000000100010011 &
b10000000000000010000000100010011 9
b10000000000000010000000100010011 %"
b100000 j
b1000100110111 d
b1000100110111 q
b11000 e
b11100 #
b11100 $
b11100 k
b11100 $"
b10100 ]
b10000 Q
1!
#110
0!
#115
bx ;
bx 6
bx !"
b0 =
b1000000000000 ?
b1000000000000 p
b0 J
b0 s
b1000000000000 I
b1000000000000 o
b0 u
bx G
bx t
b11111111111111111111100000000000 :
b11111111111111111111100000000000 w
bx 4
bx z
bx |
b10 5
b10 y
b10 {
b10 8
b10 x
1F
1@
b10011 r
b100100 j
b100010000000000000011101111 &
b100010000000000000011101111 9
b100010000000000000011101111 %"
b10100 Q
b0 c
b10 ^
b0 `
b1000000000000 W
b1011 T
b1011 m
b11000 ]
b10000000000000010000000100010011 d
b10000000000000010000000100010011 q
b11100 e
b100000 #
b100000 $
b100000 k
b100000 $"
1!
#120
0!
#125
b100000000000 ?
b100000000000 p
bx <
b1000000000000 .
b1000000000000 n
b1000000000000 >
bx 7
bx ""
bx J
bx s
bx =
1D
bx G
bx t
b1000100 :
b1000100 w
bx 5
bx y
bx {
b1 8
b1 x
bx u
1F
1@
b1101111 r
b1100010000000010010011 &
b1100010000000010010011 9
b1100010000000010010011 %"
b11111111111111111111100000000000 I
b11111111111111111111100000000000 o
b101000 j
b100010000000000000011101111 d
b100010000000000000011101111 q
b100000 e
b100100 #
b100100 $
b100100 k
b100100 $"
bx c
b10 b
bx `
b11111111111111111111100000000000 W
b0 T
b0 m
b11100 ]
b11000 Q
b0 (
b0 +
b0 0
b0 O
b10 R
b1000000000000 )
b1000000000000 ,
b1000000000000 /
b1000000000000 K
1!
#130
0!
#135
b1000000000000 <
b0 7
b0 ""
b0 J
b0 s
bx .
bx n
bx >
1i
b1000100 I
b1000100 o
b10 5
b10 y
b10 {
b0 u
0D
bx G
bx t
b11 :
b11 w
b1 8
b1 x
1F
1@
b10011 r
b1100100 j
b11000101000001000010011 &
b11000101000001000010011 9
b11000101000001000010011 %"
b1000000000000 g
b1000000000000 ~
b10 f
b10 }
b11100 Q
bx (
bx +
bx 0
bx O
b100000000000 )
b100000000000 ,
b100000000000 /
b100000000000 K
1Y
bx b
b1 ^
bx _
b1000100 W
bx T
bx m
b100000 ]
b1100010000000010010011 d
b1100010000000010010011 q
b100100 e
b101000 #
b101000 $
b101000 k
b101000 $"
1!
#140
0!
#145
b0 ?
b0 p
b0 .
b0 n
b0 >
b0 =
b0 7
b0 ""
bx G
bx t
b0 :
b0 w
b0 5
b0 y
b0 {
b0 8
b0 x
b0 u
1F
1@
b11111110000000010000000100010011 &
b11111110000000010000000100010011 9
b11111110000000010000000100010011 %"
0i
b0 I
b0 o
b1101000 j
b0 <
b10011 d
b10011 q
b101000 e
b1100100 #
b1100100 $
b1100100 k
b1100100 $"
0Y
b0 U
0V
0a
b0 c
b0 b
b0 ^
b0 `
b0 _
b0 W
b0 T
b0 m
b0 ]
1L
b100000 Q
b1 R
b100000000000 g
b100000000000 ~
1!
#150
0!
#155
b100000000000 <
b100000000000 7
b100000000000 ""
bx =
bx G
bx t
b11111111111111111111111111100000 :
b11111111111111111111111111100000 w
b10 5
b10 y
b10 {
b10 8
b10 x
b0 u
1F
1@
b1101100 j
b100010010111000100011 &
b100010010111000100011 9
b100010010111000100011 %"
b100100 g
b100100 ~
b1 f
b1 }
0L
b0 Q
0S
b0 (
b0 +
b0 0
b0 O
b0 R
b0 )
b0 ,
b0 /
b0 K
bx U
1V
1a
bx c
bx `
b101000 ]
b11111110000000010000000100010011 d
b11111110000000010000000100010011 q
b1100100 e
b1101000 #
b1101000 $
b1101000 k
b1101000 $"
1!
#160
0!
